Workbook

Sheet Май 26
A1: Дата | B1: Ответственный | C1: Клиент | D1: Статус обращения | E1: Срок решения и комментарий | F1: Решение (ссылка на тикет/ссылка на документацию) | G1: Обращение клиента | H1: Время | I1: Статус внесения обращения в Obsidian | J1: Ссылка на Merge Request
A2: 46143 | B2: Мишина Анна | H2: 9:00-10:00
B3: Мишина Анна | H3: 10:00-11:00
B4: Мишина Анна | H4: 11:00-12:00
B5: Мишина Анна | H5: 12:00-13:00
B6: Мишина Анна | H6: 13:00-14:00
B7: Мишина Анна | H7: 14:00-15:00
B8: Мишина Анна | H8: 15:00-16:00
B9: Мишина Анна | H9: 16:00-17:00
B10: Мишина Анна | H10: 17:00-18:00
B11: Мишина Анна | H11: 18:00-19:00
B12: Мишина Анна | H12: 19:00-20:00
B13: Мишина Анна | H13: 20:00-21:00
B14: Мишина Анна | H14: 21:00-22:00
B15: Мишина Анна | H15: 22:00-23:00
A16: 46144 | B16: Мишина Анна | H16: 9:00-10:00
B17: Мишина Анна | H17: 10:00-11:00
B18: Мишина Анна | H18: 11:00-12:00
B19: Мишина Анна | H19: 12:00-13:00
B20: Мишина Анна | H20: 13:00-14:00
B21: Мишина Анна | H21: 14:00-15:00
B22: Мишина Анна | H22: 15:00-16:00
B23: Мишина Анна | H23: 16:00-17:00
B24: Мишина Анна | H24: 17:00-18:00
B25: Мишина Анна | H25: 18:00-19:00
B26: Мишина Анна | H26: 19:00-20:00
B27: Мишина Анна | H27: 20:00-21:00
B28: Мишина Анна | H28: 21:00-22:00
B29: Мишина Анна | H29: 22:00-23:00
A30: 46145 | B30: Мишина Анна | H30: 9:00-10:00
B31: Мишина Анна | H31: 10:00-11:00
B32: Мишина Анна | H32: 11:00-12:00
B33: Мишина Анна | H33: 12:00-13:00
B34: Мишина Анна | H34: 13:00-14:00
B35: Мишина Анна | H35: 14:00-15:00
B36: Мишина Анна | H36: 15:00-16:00
B37: Мишина Анна | H37: 16:00-17:00
B38: Мишина Анна | H38: 17:00-18:00
B39: Мишина Анна | H39: 18:00-19:00
B40: Мишина Анна | H40: 19:00-20:00
B41: Мишина Анна | H41: 20:00-21:00
B42: Мишина Анна | H42: 21:00-22:00
B43: Мишина Анна | H43: 22:00-23:00
A44: 46146 | B44: Червякова Ольга | H44: 9:00-10:00
B45: Червякова Ольга | H45: 10:00-11:00
B46: Червякова Ольга | H46: 11:00-12:00
B47: Червякова Ольга | H47: 12:00-13:00
B48: Червякова Ольга | H48: 13:00-14:00
B49: Червякова Ольга | H49: 14:00-15:00
B50: Червякова Ольга | H50: 15:00-16:00
B51: Червякова Ольга | H51: 16:00-17:00
B52: Червякова Ольга | H52: 17:00-18:00
B53: Червякова Ольга | H53: 18:00-19:00
B54: Червякова Ольга | H54: 19:00-20:00
B55: Червякова Ольга | H55: 20:00-21:00
B56: Червякова Ольга | H56: 21:00-22:00
B57: Червякова Ольга | H57: 22:00-23:00
A58: 46147 | B58: Червякова Ольга | H58: 9:00-10:00
B59: Червякова Ольга | H59: 10:00-11:00
B60: Червякова Ольга | H60: 11:00-12:00
B61: Червякова Ольга | H61: 12:00-13:00
B62: Червякова Ольга | H62: 13:00-14:00
B63: Червякова Ольга | H63: 14:00-15:00
B64: Червякова Ольга | H64: 15:00-16:00
B65: Червякова Ольга | H65: 16:00-17:00
B66: Червякова Ольга | H66: 17:00-18:00
B67: Червякова Ольга | H67: 18:00-19:00
B68: Червякова Ольга | H68: 19:00-20:00
B69: Червякова Ольга | H69: 20:00-21:00
B70: Червякова Ольга | H70: 21:00-22:00
B71: Червякова Ольга | H71: 22:00-23:00
A72: 46148 | B72: Червякова Ольга | H72: 9:00-10:00
B73: Червякова Ольга | H73: 10:00-11:00
B74: Червякова Ольга | H74: 11:00-12:00
B75: Червякова Ольга | H75: 12:00-13:00
B76: Червякова Ольга | H76: 13:00-14:00
B77: Червякова Ольга | H77: 14:00-15:00
B78: Червякова Ольга | H78: 15:00-16:00
B79: Червякова Ольга | H79: 16:00-17:00
B80: Червякова Ольга | H80: 17:00-18:00
B81: Червякова Ольга | H81: 18:00-19:00
B82: Червякова Ольга | H82: 19:00-20:00
B83: Мишина Анна | H83: 20:00-21:00
B84: Мишина Анна | H84: 21:00-22:00
B85: Мишина Анна | H85: 22:00-23:00
A86: 46149 | B86: Червякова Ольга | H86: 9:00-10:00
B87: Червякова Ольга | H87: 10:00-11:00
B88: Червякова Ольга | H88: 11:00-12:00
B89: Червякова Ольга | H89: 12:00-13:00
B90: Червякова Ольга | H90: 13:00-14:00
B91: Червякова Ольга | H91: 14:00-15:00
B92: Червякова Ольга | H92: 15:00-16:00
B93: Червякова Ольга | H93: 16:00-17:00
B94: Червякова Ольга | H94: 17:00-18:00
B95: Червякова Ольга | H95: 18:00-19:00
B96: Червякова Ольга | H96: 19:00-20:00
B97: Червякова Ольга | H97: 20:00-21:00
B98: Червякова Ольга | H98: 21:00-22:00
B99: Червякова Ольга | H99: 22:00-23:00
A100: 46150 | B100: Мишина Анна | H100: 9:00-10:00
...

Sheet Информация
A2: Статус по занятости членов команды для поиска замены
A3: смогу
A4: возможно смогу
A5: не смогу
A8: Клиент | B8: Количество обращений

Sheet ТИКЕТЫ В РАБОТЕ
A1: =IFERROR(__xludf.DUMMYFUNCTION("QUERY({ 'Июль 25'!A:H; 'Июнь 25'!A:H; 'Май 25'!A:H; 'Апрель 25'!A:H; 'Март 25'!A:H; 'Февраль 25'!A:H; 'Январь 25'!A:H; 'Декабрь 24'!A:H; 'Ноябрь 24'!A:H; 'Октябрь 24'!A:H; 'Сентябрь 24'!A:H; 'Июнь 24'!A:H; 'Июль 24'!A:H; 'Авгус"&"т 24'!A:H; 'Май 24'!A:H; 'Апрель 24'!A:H; 'Март 24'!A:H }, ""select Col1, Col2, Col3, Col4, Col5, Col6, Col7, Col8 where Col4 = 'Создан тикет' OR Col4 = 'В работе'"", 1)"),"") | B1: =IFERROR(__xludf.DUMMYFUNCTION("""COMPUTED_VALUE"""),"Ответственный") -> Ответственный | C1: =IFERROR(__xludf.DUMMYFUNCTION("""COMPUTED_VALUE"""),"Клиент") -> Клиент | D1: =IFERROR(__xludf.DUMMYFUNCTION("""COMPUTED_VALUE"""),"Статус обращения") -> Статус обращения | E1: =IFERROR(__xludf.DUMMYFUNCTION("""COMPUTED_VALUE"""),"Срок решения и комментарий") -> Срок решения и комментарий | F1: =IFERROR(__xludf.DUMMYFUNCTION("""COMPUTED_VALUE"""),"Решение (ссылка на тикет/ссылка на документацию)") -> Решение (ссылка на тикет/ссылка на документацию) | G1: =IFERROR(__xludf.DUMMYFUNCTION("""COMPUTED_VALUE"""),"Обращение клиента") -> Обращение клиента | H1: =IFERROR(__xludf.DUMMYFUNCTION("""COMPUTED_VALUE"""),"Время") -> Время
B2: =IFERROR(__xludf.DUMMYFUNCTION("""COMPUTED_VALUE"""),"Червякова Ольга") -> Червякова Ольга | C2: =IFERROR(__xludf.DUMMYFUNCTION("""COMPUTED_VALUE"""),"КХЛ") -> КХЛ | D2: =IFERROR(__xludf.DUMMYFUNCTION("""COMPUTED_VALUE"""),"Создан тикет") -> Создан тикет | G2: =IFERROR(__xludf.DUMMYFUNCTION("""COMPUTED_VALUE"""),"Коллеги, заметил один момент на вебкастере. Через поиск хочу найти все голы Виноградова за сезон 24/25") -> Коллеги, заметил один момент на вебкастере. Через поиск хочу найти все голы Виноградова за сезон 24/25 | H2: =IFERROR(__xludf.DUMMYFUNCTION("""COMPUTED_VALUE"""),"13:00-14:00") -> 13:00-14:00
B3: =IFERROR(__xludf.DUMMYFUNCTION("""COMPUTED_VALUE"""),"Червякова Ольга") -> Червякова Ольга | C3: =IFERROR(__xludf.DUMMYFUNCTION("""COMPUTED_VALUE"""),"RDS") -> RDS | D3: =IFERROR(__xludf.DUMMYFUNCTION("""COMPUTED_VALUE"""),"В работе") -> В работе | G3: =IFERROR(__xludf.DUMMYFUNCTION("""COMPUTED_VALUE"""),"Коллеги, добрый день! Посмотрите, пожалуйста, запрос от пользователя: Плеер нормально работает только в режиме окна, а в полноэкранном режиме картинка дёргается так, что невозможно смотреть. Подскажите, что можно ответить?") -> Коллеги, добрый день! Посмотрите, пожалуйста, запрос от пользователя: Плеер нормально работает только в режиме окна, а в полноэкранном режиме картинка дёргается так, что невозможно смотреть. Подскажите, что можно ответить? | H3: =IFERROR(__xludf.DUMMYFUNCTION("""COMPUTED_VALUE"""),"16:00-17:00") -> 16:00-17:00
B4: =IFERROR(__xludf.DUMMYFUNCTION("""COMPUTED_VALUE"""),"Червякова Ольга") -> Червякова Ольга | C4: =IFERROR(__xludf.DUMMYFUNCTION("""COMPUTED_VALUE"""),"МатчТВ") -> МатчТВ | D4: =IFERROR(__xludf.DUMMYFUNCTION("""COMPUTED_VALUE"""),"В работе") -> В работе | G4: =IFERROR(__xludf.DUMMYFUNCTION("""COMPUTED_VALUE"""),"Здравствуйте. Коллеги, проблема с загрузкой файла по ссылке. Загружаю: https://fc.gpm-match.ru/index.php/s/PEF86rCfTb5Qyw4 Получаю результат: https://video.matchtv.ru/client/events/1279141") -> Здравствуйте. Коллеги, проблема с загрузкой файла по ссылке. Загружаю: https://fc.gpm-match.ru/index.php/s/PEF86rCfTb5Qyw4 Получаю результат: https://video.matchtv.ru/client/events/1279141 | H4: =IFERROR(__xludf.DUMMYFUNCTION("""COMPUTED_VALUE"""),"18:00-19:00") -> 18:00-19:00
B5: =IFERROR(__xludf.DUMMYFUNCTION("""COMPUTED_VALUE"""),"Червякова Ольга") -> Червякова Ольга | C5: =IFERROR(__xludf.DUMMYFUNCTION("""COMPUTED_VALUE"""),"МатчТВ") -> МатчТВ | D5: =IFERROR(__xludf.DUMMYFUNCTION("""COMPUTED_VALUE"""),"В работе") -> В работе | G5: =IFERROR(__xludf.DUMMYFUNCTION("""COMPUTED_VALUE"""),"Добрый день. Установка «заглушки» на дополнительные камеры РПЛ, сломало отображение доп. камер - бесконечное ожидание вместо «заглушки».") -> Добрый день. Установка «заглушки» на дополнительные камеры РПЛ, сломало отображение доп. камер - бесконечное ожидание вместо «заглушки». | H5: =IFERROR(__xludf.DUMMYFUNCTION("""COMPUTED_VALUE"""),"16:00-17:00") -> 16:00-17:00
B6: =IFERROR(__xludf.DUMMYFUNCTION("""COMPUTED_VALUE"""),"Толкачев Егор") -> Толкачев Егор | C6: =IFERROR(__xludf.DUMMYFUNCTION("""COMPUTED_VALUE"""),"Restream") -> Restream | D6: =IFERROR(__xludf.DUMMYFUNCTION("""COMPUTED_VALUE"""),"В работе") -> В работе | G6: =IFERROR(__xludf.DUMMYFUNCTION("""COMPUTED_VALUE"""),"Здравствуйте, продолжает скакать картинка") -> Здравствуйте, продолжает скакать картинка | H6: =IFERROR(__xludf.DUMMYFUNCTION("""COMPUTED_VALUE"""),"19:00-20:00") -> 19:00-20:00
B7: =IFERROR(__xludf.DUMMYFUNCTION("""COMPUTED_VALUE"""),"Алексеева Александра") -> Алексеева Александра | C7: =IFERROR(__xludf.DUMMYFUNCTION("""COMPUTED_VALUE"""),"ТВСтарт") -> ТВСтарт | D7: =IFERROR(__xludf.DUMMYFUNCTION("""COMPUTED_VALUE"""),"Создан тикет") -> Создан тикет | F7: =IFERROR(__xludf.DUMMYFUNCTION("""COMPUTED_VALUE"""),"https://rdm.inventos.ru/issues/159051") -> https://rdm.inventos.ru/issues/159051 | G7: =IFERROR(__xludf.DUMMYFUNCTION("""COMPUTED_VALUE"""),"Добрый день. Как там наш сервер поживает, скоро запустим?") -> Добрый день. Как там наш сервер поживает, скоро запустим? | H7: =IFERROR(__xludf.DUMMYFUNCTION("""COMPUTED_VALUE"""),"12:00-13:00") -> 12:00-13:00
B8: =IFERROR(__xludf.DUMMYFUNCTION("""COMPUTED_VALUE"""),"Алексеева Александра") -> Алексеева Александра | C8: =IFERROR(__xludf.DUMMYFUNCTION("""COMPUTED_VALUE"""),"ЛигаВТБ") -> ЛигаВТБ | D8: =IFERROR(__xludf.DUMMYFUNCTION("""COMPUTED_VALUE"""),"Создан тикет") -> Создан тикет | F8: =IFERROR(__xludf.DUMMYFUNCTION("""COMPUTED_VALUE"""),"https://rdm.inventos.ru/issues/160903") -> https://rdm.inventos.ru/issues/160903 | G8: =IFERROR(__xludf.DUMMYFUNCTION("""COMPUTED_VALUE"""),"Виталий Брагин, [10 июня 2025 г., 10:52:26]: Здравствуйте. Давайте отключим совсем сервер ВТБ SDI 5,6,7,8 эти каналы мы переведём на новый сервер, они нам не понадобятся летом. Хотя нет. эти каналы разбросаны по разным серверам. Лучше отключим сервер 1,"&"2,3,4 совсем и переместим каналы на новый сервер. Сервер мы получается возвращаем вам.") -> Виталий Брагин, [10 июня 2025 г., 10:52:26]: Здравствуйте. Давайте отключим совсем сервер ВТБ SDI 5,6,7,8 эти каналы мы переведём на новый сервер, они нам не понадобятся летом. Хотя нет. эти каналы разбросаны по разным серверам. Лучше отключим сервер 1,2,3,4 совсем и переместим каналы на новый сервер. Сервер мы получается возвращаем вам. | H8: =IFERROR(__xludf.DUMMYFUNCTION("""COMPUTED_VALUE"""),"10:00-11:00") -> 10:00-11:00
B9: =IFERROR(__xludf.DUMMYFUNCTION("""COMPUTED_VALUE"""),"Толкачев Егор") -> Толкачев Егор | C9: =IFERROR(__xludf.DUMMYFUNCTION("""COMPUTED_VALUE"""),"Restream") -> Restream | D9: =IFERROR(__xludf.DUMMYFUNCTION("""COMPUTED_VALUE"""),"Создан тикет") -> Создан тикет | F9: =IFERROR(__xludf.DUMMYFUNCTION("""COMPUTED_VALUE"""),"https://rdm.inventos.ru/issues/161135") -> https://rdm.inventos.ru/issues/161135 | G9: =IFERROR(__xludf.DUMMYFUNCTION("""COMPUTED_VALUE"""),"Добрый вечер! Почему то вчера и сегодня в вечернее время трансляция приходит на restream, но в ВК вобще не пошла а на Ютюб пошла минут через 8 после начала эфира") -> Добрый вечер! Почему то вчера и сегодня в вечернее время трансляция приходит на restream, но в ВК вобще не пошла а на Ютюб пошла минут через 8 после начала эфира | H9: =IFERROR(__xludf.DUMMYFUNCTION("""COMPUTED_VALUE"""),"20:00-21:00") -> 20:00-21:00
B10: =IFERROR(__xludf.DUMMYFUNCTION("""COMPUTED_VALUE"""),"Алексеева Александра") -> Алексеева Александра | C10: =IFERROR(__xludf.DUMMYFUNCTION("""COMPUTED_VALUE"""),"ЛигаВТБ") -> ЛигаВТБ | D10: =IFERROR(__xludf.DUMMYFUNCTION("""COMPUTED_VALUE"""),"Создан тикет") -> Создан тикет | E10: =IFERROR(__xludf.DUMMYFUNCTION("""COMPUTED_VALUE"""),"Костя ответил") -> Костя ответил | F10: =IFERROR(__xludf.DUMMYFUNCTION("""COMPUTED_VALUE"""),"https://rdm.inventos.ru/issues/160903") -> https://rdm.inventos.ru/issues/160903 | G10: =IFERROR(__xludf.DUMMYFUNCTION("""COMPUTED_VALUE"""),"Здравствуйте. Подскажите, как проходит процесс переноса данный с сервера ВТБ ?") -> Здравствуйте. Подскажите, как проходит процесс переноса данный с сервера ВТБ ? | H10: =IFERROR(__xludf.DUMMYFUNCTION("""COMPUTED_VALUE"""),"13:00-14:00") -> 13:00-14:00
B11: =IFERROR(__xludf.DUMMYFUNCTION("""COMPUTED_VALUE"""),"Алексеева Александра") -> Алексеева Александра | C11: =IFERROR(__xludf.DUMMYFUNCTION("""COMPUTED_VALUE"""),"МатчТВ") -> МатчТВ | D11: =IFERROR(__xludf.DUMMYFUNCTION("""COMPUTED_VALUE"""),"Создан тикет") -> Создан тикет | F11: =IFERROR(__xludf.DUMMYFUNCTION("""COMPUTED_VALUE"""),"https://rdm.inventos.ru/issues/161279") -> https://rdm.inventos.ru/issues/161279 | G11: =IFERROR(__xludf.DUMMYFUNCTION("""COMPUTED_VALUE"""),"Доброе утро! @small9rose помогите, пожалуйста, разобраться с пользователем. UID LNrTyVjmWnugex5DCELcMX https://api.video.matchtv.ru/client/users/2352501 Перехожу в транзакции, а там у данного пользователя почему то множество покупок и разные почты. Реа"&"льная покупка пользователя 23 июня 2025 в 10:25 https://api.video.matchtv.ru/admin/transactions?date_from=2024-08-31&transaction%5Bcustomer%5D=2352501") -> Доброе утро! @small9rose помогите, пожалуйста, разобраться с пользователем. UID LNrTyVjmWnugex5DCELcMX https://api.video.matchtv.ru/client/users/2352501 Перехожу в транзакции, а там у данного пользователя почему то множество покупок и разные почты. Реальная покупка пользователя 23 июня 2025 в 10:25 https://api.video.matchtv.ru/admin/transactions?date_from=2024-08-31&transaction%5Bcustomer%5D=2352501 | H11: =IFERROR(__xludf.DUMMYFUNCTION("""COMPUTED_VALUE"""),"10:00-11:00") -> 10:00-11:00
B12: =IFERROR(__xludf.DUMMYFUNCTION("""COMPUTED_VALUE"""),"Алексеева Александра") -> Алексеева Александра | C12: =IFERROR(__xludf.DUMMYFUNCTION("""COMPUTED_VALUE"""),"МатчТВ") -> МатчТВ | D12: =IFERROR(__xludf.DUMMYFUNCTION("""COMPUTED_VALUE"""),"Создан тикет") -> Создан тикет | F12: =IFERROR(__xludf.DUMMYFUNCTION("""COMPUTED_VALUE"""),"https://rdm.inventos.ru/issues/161291") -> https://rdm.inventos.ru/issues/161291 | G12: =IFERROR(__xludf.DUMMYFUNCTION("""COMPUTED_VALUE"""),"@konyshevvvv @small9rose добрый день! Мы закончили снимать с публикации ролики и трансляции немецких футбольных турниров, на которые у нас истекли права. Можно начать очищать от них хранилище: Удалить все ролики и трансляции: У которых есть признак ""Т"&"урнир"": - Бундеслига (Германия); - Кубок Германии 2024-25; - Суперкубок Германии. 2024; - Суперкубок Германии. 2023; - Вторая Бундеслига 2024-25; - Вторая Бундеслига (Германия). У которых в поле ""Название"" есть сочетания: - Чемпионат Германии; - Чемп"&"ионата Германии; - Кубок Германии; - Кубка Германии; - Суперкубок Германии; - Суперкубка Германии; - Вторая Бундеслига; - Второй Бундеслиги.") -> @konyshevvvv @small9rose добрый день! Мы закончили снимать с публикации ролики и трансляции немецких футбольных турниров, на которые у нас истекли права. Можно начать очищать от них хранилище: Удалить все ролики и трансляции: У которых есть признак "Турнир": - Бундеслига (Германия); - Кубок Германии 2024-25; - Суперкубок Германии. 2024; - Суперкубок Германии. 2023; - Вторая Бундеслига 2024-25; - Вторая Бундеслига (Германия). У которых в поле "Название" есть сочетания: - Чемпионат Германии; - Чемпионата Германии; - Кубок Германии; - Кубка Германии; - Суперкубок Германии; - Суперкубка Германии; - Вторая Бундеслига; - Второй Бундеслиги. | H12: =IFERROR(__xludf.DUMMYFUNCTION("""COMPUTED_VALUE"""),"12:00-13:00") -> 12:00-13:00
B13: =IFERROR(__xludf.DUMMYFUNCTION("""COMPUTED_VALUE"""),"Толкачев Егор") -> Толкачев Егор | C13: =IFERROR(__xludf.DUMMYFUNCTION("""COMPUTED_VALUE"""),"Restream") -> Restream | D13: =IFERROR(__xludf.DUMMYFUNCTION("""COMPUTED_VALUE"""),"В работе") -> В работе | G13: =IFERROR(__xludf.DUMMYFUNCTION("""COMPUTED_VALUE"""),"Хочу сделать рестрим с тик тока. Скачал тик ток студию , но он не дает запускать, пишет что 180 дней не было эфира, как это исправить ?") -> Хочу сделать рестрим с тик тока. Скачал тик ток студию , но он не дает запускать, пишет что 180 дней не было эфира, как это исправить ? | H13: =IFERROR(__xludf.DUMMYFUNCTION("""COMPUTED_VALUE"""),"15:00-16:00") -> 15:00-16:00
B14: =IFERROR(__xludf.DUMMYFUNCTION("""COMPUTED_VALUE"""),"Щемелинин Владислав ") -> Щемелинин Владислав | C14: =IFERROR(__xludf.DUMMYFUNCTION("""COMPUTED_VALUE"""),"Restream") -> Restream | D14: =IFERROR(__xludf.DUMMYFUNCTION("""COMPUTED_VALUE"""),"Создан тикет") -> Создан тикет | E14: =IFERROR(__xludf.DUMMYFUNCTION("""COMPUTED_VALUE"""),"Передал Сегегину для решения") -> Передал Сегегину для решения | F14: =IFERROR(__xludf.DUMMYFUNCTION("""COMPUTED_VALUE"""),"https://rdm.inventos.ru/issues/160551") -> https://rdm.inventos.ru/issues/160551 | G14: =IFERROR(__xludf.DUMMYFUNCTION("""COMPUTED_VALUE"""),"Дергается картинка на стриме") -> Дергается картинка на стриме | H14: =IFERROR(__xludf.DUMMYFUNCTION("""COMPUTED_VALUE"""),"20:00-21:00") -> 20:00-21:00
A15: =IFERROR(__xludf.DUMMYFUNCTION("""COMPUTED_VALUE"""),45750) -> 45750 | B15: =IFERROR(__xludf.DUMMYFUNCTION("""COMPUTED_VALUE"""),"Алексеева Александра") -> Алексеева Александра | C15: =IFERROR(__xludf.DUMMYFUNCTION("""COMPUTED_VALUE"""),"Restream") -> Restream | D15: =IFERROR(__xludf.DUMMYFUNCTION("""COMPUTED_VALUE"""),"Создан тикет") -> Создан тикет | F15: =IFERROR(__xludf.DUMMYFUNCTION("""COMPUTED_VALUE"""),"https://rdm.inventos.ru/issues/156599") -> https://rdm.inventos.ru/issues/156599 | G15: =IFERROR(__xludf.DUMMYFUNCTION("""COMPUTED_VALUE"""),"ребята, привет. я все понимаю, но уже полмесяца чат толком не работает на стримах. можно все-таки узнать, когда будет обновление, которое эту проблему уже решит? трансляции проводить в таких условиях не комфортно ни нам, ни зрителям.") -> ребята, привет. я все понимаю, но уже полмесяца чат толком не работает на стримах. можно все-таки узнать, когда будет обновление, которое эту проблему уже решит? трансляции проводить в таких условиях не комфортно ни нам, ни зрителям. | H15: =IFERROR(__xludf.DUMMYFUNCTION("""COMPUTED_VALUE"""),"9:00-10:00") -> 9:00-10:00
A16: =IFERROR(__xludf.DUMMYFUNCTION("""COMPUTED_VALUE"""),45738) -> 45738 | B16: =IFERROR(__xludf.DUMMYFUNCTION("""COMPUTED_VALUE"""),"Алексеева Александра") -> Алексеева Александра | C16: =IFERROR(__xludf.DUMMYFUNCTION("""COMPUTED_VALUE"""),"Restream") -> Restream | D16: =IFERROR(__xludf.DUMMYFUNCTION("""COMPUTED_VALUE"""),"Создан тикет") -> Создан тикет | F16: =IFERROR(__xludf.DUMMYFUNCTION("""COMPUTED_VALUE"""),"https://rdm.inventos.ru/issues/156599 ") -> https://rdm.inventos.ru/issues/156599 | G16: =IFERROR(__xludf.DUMMYFUNCTION("""COMPUTED_VALUE"""),"Здравствуйте. Чат по-прежнему не собирает в себя сообщения самостоятельно. Приходится постоянно вручную обновлять кэш, чтобы сообщения прогружались") -> Здравствуйте. Чат по-прежнему не собирает в себя сообщения самостоятельно. Приходится постоянно вручную обновлять кэш, чтобы сообщения прогружались | H16: =IFERROR(__xludf.DUMMYFUNCTION("""COMPUTED_VALUE"""),"9:00-10:00") -> 9:00-10:00
B17: =IFERROR(__xludf.DUMMYFUNCTION("""COMPUTED_VALUE"""),"Алексеева Александра") -> Алексеева Александра | C17: =IFERROR(__xludf.DUMMYFUNCTION("""COMPUTED_VALUE"""),"Restream") -> Restream | D17: =IFERROR(__xludf.DUMMYFUNCTION("""COMPUTED_VALUE"""),"Создан тикет") -> Создан тикет | F17: =IFERROR(__xludf.DUMMYFUNCTION("""COMPUTED_VALUE"""),"https://rdm.inventos.ru/issues/156599") -> https://rdm.inventos.ru/issues/156599 | G17: =IFERROR(__xludf.DUMMYFUNCTION("""COMPUTED_VALUE"""),"добрый день, столкнулся с такой проблемой: сообщения из чатов не передаются в обс. то есть они попадают в сам чат рестрима, но не передаются на докпанель в обсе. уже перепробовал все возможное - от переустановки обс до чистки кэша и различных перезапусков"&". другие док панели работают корректно, например если выводить в док панель чат с твича. но чат с рестрима не работает ни в какую. может быть можете подсказать, как это можно поправить? возможно у кого уже была такая проблема :(") -> добрый день, столкнулся с такой проблемой: сообщения из чатов не передаются в обс. то есть они попадают в сам чат рестрима, но не передаются на докпанель в обсе. уже перепробовал все возможное - от переустановки обс до чистки кэша и различных перезапусков. другие док панели работают корректно, например если выводить в док панель чат с твича. но чат с рестрима не работает ни в какую. может быть можете подсказать, как это можно поправить? возможно у кого уже была такая проблема :( | H17: =IFERROR(__xludf.DUMMYFUNCTION("""COMPUTED_VALUE"""),"11:00-12:00") -> 11:00-12:00
B18: =IFERROR(__xludf.DUMMYFUNCTION("""COMPUTED_VALUE"""),"Тимохина Дарья ") -> Тимохина Дарья | C18: =IFERROR(__xludf.DUMMYFUNCTION("""COMPUTED_VALUE"""),"ТВСтарт") -> ТВСтарт | D18: =IFERROR(__xludf.DUMMYFUNCTION("""COMPUTED_VALUE"""),"Создан тикет") -> Создан тикет | E18: =IFERROR(__xludf.DUMMYFUNCTION("""COMPUTED_VALUE"""),"https://rdm.inventos.ru/issues/157723") -> https://rdm.inventos.ru/issues/157723 | F18: =IFERROR(__xludf.DUMMYFUNCTION("""COMPUTED_VALUE"""),"Была аналогичная ситуация уже, создала тикет, работы ведутся. ") -> Была аналогичная ситуация уже, создала тикет, работы ведутся. | G18: =IFERROR(__xludf.DUMMYFUNCTION("""COMPUTED_VALUE"""),"Вот ещё возьмите, пожалуйста, такую просьбу в работу? Мы удаляем контент из событий примерно раньше квартала к текущей дате. Сейчас открыл архив событий и в прошлом году все ивенты с неудалённым контентом. Можете посмотреть, разобраться? У нас было такое "&"уже, в списке отображается наличие контента, в ивент заходишь - там пусто.") -> Вот ещё возьмите, пожалуйста, такую просьбу в работу? Мы удаляем контент из событий примерно раньше квартала к текущей дате. Сейчас открыл архив событий и в прошлом году все ивенты с неудалённым контентом. Можете посмотреть, разобраться? У нас было такое уже, в списке отображается наличие контента, в ивент заходишь - там пусто. | H18: =IFERROR(__xludf.DUMMYFUNCTION("""COMPUTED_VALUE"""),"14:00-15:00") -> 14:00-15:00
B19: =IFERROR(__xludf.DUMMYFUNCTION("""COMPUTED_VALUE"""),"Червякова Ольга") -> Червякова Ольга | C19: =IFERROR(__xludf.DUMMYFUNCTION("""COMPUTED_VALUE"""),"Restream") -> Restream | D19: =IFERROR(__xludf.DUMMYFUNCTION("""COMPUTED_VALUE"""),"В работе") -> В работе | E19: =IFERROR(__xludf.DUMMYFUNCTION("""COMPUTED_VALUE"""),"тикет на тестировании") -> тикет на тестировании | G19: =IFERROR(__xludf.DUMMYFUNCTION("""COMPUTED_VALUE"""),"Ребята, привет. У нас стрим опять начал пропускать сообщения с вк и твича") -> Ребята, привет. У нас стрим опять начал пропускать сообщения с вк и твича | H19: =IFERROR(__xludf.DUMMYFUNCTION("""COMPUTED_VALUE"""),"20:00-21:00") -> 20:00-21:00
B20: =IFERROR(__xludf.DUMMYFUNCTION("""COMPUTED_VALUE"""),"Алексеева Александра") -> Алексеева Александра | C20: =IFERROR(__xludf.DUMMYFUNCTION("""COMPUTED_VALUE"""),"МОНИКИ") -> МОНИКИ | D20: =IFERROR(__xludf.DUMMYFUNCTION("""COMPUTED_VALUE"""),"Создан тикет") -> Создан тикет | F20: =IFERROR(__xludf.DUMMYFUNCTION("""COMPUTED_VALUE"""),"https://rdm.inventos.ru/issues/157875") -> https://rdm.inventos.ru/issues/157875 | G20: =IFERROR(__xludf.DUMMYFUNCTION("""COMPUTED_VALUE""")," Доброе утро коллеги! https://wbnr.su:50443/rooms?meet=cf81c5e8-4966-44f0-85ea-f02769477297 посмотрите лекцию подалуйста никто не может зайти") -> Доброе утро коллеги! https://wbnr.su:50443/rooms?meet=cf81c5e8-4966-44f0-85ea-f02769477297 посмотрите лекцию подалуйста никто не может зайти | H20: =IFERROR(__xludf.DUMMYFUNCTION("""COMPUTED_VALUE"""),"10:00-11:00") -> 10:00-11:00
B21: =IFERROR(__xludf.DUMMYFUNCTION("""COMPUTED_VALUE"""),"Алексеева Александра") -> Алексеева Александра | C21: =IFERROR(__xludf.DUMMYFUNCTION("""COMPUTED_VALUE"""),"МОНИКИ") -> МОНИКИ | D21: =IFERROR(__xludf.DUMMYFUNCTION("""COMPUTED_VALUE"""),"Создан тикет") -> Создан тикет | F21: =IFERROR(__xludf.DUMMYFUNCTION("""COMPUTED_VALUE"""),"https://rdm.inventos.ru/issues/157875") -> https://rdm.inventos.ru/issues/157875 | G21: =IFERROR(__xludf.DUMMYFUNCTION("""COMPUTED_VALUE"""),"Коллеги, лектора выкидывает с вебинара") -> Коллеги, лектора выкидывает с вебинара | H21: =IFERROR(__xludf.DUMMYFUNCTION("""COMPUTED_VALUE"""),"10:00-11:00") -> 10:00-11:00
B22: =IFERROR(__xludf.DUMMYFUNCTION("""COMPUTED_VALUE"""),"Алексеева Александра") -> Алексеева Александра | C22: =IFERROR(__xludf.DUMMYFUNCTION("""COMPUTED_VALUE"""),"МОНИКИ") -> МОНИКИ | D22: =IFERROR(__xludf.DUMMYFUNCTION("""COMPUTED_VALUE"""),"Создан тикет") -> Создан тикет | F22: =IFERROR(__xludf.DUMMYFUNCTION("""COMPUTED_VALUE"""),"https://rdm.inventos.ru/issues/157875") -> https://rdm.inventos.ru/issues/157875 | G22: =IFERROR(__xludf.DUMMYFUNCTION("""COMPUTED_VALUE"""),"Доброе утро! История повторилась вчерашняя") -> Доброе утро! История повторилась вчерашняя | H22: =IFERROR(__xludf.DUMMYFUNCTION("""COMPUTED_VALUE"""),"10:00-11:00") -> 10:00-11:00
A23: =IFERROR(__xludf.DUMMYFUNCTION("""COMPUTED_VALUE"""),45714) -> 45714 | B23: =IFERROR(__xludf.DUMMYFUNCTION("""COMPUTED_VALUE"""),"Алексеева Александра") -> Алексеева Александра | C23: =IFERROR(__xludf.DUMMYFUNCTION("""COMPUTED_VALUE"""),"МатчТВ") -> МатчТВ | D23: =IFERROR(__xludf.DUMMYFUNCTION("""COMPUTED_VALUE"""),"Создан тикет") -> Создан тикет | E23: =IFERROR(__xludf.DUMMYFUNCTION("""COMPUTED_VALUE"""),"https://rdm.inventos.ru/issues/157987") -> https://rdm.inventos.ru/issues/157987 | F23: =IFERROR(__xludf.DUMMYFUNCTION("""COMPUTED_VALUE"""),"https://mm.inventos.ru/inventos/pl/at4z7asgdbdk3kni7yfs6shhkw") -> https://mm.inventos.ru/inventos/pl/at4z7asgdbdk3kni7yfs6shhkw | G23: =IFERROR(__xludf.DUMMYFUNCTION("""COMPUTED_VALUE"""),"https://news.sportbox.ru/Vidy_sporta/Futbol/Evropejskie_chempionaty/Germaniya/Kubok_Germanii/spbvideo_NI2173002_clip_Arminija___Verder_Goly_video_Kubok_Germanii_Futbol Слишком долго осуществляется склейка и еще наблюдаются торможения в работе админки "&"в целом") -> https://news.sportbox.ru/Vidy_sporta/Futbol/Evropejskie_chempionaty/Germaniya/Kubok_Germanii/spbvideo_NI2173002_clip_Arminija___Verder_Goly_video_Kubok_Germanii_Futbol Слишком долго осуществляется склейка и еще наблюдаются торможения в работе админки в целом | H23: =IFERROR(__xludf.DUMMYFUNCTION("""COMPUTED_VALUE"""),"9:00-10:00") -> 9:00-10:00
B24: =IFERROR(__xludf.DUMMYFUNCTION("""COMPUTED_VALUE"""),"Алексеева Александра") -> Алексеева Александра | C24: =IFERROR(__xludf.DUMMYFUNCTION("""COMPUTED_VALUE"""),"Restream") -> Restream | D24: =IFERROR(__xludf.DUMMYFUNCTION("""COMPUTED_VALUE"""),"Создан тикет") -> Создан тикет | F24: =IFERROR(__xludf.DUMMYFUNCTION("""COMPUTED_VALUE"""),"https://rdm.inventos.ru/issues/156883 https://rdm.inventos.ru/issues/156587 https://rdm.inventos.ru/issues/156955") -> https://rdm.inventos.ru/issues/156883 https://rdm.inventos.ru/issues/156587 https://rdm.inventos.ru/issues/156955 | G24: =IFERROR(__xludf.DUMMYFUNCTION("""COMPUTED_VALUE"""),"Ошибка при авторизации на ютуб") -> Ошибка при авторизации на ютуб | H24: =IFERROR(__xludf.DUMMYFUNCTION("""COMPUTED_VALUE"""),"12:00-13:00") -> 12:00-13:00
B25: =IFERROR(__xludf.DUMMYFUNCTION("""COMPUTED_VALUE"""),"Алексеева Александра") -> Алексеева Александра | C25: =IFERROR(__xludf.DUMMYFUNCTION("""COMPUTED_VALUE"""),"Restream") -> Restream | D25: =IFERROR(__xludf.DUMMYFUNCTION("""COMPUTED_VALUE"""),"Создан тикет") -> Создан тикет | E25: =IFERROR(__xludf.DUMMYFUNCTION("""COMPUTED_VALUE"""),"Пользователь использует нашу платформу в качестве сбора сообщений, при этом пользователь не подае поток на нашу платформу. Благодаря этому случаю удалось найти баг: почему то мультичат собирает сообщения, но при этом на платформу не идет поток и не добавл"&"ены каналы. Этот баг обнаружили вместе с Сашей Серегиным. Ответ пользователю: ""Виджет чата будет работать корректно и собирать все сообщения только при транслировании потока на наш сервис. Если вы будете использовать только виджет, без отправки потока, т"&"о чат не будет работать корректно. Мы рекомендуем вам воспользоваться нашей платформой для рестрима потока на разные платформы.""") -> Пользователь использует нашу платформу в качестве сбора сообщений, при этом пользователь не подае поток на нашу платформу. Благодаря этому случаю удалось найти баг: почему то мультичат собирает сообщения, но при этом на платформу не идет поток и не добавлены каналы. Этот баг обнаружили вместе с Сашей Серегиным. Ответ пользователю: "Виджет чата будет работать корректно и собирать все сообщения только при транслировании потока на наш сервис. Если вы будете использовать только виджет, без отправки потока, то чат не будет работать корректно. Мы рекомендуем вам воспользоваться нашей платформой для рестрима потока на разные платформы." | F25: =IFERROR(__xludf.DUMMYFUNCTION("""COMPUTED_VALUE"""),"https://rdm.inventos.ru/issues/156883. https://rdm.inventos.ru/issues/156587. https://rdm.inventos.ru/issues/156955") -> https://rdm.inventos.ru/issues/156883. https://rdm.inventos.ru/issues/156587. https://rdm.inventos.ru/issues/156955 | G25: =IFERROR(__xludf.DUMMYFUNCTION("""COMPUTED_VALUE"""),"Добрый день.Не работает чат на ютубе, только на твич") -> Добрый день.Не работает чат на ютубе, только на твич | H25: =IFERROR(__xludf.DUMMYFUNCTION("""COMPUTED_VALUE"""),"13:00-14:00") -> 13:00-14:00
B26: =IFERROR(__xludf.DUMMYFUNCTION("""COMPUTED_VALUE"""),"Толкачев Егор") -> Толкачев Егор | C26: =IFERROR(__xludf.DUMMYFUNCTION("""COMPUTED_VALUE"""),"Restream") -> Restream | D26: =IFERROR(__xludf.DUMMYFUNCTION("""COMPUTED_VALUE"""),"В работе") -> В работе | G26: =IFERROR(__xludf.DUMMYFUNCTION("""COMPUTED_VALUE"""),"Ребят, привет. У нас чат сломался щас на стриме. Вообще не собирает сообщения. Я уже кеш сбрасывал. Ничего") -> Ребят, привет. У нас чат сломался щас на стриме. Вообще не собирает сообщения. Я уже кеш сбрасывал. Ничего | H26: =IFERROR(__xludf.DUMMYFUNCTION("""COMPUTED_VALUE"""),"20:00-21:00") -> 20:00-21:00
B27: =IFERROR(__xludf.DUMMYFUNCTION("""COMPUTED_VALUE"""),"Толкачев Егор") -> Толкачев Егор | C27: =IFERROR(__xludf.DUMMYFUNCTION("""COMPUTED_VALUE"""),"Restream") -> Restream | D27: =IFERROR(__xludf.DUMMYFUNCTION("""COMPUTED_VALUE"""),"В работе") -> В работе | G27: =IFERROR(__xludf.DUMMYFUNCTION("""COMPUTED_VALUE"""),"опять с ВК нет комментариев*") -> опять с ВК нет комментариев* | H27: =IFERROR(__xludf.DUMMYFUNCTION("""COMPUTED_VALUE"""),"19:00-20:00") -> 19:00-20:00
B28: =IFERROR(__xludf.DUMMYFUNCTION("""COMPUTED_VALUE"""),"Алексеева Александра") -> Алексеева Александра | C28: =IFERROR(__xludf.DUMMYFUNCTION("""COMPUTED_VALUE"""),"МатчТВ") -> МатчТВ | D28: =IFERROR(__xludf.DUMMYFUNCTION("""COMPUTED_VALUE"""),"Создан тикет") -> Создан тикет | F28: =IFERROR(__xludf.DUMMYFUNCTION("""COMPUTED_VALUE"""),"https://rdm.inventos.ru/issues/156703 https://rdm.inventos.ru/issues/156771 ") -> https://rdm.inventos.ru/issues/156703 https://rdm.inventos.ru/issues/156771 | G28: =IFERROR(__xludf.DUMMYFUNCTION("""COMPUTED_VALUE"""),"Всем привет! На планшетах, проверьте еще, пожалуйста. Возможно связанные проблемы. Получили обращение такое: Так как на айпаде нет официального приложения матч.ТВ, я использую Яндекс браузер. Перестала работать возможность просмотра записей трансляций"&" через этот браузер. Пишет, что трансляция использует функционал, который не поддерживает данный браузер. Пробовал сафари. Итог тот же. Браузер версия 24.12.4 от 2 января 2025 IpadOS 18.1.1 IPad 9го поколения.") -> Всем привет! На планшетах, проверьте еще, пожалуйста. Возможно связанные проблемы. Получили обращение такое: Так как на айпаде нет официального приложения матч.ТВ, я использую Яндекс браузер. Перестала работать возможность просмотра записей трансляций через этот браузер. Пишет, что трансляция использует функционал, который не поддерживает данный браузер. Пробовал сафари. Итог тот же. Браузер версия 24.12.4 от 2 января 2025 IpadOS 18.1.1 IPad 9го поколения. | H28: =IFERROR(__xludf.DUMMYFUNCTION("""COMPUTED_VALUE"""),"10:00-11:00") -> 10:00-11:00
B29: =IFERROR(__xludf.DUMMYFUNCTION("""COMPUTED_VALUE"""),"Червякова Ольга") -> Червякова Ольга | C29: =IFERROR(__xludf.DUMMYFUNCTION("""COMPUTED_VALUE"""),"МатчТВ") -> МатчТВ | D29: =IFERROR(__xludf.DUMMYFUNCTION("""COMPUTED_VALUE"""),"В работе") -> В работе | F29: =IFERROR(__xludf.DUMMYFUNCTION("""COMPUTED_VALUE"""),"Константин проверяет на LG в офисе") -> Константин проверяет на LG в офисе | G29: =IFERROR(__xludf.DUMMYFUNCTION("""COMPUTED_VALUE"""),"Добрый вечер! У пользователя на канале Футбол1, трансляция идет с прерыванием. Другие футбольные каналы работают нормально. Смотрит на смарт тв. IP 194.32.230.128") -> Добрый вечер! У пользователя на канале Футбол1, трансляция идет с прерыванием. Другие футбольные каналы работают нормально. Смотрит на смарт тв. IP 194.32.230.128 | H29: =IFERROR(__xludf.DUMMYFUNCTION("""COMPUTED_VALUE"""),"20:00-21:00") -> 20:00-21:00
B30: =IFERROR(__xludf.DUMMYFUNCTION("""COMPUTED_VALUE"""),"Червякова Ольга") -> Червякова Ольга | C30: =IFERROR(__xludf.DUMMYFUNCTION("""COMPUTED_VALUE"""),"МатчТВ") -> МатчТВ | D30: =IFERROR(__xludf.DUMMYFUNCTION("""COMPUTED_VALUE"""),"В работе") -> В работе | G30: =IFERROR(__xludf.DUMMYFUNCTION("""COMPUTED_VALUE"""),"Добрый день! Пользователю недоступен просмотр канала Матч Премьер на сайте. 30 Jan 25 16:53:40 +0300 GeoIP country: RU GeoIP country nginx: RU GeoIP region nginx: MOW HTTP_USER_AGENT: Mozilla/5.0 (Linux; Android 10; K) AppleWebKit/537.36 (KHTML, like Geck"&"o) Chrome/131.0.6778.260 Mobile Safari/537.36 REMOTE_ADDR: 5.188.121.199 HTTP_X_FORWARDED_FOR: 185.107.136.0 IP-Z: 185.107.136.0 Proxied IP: 5.188.121.199 Network Family: common Current UID/SU: / HAS FLASH: false MSE: true") -> Добрый день! Пользователю недоступен просмотр канала Матч Премьер на сайте. 30 Jan 25 16:53:40 +0300 GeoIP country: RU GeoIP country nginx: RU GeoIP region nginx: MOW HTTP_USER_AGENT: Mozilla/5.0 (Linux; Android 10; K) AppleWebKit/537.36 (KHTML, like Gecko) Chrome/131.0.6778.260 Mobile Safari/537.36 REMOTE_ADDR: 5.188.121.199 HTTP_X_FORWARDED_FOR: 185.107.136.0 IP-Z: 185.107.136.0 Proxied IP: 5.188.121.199 Network Family: common Current UID/SU: / HAS FLASH: false MSE: true | H30: =IFERROR(__xludf.DUMMYFUNCTION("""COMPUTED_VALUE"""),"17:00-18:00") -> 17:00-18:00
B31: =IFERROR(__xludf.DUMMYFUNCTION("""COMPUTED_VALUE"""),"Тимохина Дарья ") -> Тимохина Дарья | C31: =IFERROR(__xludf.DUMMYFUNCTION("""COMPUTED_VALUE"""),"ТВСтарт") -> ТВСтарт | D31: =IFERROR(__xludf.DUMMYFUNCTION("""COMPUTED_VALUE"""),"Создан тикет") -> Создан тикет | G31: =IFERROR(__xludf.DUMMYFUNCTION("""COMPUTED_VALUE"""),"Добрый день! Описываю странное поведение в ЛК Вебкастера. При создании кода внедрения не работает кнопка Копировать, не копируется код в буфер. Она не работает только в типе ембеда Iframe, в других всё ок. Работаю в Опере, кеш чистил.") -> Добрый день! Описываю странное поведение в ЛК Вебкастера. При создании кода внедрения не работает кнопка Копировать, не копируется код в буфер. Она не работает только в типе ембеда Iframe, в других всё ок. Работаю в Опере, кеш чистил. | H31: =IFERROR(__xludf.DUMMYFUNCTION("""COMPUTED_VALUE"""),"15:00-16:00") -> 15:00-16:00
B32: =IFERROR(__xludf.DUMMYFUNCTION("""COMPUTED_VALUE"""),"Григорьев Дмитрий") -> Григорьев Дмитрий | C32: =IFERROR(__xludf.DUMMYFUNCTION("""COMPUTED_VALUE"""),"Restream") -> Restream | D32: =IFERROR(__xludf.DUMMYFUNCTION("""COMPUTED_VALUE"""),"Создан тикет") -> Создан тикет | F32: =IFERROR(__xludf.DUMMYFUNCTION("""COMPUTED_VALUE"""),"https://rdm.inventos.ru/issues/156163") -> https://rdm.inventos.ru/issues/156163 | G32: =IFERROR(__xludf.DUMMYFUNCTION("""COMPUTED_VALUE"""),"Здравствуйте, почему у меня сообщения в чате дублируются, можно исправить?") -> Здравствуйте, почему у меня сообщения в чате дублируются, можно исправить? | H32: =IFERROR(__xludf.DUMMYFUNCTION("""COMPUTED_VALUE"""),"13:00-14:00") -> 13:00-14:00
B33: =IFERROR(__xludf.DUMMYFUNCTION("""COMPUTED_VALUE"""),"Червякова Ольга") -> Червякова Ольга | C33: =IFERROR(__xludf.DUMMYFUNCTION("""COMPUTED_VALUE"""),"ТВСтарт") -> ТВСтарт | D33: =IFERROR(__xludf.DUMMYFUNCTION("""COMPUTED_VALUE"""),"Создан тикет") -> Создан тикет | F33: =IFERROR(__xludf.DUMMYFUNCTION("""COMPUTED_VALUE"""),"https://rdm.inventos.ru/issues/156475") -> https://rdm.inventos.ru/issues/156475 | G33: =IFERROR(__xludf.DUMMYFUNCTION("""COMPUTED_VALUE"""),"Добрый день. Размещаю видео на сервер. И пишет что обработка 130%. Это нормально?") -> Добрый день. Размещаю видео на сервер. И пишет что обработка 130%. Это нормально? | H33: =IFERROR(__xludf.DUMMYFUNCTION("""COMPUTED_VALUE"""),"14:00-15:00") -> 14:00-15:00
B34: =IFERROR(__xludf.DUMMYFUNCTION("""COMPUTED_VALUE"""),"Червякова Ольга") -> Червякова Ольга | C34: =IFERROR(__xludf.DUMMYFUNCTION("""COMPUTED_VALUE"""),"МатчТВ") -> МатчТВ | D34: =IFERROR(__xludf.DUMMYFUNCTION("""COMPUTED_VALUE"""),"Создан тикет") -> Создан тикет | F34: =IFERROR(__xludf.DUMMYFUNCTION("""COMPUTED_VALUE"""),"https://rdm.inventos.ru/issues/155107") -> https://rdm.inventos.ru/issues/155107 | G34: =IFERROR(__xludf.DUMMYFUNCTION("""COMPUTED_VALUE"""),"Добрый день. Коллеги, почему-то не получалось запустить трансляцию из нашей админки. Запускал трансляцию напрямую из вебкастера.") -> Добрый день. Коллеги, почему-то не получалось запустить трансляцию из нашей админки. Запускал трансляцию напрямую из вебкастера. | H34: =IFERROR(__xludf.DUMMYFUNCTION("""COMPUTED_VALUE"""),"15:00-16:00") -> 15:00-16:00
B35: =IFERROR(__xludf.DUMMYFUNCTION("""COMPUTED_VALUE"""),"Алексеева Александра") -> Алексеева Александра | C35: =IFERROR(__xludf.DUMMYFUNCTION("""COMPUTED_VALUE"""),"МатчТВ") -> МатчТВ | D35: =IFERROR(__xludf.DUMMYFUNCTION("""COMPUTED_VALUE"""),"Создан тикет") -> Создан тикет | F35: =IFERROR(__xludf.DUMMYFUNCTION("""COMPUTED_VALUE"""),"https://rdm.inventos.ru/issues/155131") -> https://rdm.inventos.ru/issues/155131 | G35: =IFERROR(__xludf.DUMMYFUNCTION("""COMPUTED_VALUE"""),"Коллеги, добрый день! Иногда сталкиваюсь с проблемой, что при раскрытии веб плеера у меня на какое-то время прогружаются элементы интерфейса плеера, а потом сам плеер. Выглядит странно. Давно эту проблему наблюдаю, но записать удалось только сейчас") -> Коллеги, добрый день! Иногда сталкиваюсь с проблемой, что при раскрытии веб плеера у меня на какое-то время прогружаются элементы интерфейса плеера, а потом сам плеер. Выглядит странно. Давно эту проблему наблюдаю, но записать удалось только сейчас | H35: =IFERROR(__xludf.DUMMYFUNCTION("""COMPUTED_VALUE"""),"11:00-12:00") -> 11:00-12:00
B36: =IFERROR(__xludf.DUMMYFUNCTION("""COMPUTED_VALUE"""),"Червякова Ольга") -> Червякова Ольга | C36: =IFERROR(__xludf.DUMMYFUNCTION("""COMPUTED_VALUE"""),"МатчТВ") -> МатчТВ | D36: =IFERROR(__xludf.DUMMYFUNCTION("""COMPUTED_VALUE"""),"Создан тикет") -> Создан тикет | F36: =IFERROR(__xludf.DUMMYFUNCTION("""COMPUTED_VALUE"""),"https://rdm.inventos.ru/issues/155467") -> https://rdm.inventos.ru/issues/155467 | G36: =IFERROR(__xludf.DUMMYFUNCTION("""COMPUTED_VALUE"""),"Здравствуйте https://news.sportbox.ru/node/2133588 Слишком долго грузится файл по ссылке в ноду уже минут 15 id 1227001") -> Здравствуйте https://news.sportbox.ru/node/2133588 Слишком долго грузится файл по ссылке в ноду уже минут 15 id 1227001 | H36: =IFERROR(__xludf.DUMMYFUNCTION("""COMPUTED_VALUE"""),"22:00-23:00") -> 22:00-23:00
B37: =IFERROR(__xludf.DUMMYFUNCTION("""COMPUTED_VALUE"""),"Тимохина Дарья ") -> Тимохина Дарья | C37: =IFERROR(__xludf.DUMMYFUNCTION("""COMPUTED_VALUE"""),"МатчТВ") -> МатчТВ | D37: =IFERROR(__xludf.DUMMYFUNCTION("""COMPUTED_VALUE"""),"Создан тикет") -> Создан тикет | F37: =IFERROR(__xludf.DUMMYFUNCTION("""COMPUTED_VALUE"""),"https://rdm.inventos.ru/issues/154931") -> https://rdm.inventos.ru/issues/154931 | G37: =IFERROR(__xludf.DUMMYFUNCTION("""COMPUTED_VALUE"""),"На остальных каналах тоже были рассыпания. Сейчас пересматриваем UFC, который был в субботу вечером: https://video.matchtv.ru/client/events/1217337") -> На остальных каналах тоже были рассыпания. Сейчас пересматриваем UFC, который был в субботу вечером: https://video.matchtv.ru/client/events/1217337 | H37: =IFERROR(__xludf.DUMMYFUNCTION("""COMPUTED_VALUE"""),"14:00-15:00") -> 14:00-15:00
B38: =IFERROR(__xludf.DUMMYFUNCTION("""COMPUTED_VALUE"""),"Червякова Ольга") -> Червякова Ольга | C38: =IFERROR(__xludf.DUMMYFUNCTION("""COMPUTED_VALUE"""),"МатчТВ") -> МатчТВ | D38: =IFERROR(__xludf.DUMMYFUNCTION("""COMPUTED_VALUE"""),"Создан тикет") -> Создан тикет | E38: =IFERROR(__xludf.DUMMYFUNCTION("""COMPUTED_VALUE"""),"Баг") -> Баг | G38: =IFERROR(__xludf.DUMMYFUNCTION("""COMPUTED_VALUE"""),"https://rdm.inventos.ru/issues/152223") -> https://rdm.inventos.ru/issues/152223 | H38: =IFERROR(__xludf.DUMMYFUNCTION("""COMPUTED_VALUE"""),"подскажите, пожалуйста, с чем может быть связана разная скорость запуска прямого эфира и разовой трансляции? сейчас, когда мы для подписчиков отключили пре-роллы, заметили, что любая разовая трансляция/обзор/хайлайт запускается моментально, а вот прямой э"&"фир запускается секунды через 4-5, а до этого крутится лоудер") -> подскажите, пожалуйста, с чем может быть связана разная скорость запуска прямого эфира и разовой трансляции? сейчас, когда мы для подписчиков отключили пре-роллы, заметили, что любая разовая трансляция/обзор/хайлайт запускается моментально, а вот прямой эфир запускается секунды через 4-5, а до этого крутится лоудер
B39: =IFERROR(__xludf.DUMMYFUNCTION("""COMPUTED_VALUE"""),"Курасов Павел") -> Курасов Павел | C39: =IFERROR(__xludf.DUMMYFUNCTION("""COMPUTED_VALUE"""),"Ifree") -> Ifree | D39: =IFERROR(__xludf.DUMMYFUNCTION("""COMPUTED_VALUE"""),"Создан тикет") -> Создан тикет | F39: =IFERROR(__xludf.DUMMYFUNCTION("""COMPUTED_VALUE"""),"https://rdm.inventos.ru/issues/152371") -> https://rdm.inventos.ru/issues/152371 | G39: =IFERROR(__xludf.DUMMYFUNCTION("""COMPUTED_VALUE"""),"Добрый день! Можете пожалуйста посмотреть это видео дважды выдало ошибку https://ifree.webcaster.pro/client/video_files/1089827") -> Добрый день! Можете пожалуйста посмотреть это видео дважды выдало ошибку https://ifree.webcaster.pro/client/video_files/1089827 | H39: =IFERROR(__xludf.DUMMYFUNCTION("""COMPUTED_VALUE"""),"10:00-11:00") -> 10:00-11:00
B40: =IFERROR(__xludf.DUMMYFUNCTION("""COMPUTED_VALUE"""),"Червякова Ольга") -> Червякова Ольга | C40: =IFERROR(__xludf.DUMMYFUNCTION("""COMPUTED_VALUE"""),"ТВСтарт") -> ТВСтарт | D40: =IFERROR(__xludf.DUMMYFUNCTION("""COMPUTED_VALUE"""),"Создан тикет") -> Создан тикет | F40: =IFERROR(__xludf.DUMMYFUNCTION("""COMPUTED_VALUE"""),"https://rdm.inventos.ru/issues/153355") -> https://rdm.inventos.ru/issues/153355 | G40: =IFERROR(__xludf.DUMMYFUNCTION("""COMPUTED_VALUE"""),"Ещё вопрос в админке лиги ВТб постоянно выскакивает окно, оно для чего и может его убрать?") -> Ещё вопрос в админке лиги ВТб постоянно выскакивает окно, оно для чего и может его убрать? | H40: =IFERROR(__xludf.DUMMYFUNCTION("""COMPUTED_VALUE"""),"13:00-14:00") -> 13:00-14:00
B41: =IFERROR(__xludf.DUMMYFUNCTION("""COMPUTED_VALUE"""),"Толкачев Егор") -> Толкачев Егор | C41: =IFERROR(__xludf.DUMMYFUNCTION("""COMPUTED_VALUE"""),"МатчТВ") -> МатчТВ | D41: =IFERROR(__xludf.DUMMYFUNCTION("""COMPUTED_VALUE"""),"Создан тикет") -> Создан тикет | E41: =IFERROR(__xludf.DUMMYFUNCTION("""COMPUTED_VALUE"""),"Передано Стасу для уточнения: Здесь мне нужно уточнить у матча инфо из последнего комментария Просрочена потому что нашлась несостыковка в параметрах запроса") -> Передано Стасу для уточнения: Здесь мне нужно уточнить у матча инфо из последнего комментария Просрочена потому что нашлась несостыковка в параметрах запроса | F41: =IFERROR(__xludf.DUMMYFUNCTION("""COMPUTED_VALUE"""),"https://rdm.inventos.ru/issues/149919?issue_count=140&issue_position=1&next_issue_id=148855") -> https://rdm.inventos.ru/issues/149919?issue_count=140&issue_position=1&next_issue_id=148855 | G41: =IFERROR(__xludf.DUMMYFUNCTION("""COMPUTED_VALUE"""),"Добрый день. Не получается стартануть трансляцию") -> Добрый день. Не получается стартануть трансляцию | H41: =IFERROR(__xludf.DUMMYFUNCTION("""COMPUTED_VALUE"""),"20:00-21:00") -> 20:00-21:00
B42: =IFERROR(__xludf.DUMMYFUNCTION("""COMPUTED_VALUE"""),"Червякова Ольга") -> Червякова Ольга | C42: =IFERROR(__xludf.DUMMYFUNCTION("""COMPUTED_VALUE"""),"МатчТВ") -> МатчТВ | D42: =IFERROR(__xludf.DUMMYFUNCTION("""COMPUTED_VALUE"""),"Создан тикет") -> Создан тикет | E42: =IFERROR(__xludf.DUMMYFUNCTION("""COMPUTED_VALUE"""),"Передали данный запрос в работу разработчикам") -> Передали данный запрос в работу разработчикам | F42: =IFERROR(__xludf.DUMMYFUNCTION("""COMPUTED_VALUE"""),"https://rdm.inventos.ru/issues/149955") -> https://rdm.inventos.ru/issues/149955 | G42: =IFERROR(__xludf.DUMMYFUNCTION("""COMPUTED_VALUE"""),"После смены качества трансляции, меню с контроллами не скрывается при бездействии курсора. Приходится сворачивать плеер в шортвью и затем раскрывать заново. ") -> После смены качества трансляции, меню с контроллами не скрывается при бездействии курсора. Приходится сворачивать плеер в шортвью и затем раскрывать заново. | H42: =IFERROR(__xludf.DUMMYFUNCTION("""COMPUTED_VALUE"""),"21:00-22:00") -> 21:00-22:00
F50: https://rdm.inventos.ru/issues/149955

Sheet Февраль 26
A1: Дата | B1: Ответственный | C1: Клиент | D1: Статус обращения | E1: Срок решения и комментарий | F1: Решение (ссылка на тикет/ссылка на документацию) | G1: Обращение клиента | H1: Время | I1: Статус внесения обращения в Obsidian | J1: Ссылка на Merge Request
A2: 46054 | B2: Мишина Анна | H2: 9:00-10:00
B3: Мишина Анна | C3: Restream | D3: Завершен | E3: Саша сказал надо смотреть upd 05.02: всё должно работать нормально, клиенту отписались | G3: Добрый день, @restream_webcaster, подскажите, не идёт сигнал в Ютуб, вк и рутуб. Все настроено, как надо, но не работает | H3: 10:00-11:00 | I3: Не требует инструкции
B4: Мишина Анна | H4: 11:00-12:00
B5: Мишина Анна | H5: 12:00-13:00
B6: Мишина Анна | H6: 13:00-14:00
B7: Мишина Анна | H7: 14:00-15:00
B8: Мишина Анна | H8: 15:00-16:00
B9: Мишина Анна | H9: 16:00-17:00
B10: Мишина Анна | H10: 17:00-18:00
B11: Мишина Анна | C11: Restream | D11: В работе | E11: аналогично | G11: Добрый день подскажите пожалуйста, что-то второй день не могу запустить рестримы, начинают идти и через минут две пропадают, в чем может быть проблема? | H11: 18:00-19:00
B12: Мишина Анна | H12: 19:00-20:00
B13: Мишина Анна | H13: 20:00-21:00
B14: Мишина Анна | H14: 21:00-22:00
B15: Мишина Анна | H15: 22:00-23:00
A16: 46055 | B16: Мишина Анна | H16: 9:00-10:00
B17: Мишина Анна | H17: 10:00-11:00
B18: Мишина Анна | H18: 11:00-12:00
B19: Мишина Анна | C19: Restream | D19: Завершен | E19: вчерашний, в работе upd 05.02: всё должно работать нормально, клиенту отписались | G19: Добрый день, надеюсь о моём вопросе ещё не забыли? | H19: 12:00-13:00
B20: Мишина Анна | H20: 13:00-14:00
B21: Мишина Анна | H21: 14:00-15:00
B22: Мишина Анна | H22: 15:00-16:00
B23: Мишина Анна | H23: 16:00-17:00
B24: Мишина Анна | H24: 17:00-18:00
B25: Мишина Анна | C25: МатчТВ | D25: Завершен | G25: Добрый вечер! У пользователя на ПК при попытке просмотра на сайте Матч ТВ возникает ошибка "Не удалось установить соединение с сайтом". Проблема возникает в Яндекс Браузере и Гугл Хром. Использует Wi-fi. При использовании другого источника интернета (LTE) проблем нет. IP-адрес 5.44.172.54 | H25: 18:00-19:00 | I25: Добавлена
B26: Мишина Анна | C26: КХЛ | D26: Завершен | E26: редактор доразметил | G26: Подскажите, почему разметка в лисах закончилась на счете 1:2? | H26: 19:00-20:00 | I26: Не требует инструкции
B27: Мишина Анна | C27: МатчТВ | D27: Завершен | E27: там уже 15 примеров | G27: Пользователю из Луганска недоступен просмотр Матч ТВ на сайте. Ошибка "трансляция недоступна в вашем регионе". Date: Mon, 02 Feb 26 20:32:12 +0300 GeoIP country: RU GeoIP country nginx: RU GeoIP region nginx: 00 HTTP_USER_AGENT: Mozilla/5.0 (Windows NT 10.0; Win64; x64) AppleWebKit/537.36 (KHTML, like Gecko) Chrome/142.0.0.0 YaBrowser/25.12.0.0 Safari/537.36 REMOTE_ADDR: 178.158.14.4 HTTP_X_FORWARDED_FOR: 178.158.14.4, 178.158.14.4 IP-Z: 178.158.14.4 Proxied IP: 178.158.14.4 Network Family: common Current UID/SU: / HAS FLASH: false MSE: true ВПН - нет | H27: 20:00-21:00 | I27: Не требует инструкции
B28: Мишина Анна | H28: 21:00-22:00
B29: Мишина Анна | H29: 22:00-23:00
A30: 46056 | B30: Мишина Анна | C30: Restream | D30: Завершен | G30: стрим падает каждые 30 секунд через рестрим, битрейт в ОБС стабильный в чём может быть дело? Такое бывало и на бесплатном тарифе, но сейчас я взял R5, данная проблема появляется также | H30: 9:00-10:00 | I30: Добавлена
B31: Мишина Анна | H31: 10:00-11:00
B32: Мишина Анна | H32: 11:00-12:00
B33: Мишина Анна | H33: 12:00-13:00
B34: Мишина Анна | H34: 13:00-14:00
B35: Мишина Анна | C35: Restream | D35: Завершен | G35: Подскажите, пожалуйста, а надо обложку для эфира публиковать общую у вас или на каждой площадке (вк,ок, ютуб, рутьюб) и можно ли везде делать запланированные эфиры на этих площадках? | H35: 14:00-15:00 | I35: Добавлена
B36: Мишина Анна | H36: 15:00-16:00
B37: Мишина Анна | H37: 16:00-17:00
B38: Мишина Анна | H38: 17:00-18:00
B39: Мишина Анна | H39: 18:00-19:00
B40: Мишина Анна | H40: 19:00-20:00
B41: Мишина Анна | H41: 20:00-21:00
B42: Мишина Анна | H42: 21:00-22:00
B43: Мишина Анна | H43: 22:00-23:00
A44: 46057 | B44: Гришина Светлана | C44: Restream | D44: Завершен | E44: пришло в 10:21. у неё 93988139 вопросов в секунду, но все они решаются типовыми инструкциями по добавлению нового события, подключению мультичата и пр. | G44: Добрый день! Подскажите, пожалуйста, у вас есть формат звонка или созвона? Не могу найти запланированный эфир в ВК и не могу найти тот эфир, что планировался для Ютуба, чтобы проставить время и дату | H44: 9:00-10:00 | I44: Не требует инструкции
B45: Гришина Светлана | C45: МОНИКИ | D45: Завершен | E45: участники присутствуют | G45: Кафедра Детских болезней. ПК Актуальные вопросы педиатрии. Организация оказания медицинской помощи детям в Российской Федерации. Комплексная оценка состояния здоровья детей. Льготное лекарственное обеспечение детей и подростков на региональном и федеральном уровнях. (04.02.26) - https://wbnr.su:50443/rooms?meet=2d7d5a3a-f314-49ef-bb60-4a20bb52b8c8 - Отсутствуют участники | H45: 10:00-11:00 | I45: Не требует инструкции
B46: Гришина Светлана | C46: Restream | D46: Завершен | E46: я принудительно подтвердила аккаунт (с почтой у него были проблемы). возможно, не пускает добавить канал из-за квоты по ютубу. плюс у него нет канала в вк видео лайв, помогаю зарегистрироваться. | G46: Здравствуйте! У меня не получается подключить ютуб-канал, пишет "Ошибка авторизации на платформе: youtube, время: 2026-02-04T10:31MSK" | H46: 11:00-12:00 | I46: Добавлена | J46: https://gitlab.inventos.ru/knowledge-base/obsidian/-/merge_requests/390
B47: Гришина Светлана | C47: МОНИКИ | D47: Завершен | E47: на контроле у Насти, обсуждали этот кривой перевод 15.12.2025, жду, делать тикет или нет upd 16.02: выкатили обновление для вебинаров, подобое поведение больше не должно наблюдаться, проблема решена | G47: Добрый день! Ранее уже спрашивали, но ничего не изменилось. Можно ли исправить отображение страницы при включённом автопереводе? Курсанты не в восторге, что камера у них "Не ало", а вместо "подключиться" кнопка "желчь") | H47: 12:00-13:00 | I47: Требует добавления
B48: Гришина Светлана | C48: МОНИКИ | D48: Завершен | E48: пришло в 11:45. думала mi браузер, оказалась опера, жду название модели устройства (написал просто "телефон"). сказал, отпишется завтра upd 05.02: не отписался | G48: Здравствуйте. Не получается зайти на лекцию. При нажатии на кнопку подключиться, пишет вы покинули вебинар | H48: 13:00-14:00 | I48: Не требует инструкции
B49: Гришина Светлана | C49: МОНИКИ | D49: Завершен | E49: участники присутствуют | G49: Кафедра Детских болезней. ПК Избранные вопросы неонатологии. Неонатальная желтуха, методы диагностики и лечения. Дифференциальная диагностика. Критерии выписки. (04.02.26) - https://wbnr.su:50443/rooms?meet=bc08addd-772a-4f3d-9dcc-edc12831e90d - Отсутствуют участники | H49: 14:00-15:00 | I49: Не требует инструкции
B50: Гришина Светлана | H50: 15:00-16:00
B51: Гришина Светлана | H51: 16:00-17:00
B52: Гришина Светлана | H52: 17:00-18:00
B53: Гришина Светлана | H53: 18:00-19:00
B54: Гришина Светлана | C54: КХЛ | D54: Завершен | E54: скинула редакторам в чат, поправили | G54: добрый вечер поправьте, пожалуйста, имя Боба и Барков — и.о. | H54: 19:00-20:00 | I54: Не требует инструкции
B55: Гришина Светлана | H55: 20:00-21:00
B56: Гришина Светлана | H56: 21:00-22:00
B57: Гришина Светлана | H57: 22:00-23:00
A58: 46058 | B58: Гришина Светлана | C58: Новый клиент | D58: Завершен | E58: скинула Насте | G58: Request details: Name: dHLiFeWKywNaDpxtWuDpt email: ti.mun.ew.o.2.7@gmail.com Additional information: Transaction ID: 1855933:8143710732 Block ID: rec371142116 Form Name: Подписка на рассылку https://webcaster.pro/ ----- | H58: 9:00-10:00 | I58: Не требует инструкции
B59: Гришина Светлана | C59: Restream | D59: Завершен | E59: посоветовала передобавить каналы | G59: Здравствуйте, не запускается стрим через ваш сервис, пытался час запустить, создавал новые эфиры у вас на сайте, но не работает. После подключения к сервису в ОБС и запуска стрима в обс на стримерских площадках стрим не запускался, а на ютубе вместо создания одного эфира и запуска его же создается по новому эфиру примерно каждую минуту и ни 1 из них не запускается, просто спамятся новые эфиры бесконечно. До этого такая проблема была, но решалась пересозданием эфира у вас на сайте (просто нажимал заново "Запланировать эфир", подключался к новому эфиру в ОБС и все работало). Сейчас же эта проблема уже не решилась так | H59: 10:00-11:00 | I59: Добавлена | J59: https://gitlab.inventos.ru/knowledge-base/obsidian/-/merge_requests/390
B60: Гришина Светлана | C60: МОНИКИ | D60: Завершен | E60: участники присутствуют | G60: Кафедра Детских болезней. ПК Актуальные вопросы педиатрии. Кислотозависимые заболевания у детей: ГЭРБ. Язвенная болезнь желудка и 12-перстной кишки. Вопросы диагностики и лечения. (05.02.26) - https://wbnr.su:50443/rooms?meet=8bc115ae-a9c5-4e18-b507-e6c90888d398 - Отсутствуют участники | H60: 11:00-12:00 | I60: Не требует инструкции
B61: Гришина Светлана | C61: МОНИКИ | D61: Завершен | E61: участники присутствуют | G61: Кафедра Детских болезней. ПК Избранные вопросы неонатологии. Вопросы неонатальной кардиологии. Врожденные пороки сердца. (05.02.26) - https://wbnr.su:50443/rooms?meet=95cd2e5d-8cf6-432a-ad68-4e1c6b7e8ccb - Отсутствуют участники | H61: 12:00-13:00 | I61: Не требует инструкции
B62: Гришина Светлана | H62: 13:00-14:00
B63: Гришина Светлана | H63: 14:00-15:00
B64: Гришина Светлана | H64: 15:00-16:00
B65: Гришина Светлана | H65: 16:00-17:00
B66: Гришина Светлана | H66: 17:00-18:00
B67: Гришина Светлана | H67: 18:00-19:00
B68: Гришина Светлана | C68: МХЛ | D68: Завершен | E68: передала L2 | G68: поменяйте, пожалуйста здесь время на 16:00 | H68: 19:00-20:00 | I68: Не требует инструкции
B69: Гришина Светлана | H69: 20:00-21:00
B70: Гришина Светлана | H70: 21:00-22:00
B71: Гришина Светлана | H71: 22:00-23:00
A72: 46059 | B72: Червякова Ольга | H72: 9:00-10:00
B73: Червякова Ольга | H73: 10:00-11:00
B74: Червякова Ольга | H74: 11:00-12:00
B75: Червякова Ольга | H75: 12:00-13:00
B76: Червякова Ольга | H76: 13:00-14:00
B77: Червякова Ольга | H77: 14:00-15:00
B78: Червякова Ольга | H78: 15:00-16:00
B79: Червякова Ольга | H79: 16:00-17:00
B80: Червякова Ольга | H80: 17:00-18:00
B81: Червякова Ольга | C81: Restream | D81: Завершен | G81: Добрый день! Сейчас пробовали тестово запустить только Ютуб, когда запустилась трансляция - высветилось, что нет соединения или связи - что-то такое. Почему такое может быть? | H81: 18:00-19:00
B82: Червякова Ольга | H82: 19:00-20:00
B83: Червякова Ольга | H83: 20:00-21:00
B84: Червякова Ольга | C84: Restream | D84: Завершен | E84: проблема с сервером была | G84: добрый вечер. Что то у меня стрим ни на одну площадку не запустился хотя все как обычно | H84: 21:00-22:00 | I84: Не требует инструкции
B85: Червякова Ольга | C85: Restream | D85: Завершен | E85: направила ссылку на инструкцию | G85: и видел что есть возможность получать сообщения через чат бот в телеграме | H85: 22:00-23:00 | I85: Не требует инструкции
A86: 46060 | B86: Червякова Ольга | H86: 9:00-10:00
B87: Червякова Ольга | H87: 10:00-11:00
B88: Червякова Ольга | H88: 11:00-12:00
B89: Червякова Ольга | H89: 12:00-13:00
B90: Червякова Ольга | H90: 13:00-14:00
B91: Червякова Ольга | H91: 14:00-15:00
B92: Червякова Ольга | H92: 15:00-16:00
B93: Червякова Ольга | H93: 16:00-17:00
B94: Червякова Ольга | H94: 17:00-18:00
B95: Червякова Ольга | C95: Новый клиент | D95: Завершен | E95: не вернулся с контактами | G95: Добрый вечер. Обращаюсь как юр лицо. у меня бар, хочу транслировать спортивные каналы. | H95: 18:00-19:00 | I95: Не требует инструкции
B96: Червякова Ольга | H96: 19:00-20:00
B97: Червякова Ольга | H97: 20:00-21:00
B98: Червякова Ольга | H98: 21:00-22:00
B99: Червякова Ольга | H99: 22:00-23:00
A100: 46061 | B100: Гришина Светлана | H100: 9:00-10:00
...

Sheet Декабрь 25
B1: Ответственный | C1: Клиент | D1: Статус обращения | E1: Срок решения и комментарий | F1: Решение (ссылка на тикет/ссылка на документацию) | G1: Обращение клиента | H1: Время | I1: Конышев | J1: Макогонюк | K1: Удалов | L1: Шавло | M1: Соловьёв | N1: Червякова | O1: Толкачев | P1: Макаров | Q1: Курасов
A2: 45992 | B2: Гришина Светлана | C2: МОНИКИ | D2: Завершен | G2: Доброе утро. Не могу подключиться вебинару. | H2: 9:00-10:00 | R2: =COUNTBLANK(B:B) -> 1048141
B3: Гришина Светлана | C3: МОНИКИ | D3: Завершен | E3: Сообщения в чате и обозначение голосом о необходимости включить микрофон не помогли. Присоединилась их администратор и завершила вебинар. | G3: Кафедра Детских болезней. ПК Актуальные вопросы педиатрии. Семинар по ФРМ и физиотерапии. (01.12.25) - https://wbnr.su:50443/rooms?meet=9c39637a-80a2-4a49-8da2-6c84dfaab8df - Здравствуйте! Звука нет | H3: 10:00-11:00
B4: Гришина Светлана | H4: 11:00-12:00
B5: Гришина Светлана | H5: 12:00-13:00
B6: Гришина Светлана | H6: 13:00-14:00
B7: Гришина Светлана | C7: Restream | D7: Завершен | G7: Подскажите, а если мы оплатим тариф Студии - в нее будет входить стандартный траиф рестриминга? | H7: 14:00-15:00
B8: Гришина Светлана | C8: КХЛ | D8: Завершен | E8: Ошибка в саммари в моб. приложении | G8: добрый день поправьте, пожалуйста | H8: 15:00-16:00
B9: Гришина Светлана | H9: 16:00-17:00
B10: Гришина Светлана | H10: 17:00-18:00
B11: Гришина Светлана | H11: 18:00-19:00
B12: Гришина Светлана | H12: 19:00-20:00
B13: Андреева Варвара | C13: КХЛ | D13: Завершен | G13: коллеги, поправьте, пожалуйста, он И.О. Рише (Трактор), Андриевский (Амур), Козлов (Динамо М), Люзенков (Сибирь) - все и.о. | H13: 20:00-21:00
B14: Андреева Варвара | C14: Restream | D14: Завершен | G14: Сейчас запустил трансляцию, толку ноль. Ни на одну площадку контент не приходит. | H14: 21:00-22:00
B15: Андреева Варвара | C15: МатчТВ | D15: Завершен | F15: https://rdm.inventos.ru/issues/165919 | G15: Добрый вечер! У пользователя в приложении на двух устройствах Смарт ТВ LG c2 (OLED65C22LB), приставка dune Pro Vision 4K при просмотре передачи от 30.11.2025 "После футбола с Георгием Черданцевым" наблюдалась проблема: не выводится многоканальный звук (при выборе многоканальной дорожки). Со слов пользователя в программе "После футбола с Георгием Черданцевым" под значком микрофона выбор стерео/многоканал. телевизор подключен по arc к ресиверу. При просмотре на тв для любой аудиодорожки на входе ресивера сигнал стерео. Если включить эту же трансляцию на приставке, то при переключении дорожки на входе ресивера видно переключение 2.0/5.1. При этом, во всех установленных у меня на тв онлайн кинотеатрах, при просмотре контента имеющего 5,1 дорожку вывод на ресивер происходит соответственно в 5,1 по тому же arc каналу. IP 95.25.174.144 | H15: 22:00-23:00
A16: 45993 | B16: Червякова Ольга | H16: 9:00-10:00
B17: Червякова Ольга | H17: 10:00-11:00
B18: Червякова Ольга | H18: 11:00-12:00
B19: Червякова Ольга | C19: Restream | D19: Завершен | G19: Привет, подскажите, как ваша программа работает для стримов на инстаграм и ютуб? Работает ли она если ведущий и тех часть ведут стрим не в России, а с территории ЛатАм или США или ЕС? | H19: 12:00-13:00
B20: Червякова Ольга | C20: ТВСтарт | D20: Завершен | F20: https://rdm.inventos.ru/issues/165935 | G20: Добрый день! Возникла задача, необходимо канал tvstart_4_srt_22904 сделать в режиме listener, с 06.12 по 19.12. Оставим его под одно соревнование. | H20: 13:00-14:00
B21: Червякова Ольга | C21: МХЛ | D21: Завершен | E21: инструкция уже есть | G21: Коллеги, добрый день! Перезалейте, пожалуйста, матч от 01.12 Академия СКА — МХК Динамо СПБ на вебкастер https://disk.yandex.ru/i/ZG2B5WiqZ3ahIQ | H21: 14:00-15:00
B22: Червякова Ольга | C22: КХЛ | D22: Завершен | E22: передаем в чат редакторов | G22: Коллеги, посмотрите, пожалуйста, Гол попал в категорию опасных моментов | H22: 15:00-16:00
B23: Червякова Ольга | H23: 16:00-17:00
B24: Червякова Ольга | H24: 17:00-18:00
B25: Андреева Варвара | H25: 18:00-19:00
B26: Андреева Варвара | H26: 19:00-20:00
B27: Андреева Варвара | H27: 20:00-21:00
B28: Андреева Варвара | H28: 21:00-22:00
B29: Андреева Варвара | H29: 22:00-23:00
A30: 45994 | B30: Червякова Ольга | H30: 9:00-10:00
B31: Червякова Ольга | H31: 10:00-11:00
B32: Червякова Ольга | C32: RDS | D32: Завершен | G32: Всем добрый день! ➡️ В этот уик-энд, 6-7 декабря, у всех трансляций планируем 1 аудиодорожку, только РУС язык. ➡️ Следующий гоночный этап, 24-25 января, у всех трансляций также планируем 1 аудиодорожку, только РУС язык. | H32: 11:00-12:00
B33: Червякова Ольга | H33: 12:00-13:00
B34: Мишина Анна | C34: МОНИКИ | D34: Завершен | G34: Кафедра Поликлинической терапии. ПК Оказание паллиативной медицинской помощи средним медицинским персоналом. Уход за паллиативными пациентами. (03.12.2025) - https://wbnr.su:50443/rooms?meet=491d6288-3067-40c9-9069-8f22fb569a8a - Отсутствуют участники | H34: 13:00-14:00
B35: Мишина Анна | H35: 14:00-15:00
B36: Мишина Анна | C36: МОНИКИ | D36: Завершен | G36: Кафедра Поликлинической терапии. ПК Оказание паллиативной медицинской помощи средним медицинским персоналом. Управление стрессом, релаксационные методики. (03.12.2025) - https://wbnr.su:50443/rooms?meet=40351ee2-1671-44aa-bd9a-b73d60a6e994 - Отсутствуют участники | H36: 15:00-16:00
B37: Мишина Анна | H37: 16:00-17:00
B38: Мишина Анна | H38: 17:00-18:00
B39: Мишина Анна | C39: МХЛ | D39: Завершен | F39: добавлено | G39: почему статус загрузки на нуле продолжительное время | H39: 18:00-19:00
B40: Мишина Анна | H40: 19:00-20:00
B41: Мишина Анна | H41: 20:00-21:00
B42: Мишина Анна | H42: 21:00-22:00
B43: Мишина Анна | C43: МатчТВ | D43: Завершен | E43: тикет и обращение от 01.12. приглядываю, обновляю. 04.12 закрыли тикет | F43: https://rdm.inventos.ru/issues/165919 | G43: Добрый вечер! Вернулся пользователь. Смотрел запись трансляции от 01.12.2025 "Чемпионат Испании. "Райо Вальекано" - "Валенсия" в 21:05-21:10 IP 95.25.174.144 Дорога многоканал | H43: 22:00-23:00
A44: 45995 | B44: Червякова Ольга | H44: 9:00-10:00
B45: Червякова Ольга | H45: 10:00-11:00
B46: Червякова Ольга | H46: 11:00-12:00
B47: Червякова Ольга | H47: 12:00-13:00
B48: Мишина Анна | H48: 13:00-14:00
B49: Мишина Анна | C49: МОНИКИ | D49: Завершен | G49: Кафедра Поликлинической терапии. ПК Оказание паллиативной медицинской помощи средним медицинским персоналом. Особенности паллиативной помощи неврологическим больным. (04.12.2025) - https://wbnr.su:50443/rooms?meet=9aeac4e8-c3ed-47c4-a369-98563840386d - Отсутствуют участники | H49: 14:00-15:00
B50: Мишина Анна | H50: 15:00-16:00
B51: Мишина Анна | H51: 16:00-17:00
B52: Мишина Анна | H52: 17:00-18:00
B53: Мишина Анна | H53: 18:00-19:00
B54: Мишина Анна | H54: 19:00-20:00
B55: Мишина Анна | C55: Restream | D55: Завершен | G55: Здравствуйте. Хочу запустить стрим. Вы просили вас проинформировать. | H55: 20:00-21:00
B56: Мишина Анна | H56: 21:00-22:00
B57: Мишина Анна | H57: 22:00-23:00
A58: 45996 | B58: Гришина Светлана | H58: 9:00-10:00
B59: Гришина Светлана | C59: МОНИКИ | D59: Завершен | G59: Кафедра Клинической лабораторной диагностики. Ординатура 2024-2025. Морфофункциональные особенности женской половой системы. (05.12.2025) - https://wbnr.su:50443/rooms?meet=b7040819-29d2-4827-8871-91fdf365ea1a - Отсутствуют участники | H59: 10:00-11:00
B60: Гришина Светлана | H60: 11:00-12:00
B61: Гришина Светлана | H61: 12:00-13:00
B62: Мишина Анна | C62: МХЛ | D62: Завершен | E62: внесла | F62: https://rdm.inventos.ru/issues/166087 | G62: В 19:30 сломалась трансляция мхл, экстренно передала Максиму | H62: 13:00-14:00
B63: Мишина Анна | C63: Restream | D63: Завершен | E63: этого внесла днем ранее | G63: В смысле потеря пакетов? Когда я сам стримил в три потока, никогда проблем с сетью не было. | H63: 14:00-15:00
B64: Мишина Анна | C64: Restream | D64: Завершен | E64: купил много тарифов, внесла | G64: Добрый день. Оплатил Рестрим, но твич не дает трансляцию и просит свой битрейт. Я оплатил еще и транскординг, но тариф у меня также R5 | H64: 15:00-16:00
B65: Мишина Анна | C65: Новый клиент | D65: Завершен | E65: передала Насте Шавло, ждем ответа | G65: Сколько одновременных стримов можно запустить на одном сайте через вашу saas платформу? | H65: 16:00-17:00
B66: Мишина Анна | C66: Restream | D66: Завершен | E66: внесла | G66: Хочу вести трансляции футбольных матчей , которые будут проходить на улице, из аппаратуры только телефон и штатив) мобильный интернет в норме. Трансляции хочу вести в группе своего турнира в контакте. Правильно я понимаю, что через ваш сервис я смогу это сделать без особых заморочек? | H66: 17:00-18:00
B67: Мишина Анна | C67: Restream | D67: Завершен | E67: внесла | G67: А скажите у нас с Вами изменилось партнёрство и сотрудничество? | H67: 18:00-19:00
B68: Мишина Анна | C68: Restream | D68: Завершен | E68: бубубу да бебебе от клиента. я не буду добавлять в инструкции, у нас все работает как должно | G68: вы кастомный rtmp не даете добавлять нормально | H68: 19:00-20:00
B69: Мишина Анна | C69: Restream | D69: Завершен | E69: внесла | G69: Извините , а почему сервис не работает ? Сигнал идет но картинки не на одном сервисе включая сам рестрим нет , а при отлючении все еще пишет , что "сигнал есть" но его нет | H69: 20:00-21:00
B70: Мишина Анна | C70: Restream | D70: Завершен | E70: внесла | G70: Здравствуйте, не работает трансляция, "нет сигнала" и всё | H70: 21:00-22:00
B71: Мишина Анна | C71: ТВСтарт | D71: Завершен | E71: прилетело в 19:35, они между собой разобрались, скорее всего не ту ссылку юзали. не буду вносить, т.к. сами разобрались и я не уверена до конца как, просто отписались что всё ок | G71: ПОдскажите, не могу завести нового пользователя-партнёра. | H71: 22:00-23:00
A72: 45997 | B72: Гришина Светлана | C72: Restream | D72: Завершен | E72: возможно, проблема с портами на нашей стороне | G72: есть проблема не как не получается с GoodGame поток как то не приходит на Ваш не понятно почему | H72: 9:00-10:00
B73: Гришина Светлана | C73: ТВСтарт | D73: Завершен | E73: передала дежурному L2 | G73: Доброе утро. Событие дзюдо битва городов на СРТ4 не запустилась по времени. Посмотрите пожалуйста | H73: 10:00-11:00
B74: Гришина Светлана | C74: Restream | D74: Завершен | E74: относится к обращению от 30.11 | G74: Здравствуйте. Запустил трансляцию, настроив все заново. Пропуск кадров по сети 52% | H74: 11:00-12:00
B75: Гришина Светлана | H75: 12:00-13:00
B76: Червякова Ольга | H76: 13:00-14:00
B77: Червякова Ольга | H77: 14:00-15:00
B78: Червякова Ольга | H78: 15:00-16:00
B79: Червякова Ольга | H79: 16:00-17:00
B80: Червякова Ольга | C80: М1 | D80: Завершен | E80: Добавлю в имеющуюся инструкцию | G80: Друзья, приветствую 🙌 Могли бы, пожалуйста, сбросить подписку для пользователя с мейлом ana91226114@yandex.ru ? Заранее спасибо! | H80: 17:00-18:00
B81: Червякова Ольга | H81: 18:00-19:00
B82: Червякова Ольга | H82: 19:00-20:00
B83: Червякова Ольга | H83: 20:00-21:00
B84: Червякова Ольга | H84: 21:00-22:00
B85: Червякова Ольга | H85: 22:00-23:00
A86: 45998 | B86: Мишина Анна | H86: 9:00-10:00
B87: Мишина Анна | H87: 10:00-11:00
B88: Мишина Анна | H88: 11:00-12:00
B89: Мишина Анна | H89: 12:00-13:00
B90: Мишина Анна | H90: 13:00-14:00
B91: Мишина Анна | C91: КХЛ | D91: Завершен | E91: связано с обращением от 5.12, вернее это его последствия, инструкция есть | F91: https://rdm.inventos.ru/issues/166087 | G91: коллеги, добрый день https://thumbs.webcaster.pro/rec-2-3.webcaster.pro/fc/sdd/file/events/2785170/neftehimik_metallurg_mg_1080p.mp4 Посмотрите, пожалуйста, первая часть трансляции идет с дублированием кадров и звука | H91: 14:00-15:00
B92: Мишина Анна | H92: 15:00-16:00
B93: Мишина Анна | C93: КХЛ | D93: Завершен | E93: просто редакторам передала, они не увидели | G93: Поправьте, пожалуйста он не может забивать победную при счете 4:8 | H93: 16:00-17:00
B94: Мишина Анна | C94: Restream | D94: Завершен | E94: партнеры наши, писала про них инструкцию | G94: Но буду надеяться что не будет ничего лагать не вылетать и всё в этом ключе потому что для меня важно чтобы эфир у меня шёл Чётко и без сбоев | H94: 17:00-18:00
B95: Мишина Анна | H95: 18:00-19:00
B96: Мишина Анна | H96: 19:00-20:00
B97: Мишина Анна | H97: 20:00-21:00
B98: Мишина Анна | H98: 21:00-22:00
B99: Мишина Анна | H99: 22:00-23:00
A100: 45999 | B100: Гришина Светлана | C100: МОНИКИ | D100: Завершен | G100: Кафедра Детских болезней. ПК Избранные вопросы детской гепатологии. Синдром холестаза. Вопросы дифференциальной диагностики. (08.12.25) - https://wbnr.su:50443/rooms?meet=58555953-355e-49c2-95d5-004040beb18f - Отсутствуют участники | H100: 9:00-10:00
...

Sheet Ноябрь 25 
B1: Ответственный | C1: Клиент | D1: Статус обращения | E1: Срок решения и комментарий | F1: Решение (ссылка на тикет/ссылка на документацию) | G1: Обращение клиента | H1: Время | I1: Конышев | J1: Макогонюк | K1: Удалов | L1: Шавло | M1: Соловьёв | N1: Червякова | O1: Толкачев | P1: Макаров | Q1: Курасов
A2: 45962 | B2: Червякова Ольга | H2: 9:00-10:00 | R2: =COUNTBLANK(B:B) -> 1048155
B3: Червякова Ольга | C3: МОНИКИ | G3: Добрый день! Не могу подключиться к вебинару,проблема та же что и вчера. Помогите пожалуйста | H3: 10:00-11:00
B4: Червякова Ольга | H4: 11:00-12:00
B5: Червякова Ольга | H5: 12:00-13:00
B6: Червякова Ольга | H6: 13:00-14:00
B7: Червякова Ольга | H7: 14:00-15:00
B8: Червякова Ольга | H8: 15:00-16:00
B9: Червякова Ольга | H9: 16:00-17:00
B10: Мишина Анна | C10: Restream | D10: Завершен | E10: относится к обращению от 31.10 на почту | G10: Добрый день. А когда будет ответ по моим вопросам? | H10: 17:00-18:00
B11: Мишина Анна | H11: 18:00-19:00
B12: Гришина Светлана | H12: 19:00-20:00
B13: Гришина Светлана | H13: 20:00-21:00
B14: Гришина Светлана | C14: Новый клиент | D14: Завершен | G14: Здравствуйте, не могу разобраться. У вас в API сервера написано, что для формирования подписи нужно добавить "secret – выданный при регистрации Клиента секретный ключ". Вопрос: где его найти? | H14: 21:00-22:00
B15: Гришина Светлана | H15: 22:00-23:00
A16: 45963 | B16: Червякова Ольга | H16: 9:00-10:00
B17: Червякова Ольга | H17: 10:00-11:00
B18: Червякова Ольга | H18: 11:00-12:00
B19: Червякова Ольга | C19: МатчТВ | D19: В работе | E19: относится к обращению от 31.10.2025 | G19: Добрый день! Вернулся пользователь. С его слов при смене качества на более низкое, проблема сохраняется. | H19: 12:00-13:00
B20: Червякова Ольга | C20: Restream | D20: Завершен | G20: Добрый день! У нас перестал работать сервис | H20: 13:00-14:00
B21: Червякова Ольга | C21: МатчТВ | D21: Создан тикет | G21: У пользователя UID EhjbpFfosJs9AbZpN5Wp6R в приложении на Смарт ТВ при просмотре трансляций в 4К подвисание. Наблюдается на всех трансляциях которые были в 4К. Смарт ТВ Samsung QE50QN90AAUXRU подключен по кабелю. Ip адрес 31.133.234.163 | H21: 14:00-15:00
B22: Червякова Ольга | C22: МатчТВ | D22: Завершен | G22: А можно узнать точное время пропадания и появления сигнала ? | H22: 15:00-16:00
B23: Червякова Ольга | C23: МатчТВ | D23: Завершен | G23: На видеоплатформе все настроено верно. @Inventos_tech_sup с сигналом нет проблемы ? | H23: 16:00-17:00
B24: Червякова Ольга | H24: 17:00-18:00
B25: Червякова Ольга | H25: 18:00-19:00
B26: Мишина Анна | H26: 19:00-20:00
B27: Мишина Анна | H27: 20:00-21:00
B28: Мишина Анна | C28: Restream | D28: Завершен | E28: относится к обращению от 31.10 на почту | G28: Добрый вечер! Я запустил тестовый эфир | H28: 21:00-22:00
B29: Мишина Анна | C29: Restream | D29: Завершен | E29: время обращения 23:36. отвалился диск, Саша перекинул пользователя на другой сервер, всё в порядке | G29: Ребят Стрим сваливается! | H29: 22:00-23:00
A30: 45964 | B30: Гришина Светлана | H30: 9:00-10:00
B31: Гришина Светлана | H31: 10:00-11:00
B32: Гришина Светлана | H32: 11:00-12:00
B33: Червякова Ольга | H33: 12:00-13:00
B34: Червякова Ольга | H34: 13:00-14:00
B35: Червякова Ольга | H35: 14:00-15:00
B36: Червякова Ольга | H36: 15:00-16:00
B37: Червякова Ольга | H37: 16:00-17:00
B38: Червякова Ольга | H38: 17:00-18:00
B39: Мишина Анна | H39: 18:00-19:00
B40: Мишина Анна | C40: Restream | D40: Завершен | G40: Я только запустил уже пропусски | H40: 19:00-20:00
B41: Мишина Анна | H41: 20:00-21:00
B42: Мишина Анна | C42: Restream | D42: Завершен | G42: Ребят. Провалы. СИЛЬНЫЕ | H42: 21:00-22:00
B43: Мишина Анна | H43: 22:00-23:00
A44: 45965 | B44: Гришина Светлана | H44: 9:00-10:00
B45: Гришина Светлана | H45: 10:00-11:00
B46: Гришина Светлана | H46: 11:00-12:00
B47: Червякова Ольга | H47: 12:00-13:00
B48: Червякова Ольга | C48: Restream | D48: Завершен | G48: Добрый день! У нас опять те же самые проблемы | H48: 13:00-14:00
B49: Червякова Ольга | C49: Restream | D49: Завершен | G49: У всех рестрим лагает не идёт трансляция Ни на одну платформу | H49: 14:00-15:00
B50: Червякова Ольга | H50: 15:00-16:00
B51: Червякова Ольга | H51: 16:00-17:00
B52: Червякова Ольга | H52: 17:00-18:00
B53: Мишина Анна | H53: 18:00-19:00
B54: Мишина Анна | H54: 19:00-20:00
B55: Мишина Анна | C55: Restream | D55: Завершен | G55: ОПЯТЬ ЛАГИ | H55: 20:00-21:00
B56: Мишина Анна | H56: 21:00-22:00
B57: Мишина Анна | H57: 22:00-23:00
A58: 45966 | B58: Гришина Светлана | H58: 9:00-10:00
B59: Гришина Светлана | H59: 10:00-11:00
B60: Гришина Светлана | H60: 11:00-12:00
B61: Червякова Ольга | C61: Новый клиент | D61: Завершен | G61: Здравствуйте. Мы — киностудия «Беларусьфильм». Наша цель — настроить автоматизированную дистрибуцию нашего архивного и нового контента на вашу сеть партнерских VOD-платформ (таких как IVI, Кинопоиск, More.tv (http://more.tv/) и другие). Мы зарегистрировались с ролью «Загрузка архивных видео». Подскажите, пожалуйста, дальнейшие шаги для подключения к системе дистрибуции, включая настройку прав (DRM) и предоставление доступа к нашему каталогу для ваших партнеров». | H61: 12:00-13:00
B62: Червякова Ольга | H62: 13:00-14:00
B63: Червякова Ольга | C63: Ifree | D63: Завершен | G63: Коллеги, добрый день. У вас есть метод POST https://bl.webcaster.pro/, куда можно отправлять сведения о статистики просмотра с такими параметрами: ticket: 89368b4646a77682 type: file event_id: 2764339s id: 37_9341643604 sign: ff989b30c63e18ca09c3be74e8a4442d exp: 1757257450 m: 0 uid: 89368b4646a77682 Вопрос про параметр m - туда отправлять количество минут, которые прошли относительно текущего воспроизведения на таймлайне или же просто текущее время таймлайна? | H63: 14:00-15:00
B64: Червякова Ольга | H64: 15:00-16:00
B65: Червякова Ольга | H65: 16:00-17:00
B66: Червякова Ольга | H66: 17:00-18:00
B67: Мишина Анна | C67: Restream | D67: Завершен | G67: опять отвалы | H67: 18:00-19:00
B68: Мишина Анна | H68: 19:00-20:00
B69: Мишина Анна | H69: 20:00-21:00
B70: Мишина Анна | H70: 21:00-22:00
B71: Мишина Анна | H71: 22:00-23:00
A72: 45967 | B72: Червякова Ольга | H72: 9:00-10:00
B73: Червякова Ольга | H73: 10:00-11:00
B74: Червякова Ольга | H74: 11:00-12:00
B75: Червякова Ольга | H75: 12:00-13:00
B76: Червякова Ольга | H76: 13:00-14:00
B77: Червякова Ольга | H77: 14:00-15:00
B78: Червякова Ольга | H78: 15:00-16:00
B79: Червякова Ольга | H79: 16:00-17:00
B80: Червякова Ольга | H80: 17:00-18:00
B81: Мишина Анна | H81: 18:00-19:00
B82: Мишина Анна | H82: 19:00-20:00
B83: Мишина Анна | C83: Restream | D83: Завершен | G83: Кому писать претензию! | H83: 20:00-21:00
B84: Мишина Анна | H84: 21:00-22:00
B85: Мишина Анна | H85: 22:00-23:00
A86: 45968 | B86: Гришина Светлана | H86: 9:00-10:00
B87: Гришина Светлана | H87: 10:00-11:00
B88: Гришина Светлана | H88: 11:00-12:00
B89: Червякова Ольга | C89: КХЛ | D89: Завершен | G89: коллеги, поправьте, пожалуйста, согласование и.о. главноГО тренерА | H89: 12:00-13:00
B90: Червякова Ольга | H90: 13:00-14:00
B91: Червякова Ольга | H91: 14:00-15:00
B92: Червякова Ольга | H92: 15:00-16:00
B93: Червякова Ольга | H93: 16:00-17:00
B94: Мишина Анна | C94: Restream | D94: Завершен | H94: 17:00-18:00
B95: Мишина Анна | H95: 18:00-19:00
B96: Мишина Анна | H96: 19:00-20:00
B97: Мишина Анна | H97: 20:00-21:00
B98: Мишина Анна | H98: 21:00-22:00
B99: Мишина Анна | H99: 22:00-23:00
A100: 45969 | B100: Гришина Светлана | H100: 9:00-10:00
...

Sheet Октябрь 25
A1: С | B1: Ответственный | C1: Клиент | D1: Статус обращения | E1: Срок решения и комментарий | F1: Решение (ссылка на тикет/ссылка на документацию) | G1: Обращение клиента | H1: Время | I1: Конышев | J1: Макогонюк | K1: Удалов | L1: Шавло | M1: Соловьёв | N1: Червякова | O1: Толкачев | P1: Макаров | Q1: Курасов
A2: 45931 | B2: Гришина Светлана | H2: 9:00-10:00
B3: Гришина Светлана | H3: 10:00-11:00
B4: Гришина Светлана | C4: Restream | D4: Завершен | G4: Добрый день! Не удается привязать каналы. Нет кнопок, которые указаны в инструкции | H4: 11:00-12:00
B5: Червякова Ольга | C5: Restream | D5: Завершен | G5: Приложение в плей маркете есть? | H5: 12:00-13:00
B6: Червякова Ольга | C6: МатчТВ | D6: Завершен | G6: это канал «Матч ТВ» на Андроид ТВ. Куда делось качество при выборе 50 фпс | H6: 13:00-14:00
B7: Червякова Ольга | C7: МХЛ | D7: Завершен | E7: относится к обращению, внесенному ранее | G7: Колелги, об этой проблеме я писал еще в июле, ничего не поменялось | H7: 14:00-15:00
B8: Червякова Ольга | C8: Restream | D8: Завершен | G8: Почему у вас нет системы поощрения? я на протяжении 5-ти лет пользуюсь вашим сервисом и даю хороший фидбек по технической работе и сбоям... и как-то грустно становится, что даже не можете убрать обязательную плашку с "транслируется через Рестрим.су", которая приписывается в названии. | H8: 15:00-16:00
B9: Червякова Ольга | C9: Restream | D9: Завершен | G9: Доброй ночи. Столкнулся с такой проблемой, что когда выставляю в настройках название своих стримов, то на ютубе на предыдущем видео меняется название... не понимаю как так происходит, но это напрягает | H9: 16:00-17:00
B10: Червякова Ольга | C10: Restream | D10: Завершен | G10: Добрый день, подскажите пж как настроить интеграцию с youtube? | H10: 17:00-18:00
B11: Червякова Ольга | C11: Новый клиент | D11: Завершен | E11: обратился не от клиента | G11: Мне нужно установить приложение на смарт ТВ | H11: 18:00-19:00
B12: Кузнецова Алиса | H12: 19:00-20:00
B13: Кузнецова Алиса | H13: 20:00-21:00
B14: Червякова Ольга | H14: 21:00-22:00
B15: Червякова Ольга | H15: 22:00-23:00
A16: 45932 | B16: Толкачев Егор | H16: 9:00-10:00
B17: Толкачев Егор | H17: 10:00-11:00
B18: Толкачев Егор | H18: 11:00-12:00
B19: Червякова Ольга | C19: Restream | D19: Завершен | E19: обращение за 01.10 | G19: Все-таки возник еще один вопрос: При привязке ютуб, не могу выбрать канал, который администрирую. Только только личный аккаунт. | H19: 12:00-13:00
B20: Червякова Ольга | H20: 13:00-14:00
B21: Червякова Ольга | C21: Restream | D21: Завершен | G21: Снова прерывания стримов начались, у меня отдача идёт... а стримы пишет завершены | H21: 14:00-15:00
B22: Червякова Ольга | H22: 15:00-16:00
B23: Червякова Ольга | H23: 16:00-17:00
B24: Червякова Ольга | C24: Restream | D24: Завершен | G24: добры день. не могу понять, как вывести трансляцию на собственный сайт? где взять хтмл код? | H24: 17:00-18:00
B25: Белов Дмитрий | H25: 18:00-19:00
B26: Белов Дмитрий | H26: 19:00-20:00
B27: Белов Дмитрий | H27: 20:00-21:00
B28: Белов Дмитрий | H28: 21:00-22:00
B29: Белов Дмитрий | H29: 22:00-23:00
A30: 45933 | B30: Белов Дмитрий | C30: Restream | G30: срыв происходит спустя 3-4 минуты, максимум 4 минуты 57-58 секунд и трансляция прерывается... это случалось и днём и в ночное время | H30: 9:00-10:00
B31: Белов Дмитрий | C31: ЛигаВТБ | D31: Завершен | G31: Здравствуйте. Скажите, почему нет видео текущего сезона лиги ВТБ? Спасибо | H31: 10:00-11:00
B32: Белов Дмитрий | H32: 11:00-12:00
B33: Червякова Ольга | C33: ЛигаВТБ | D33: Завершен | G33: Здравствуйте. Скажите, почему нет видео текущего сезона лиги ВТБ? Спасибо | H33: 12:00-13:00
B34: Червякова Ольга | C34: Restream | D34: Завершен | G34: срыв происходит спустя 3-4 минуты, максимум 4 минуты 57-58 секунд и трансляция прерывается... это случалось и днём и в ночное время | H34: 13:00-14:00
B35: Червякова Ольга | H35: 14:00-15:00
B36: Червякова Ольга | H36: 15:00-16:00
B37: Червякова Ольга | H37: 16:00-17:00
B38: Червякова Ольга | H38: 17:00-18:00
B39: Червякова Ольга | H39: 18:00-19:00
B40: Червякова Ольга | H40: 19:00-20:00
B41: Червякова Ольга | H41: 20:00-21:00
B42: Червякова Ольга | H42: 21:00-22:00
B43: Червякова Ольга | H43: 22:00-23:00
A44: 45934 | B44: Алексеева Александра | H44: 9:00-10:00
B45: Гришина Светлана | H45: 10:00-11:00
B46: Гришина Светлана | C46: Restream | D46: Завершен | G46: Добрый день. Подскажите по такому вопросу. Я когда-то у вас регистрировалась, вроде как подключены каналы Телеграм и ВК. Теперь скачала OBS Studio. Читаю инструкцию. В четвертом пункте сказано: 4. Скопируйте со страницы на нашем сайте данные в поля “Сервер” и “Ключ потока” и нажмите ОК в правом нижнем углу окна настроек Вот тут-то я и зависаю: откуда скопировать? Я не понимаю, с какой страницы. Задача у меня такая: начать трансляцию на 2 канала, Телеграм и ВК, с помощью OBS Studio. | H46: 11:00-12:00
B47: Гришина Светлана | H47: 12:00-13:00
B48: Червякова Ольга | C48: RDS | D48: Завершен | E48: относится к сбою, будет описано в одной инструкции | G48: Коллеги, добрый день! Всё ли ок на вашей стороне? Не можем получить доступ в админку, на всех устройствах так. | H48: 13:00-14:00
B49: Червякова Ольга | C49: КХЛ | D49: Завершен | E49: относится к сбою, будет описано в одной инструкции | G49: Здравствуйте! Внезапно не работает приложение КХЛ(( | H49: 14:00-15:00
B50: Червякова Ольга | C50: ОТР | D50: Завершен | G50: Попробуйте еще пнуть в телегу рестрим, вроде везде работает, а телега отвалилась )) | H50: 15:00-16:00
B51: Червякова Ольга | C51: КХЛ | D51: Завершен | E51: относится к сбою, будет описано в одной инструкции | G51: Коллеги, а что с вебкастером? | H51: 16:00-17:00
B52: Толкачев Егор | C52: КХЛ | D52: Завершен | G52: @Inventos_tech_sup Проверьте, пожалуйста, экспорт файла не появляется момент в приложении | H52: 17:00-18:00
B53: Толкачев Егор | C53: МХЛ | D53: Завершен | G53: Добрый ден. можете глянуть, почему у меня остановилась конвертация ролика спартак-акм-юниор на пятидесяти двух процентах | H53: 18:00-19:00
B54: Червякова Ольга | C54: ТВСтарт | D54: Завершен | E54: относится к сбою, будет описано в одной инструкции | G54: У нас не работает личный кабинет на вебкастер | H54: 19:00-20:00
B55: Червякова Ольга | C55: КХЛ | D55: Завершен | E55: относится к сбою, будет описано в одной инструкции | G55: эээээ кхл сайт всё | H55: 20:00-21:00
B56: Червякова Ольга | C56: МатчТВ | D56: Завершен | G56: Пользователю недоступен просмотр Матч Премьер на сайте ВПН - не включен. | H56: 21:00-22:00
B57: Червякова Ольга | C57: МатчТВ | D57: Завершен | G57: При просмотре отдельной трансляции "Интер - Кремонезе. Чемпионат Италии. Тур 6" в приложении МАТЧ у пользователя звук есть но вместо изображения черный экран. UID 617axhjyzp6BmHaP3oRttP Со слов пользователя другие трансляции работают. Пробовал на разных устройствах. | H57: 22:00-23:00
A58: 45935 | B58: Червякова Ольга | C58: КХЛ | D58: Завершен | G58: Доброе утро сайт вебкастера не грузит и диагностика виндовс пишет это | H58: 9:00-10:00
B59: Червякова Ольга | C59: Restream | D59: Завершен | E59: за 04.10 | G59: привет | H59: 10:00-11:00
B60: Червякова Ольга | C60: Restream | D60: Завершен | G60: Добрый день. Не могу подключить тариф с транскодингом - перебрасывает в профиль. Подскажите, как оплатить? | H60: 11:00-12:00
B61: Червякова Ольга | C61: Restream | D61: Завершен | G61: Can I try to restream? | H61: 12:00-13:00
B62: Червякова Ольга | C62: Restream | D62: Завершен | E62: за 04.10 | G62: Здравствуйте, пытаюсь воспользоваться вашим сервисом, чтобы одновременно стримить на твич и ютуб, но у меня через ваш сервис не заходит в YouTube и выдает вот такую ошибку, подскажите, пожалуйста, в чем может быть проблема? | H62: 13:00-14:00
B63: Червякова Ольга | C63: МатчТВ | D63: Завершен | G63: Всем привет! Забыл вовремя написать: сегодня в 16:30 будет ЦСКА - Спартак. Ожидаем высокую нагрузку @Inventos_tech_sup | H63: 14:00-15:00
B64: Червякова Ольга | H64: 15:00-16:00
B65: Червякова Ольга | H65: 16:00-17:00
B66: Червякова Ольга | C66: МатчТВ | D66: Завершен | G66: Добрый день! Еще один пользователь с проблемой при просмотре записей матчей в приложении. Есть только звук, а изображения нет UID 8EdnjZs3FzFniKvqF6jm11 Смартфон: Poco x7 pro Ip 46.8.6.66 OS: Android | H66: 17:00-18:00
B67: Червякова Ольга | H67: 18:00-19:00
B68: Андреева Варвара | C68: Restream | D68: Завершен | G68: Здравствуйте. Почему не работает сервис? Когда сервис оживет? | H68: 19:00-20:00
B69: Андреева Варвара | H69: 20:00-21:00
B70: Червякова Ольга | H70: 21:00-22:00
B71: Червякова Ольга | H71: 22:00-23:00
A72: 45936 | B72: Белов Дмитрий | H72: 9:00-10:00
B73: Белов Дмитрий | H73: 10:00-11:00
B74: Белов Дмитрий | H74: 11:00-12:00
B75: Червякова Ольга | C75: Restream | D75: Завершен | G75: Добрый день. Удалось ли понять причину вчерашнего сбоя в работе сервиса? Работает ли сервис сейчас в штатном режиме? | H75: 12:00-13:00
B76: Червякова Ольга | C76: МатчТВ | D76: Завершен | G76: Добрый день! у нас проблема с каналом matchtv-test https://admin.video.matchtv.zxz.su/client/channels/1/watch?autostart=1 не показывается трансляция | H76: 13:00-14:00
B77: Червякова Ольга | C77: Restream | D77: Завершен | G77: Вопрос организационного характера. Возможно ответ указан в каком-то договоре при регистрации, в FAQ или где-то еще, но я такого там не нашел. При создании трансляций через сервис нужно вводить название и описание для выбранного сервиса (ютуб, твич и т. д.). Пользователь вводит и то и другое, на сервисах появляется запланированное на указанное время событие с указанным текстом. Но при старте к заголовку и к тексту в конце добавляется приписка в стиле «Создано при помощи сервиса restream.su», что можно расценивать как самореклама. При тарифе R2 (бесплатном) можно понять действия такого характера — сервис тратит мощности своих серверов и трафик, не получая ничего от пользователя, пусть хотя бы вставляется легкого рода рекламка. Но при использовании платного тарифа это нетипично и вызывает недопонимание. Можно как-то отключить подобные автоматические приписки? | H77: 14:00-15:00
B78: Червякова Ольга | C78: Restream | D78: Завершен | G78: Добрый день, проблема с трансляцией rtmp://82656.app-streams.restream.su/c5a3d887-c3dc-4b4d-a020-57543e537ade | H78: 15:00-16:00
B79: Червякова Ольга | C79: Restream | D79: Завершен | E79: аккаунт у пользователя тот же, что и выше, опишу в одной инструкции | G79: добрый день, не работает стрим https://app.restream.su/broadcast/82656 | H79: 16:00-17:00
B80: Червякова Ольга | H80: 17:00-18:00
B81: Андреева Варвара | C81: Restream | D81: Завершен | G81: здраствуйте не запускается стрим через ваш сервис, через остальные всё работает | H81: 18:00-19:00
B82: Андреева Варвара | C82: Restream | D82: Завершен | G82: что то опять стало с рестримом? обс не загружает его | H82: 19:00-20:00
B83: Андреева Варвара | H83: 20:00-21:00
B84: Андреева Варвара | C84: Restream | D84: Завершен | G84: добрый день не запускается рестрим, подскажите в чем может быть проблема? | H84: 21:00-22:00
B85: Андреева Варвара | C85: Restream | D85: Завершен | G85: Добрый вечер, не могу начать трансляцию, пишет не удалось подключиться к серверу | H85: 22:00-23:00
A86: 45937 | B86: Гришина Светлана | C86: Restream | D86: Завершен | G86: Здравствуйте, а что происходит с сервисом? Мне пишет что "не удалось связаться с сервером" | H86: 9:00-10:00
B87: Гришина Светлана | H87: 10:00-11:00
B88: Гришина Светлана | H88: 11:00-12:00
B89: Червякова Ольга | H89: 12:00-13:00
B90: Червякова Ольга | H90: 13:00-14:00
B91: Червякова Ольга | H91: 14:00-15:00
B92: Червякова Ольга | H92: 15:00-16:00
B93: Червякова Ольга | C93: Restream | D93: Завершен | G93: Здравствуйте. Можно ли запланировать трансляцию с помощью вашего сервиса? | H93: 16:00-17:00
B94: Червякова Ольга | H94: 17:00-18:00
B95: Андреева Варвара | C95: ТВСтарт | D95: Завершен | G95: Добрый день. https://start.webcaster.pro/admin/events/2837571 в этом событии не можем продлить окончание. Пишет ошибка. Посмотрите, пожалуйста | H95: 18:00-19:00
B96: Андреева Варвара | C96: КХЛ | D96: Завершен | G96: Коллеги, добрый вечер. При попытке сохранить описание к ролику появляется вот такая штука уже перезапускал вебкастер - все поворяется повторяется https://api-video.khl.ru/client/events/2839539 | H96: 19:00-20:00
B97: Андреева Варвара | C97: Restream | D97: Завершен | G97: Здравствуйте, у меня не получается запустить стрим через ваш сервис, используя OBS, подскажите, пожалуйста, в чем может быть проблема, выдает вот такую ошибку | H97: 20:00-21:00
B98: Андреева Варвара | H98: 21:00-22:00
B99: Андреева Варвара | H99: 22:00-23:00
A100: 45938 | B100: Гришина Светлана | C100: Restream | D100: Завершен | G100: Здравствуйте. При попытке запуска трансляции OBS выдаёт ошибку | H100: 9:00-10:00
...

Sheet Сентябрь 25
B1: Ответственный | C1: Клиент | D1: Статус обращения | E1: Срок решения и комментарий | F1: Решение (ссылка на тикет/ссылка на документацию) | G1: Обращение клиента | H1: Время | I1: Конышев | J1: Макогонюк | K1: Удалов | L1: Шавло | M1: Соловьёв | N1: Червякова | O1: Толкачев | P1: Макаров | Q1: Курасов
A2: 45901 | B2: Червякова Ольга | H2: 9:00-10:00
B3: Червякова Ольга | H3: 10:00-11:00
B4: Червякова Ольга | H4: 11:00-12:00
B5: Червякова Ольга | H5: 12:00-13:00
B6: Червякова Ольга | H6: 13:00-14:00
B7: Червякова Ольга | H7: 14:00-15:00
B8: Червякова Ольга | H8: 15:00-16:00
B9: Червякова Ольга | H9: 16:00-17:00
B10: Червякова Ольга | H10: 17:00-18:00
B11: Щемелинин Владислав | H11: 18:00-19:00
B12: Щемелинин Владислав | H12: 19:00-20:00
B13: Щемелинин Владислав | H13: 20:00-21:00
B14: Щемелинин Владислав | H14: 21:00-22:00
B15: Щемелинин Владислав | H15: 22:00-23:00
A16: 45902 | B16: Червякова Ольга | H16: 9:00-10:00
B17: Червякова Ольга | H17: 10:00-11:00
B18: Червякова Ольга | H18: 11:00-12:00
B19: Червякова Ольга | H19: 12:00-13:00
B20: Червякова Ольга | H20: 13:00-14:00
B21: Червякова Ольга | H21: 14:00-15:00
B22: Червякова Ольга | H22: 15:00-16:00
B23: Червякова Ольга | H23: 16:00-17:00
B24: Червякова Ольга | H24: 17:00-18:00
B25: Гришина Светлана | H25: 18:00-19:00
B26: Гришина Светлана | H26: 19:00-20:00
B27: Гришина Светлана | H27: 20:00-21:00
B28: Гришина Светлана | H28: 21:00-22:00
B29: Гришина Светлана | H29: 22:00-23:00
A30: 45903 | B30: Щемелинин Владислав | H30: 9:00-10:00
B31: Щемелинин Владислав | H31: 10:00-11:00
B32: Щемелинин Владислав | H32: 11:00-12:00
B33: Щемелинин Владислав | H33: 12:00-13:00
B34: Червякова Ольга | H34: 13:00-14:00
B35: Червякова Ольга | C35: Ifree | D35: Завершен | G35: Добрый день! Не могли бы вы пожалуйста обрезать загруженно видео с 01:37:46 и до конца | H35: 14:00-15:00
B36: Червякова Ольга | H36: 15:00-16:00
B37: Червякова Ольга | H37: 16:00-17:00
B38: Червякова Ольга | H38: 17:00-18:00
B39: Толкачев Егор | H39: 18:00-19:00
B40: Толкачев Егор | H40: 19:00-20:00
B41: Толкачев Егор | H41: 20:00-21:00
B42: Толкачев Егор | H42: 21:00-22:00
B43: Толкачев Егор | H43: 22:00-23:00
A44: 45904 | B44: Гришина Светлана | C44: МатчТВ | D44: Завершен | G44: Здравствуйте! У пользователя не запускаются трансляции и эфиры в приложении на ТВ Самсунг: SMfnbB21hPCCSx6AKvcAFj Ростелеком МРФ Северо-Запад 92.100.155.224. Версия ПО ТВ: T-MSLDEUC-1500.9 https://cloud.mail.ru/stock/4sw4rjQ2z5CzDsGMvCD4pAxA Последняя попытка 5 минут назад | H44: 9:00-10:00
B45: Гришина Светлана | C45: МОНИКИ | D45: Завершен | G45: Здравствуйте, не могу подключиться к лекции. Подскажите пожалуйста, что делать? Нажимаю подключиться, а мне пишет выпокинули встречу | H45: 10:00-11:00
B46: Гришина Светлана | C46: Restream | D46: Завершен | G46: Здравствуйте. Я вошла зарезервировалась на сайте через гугл аккаунт. Но сейчас мне нужно зайти с другого устройства, на котором я не хочу указывать свои данные гугл профиля. Если ввести почту и пароль, которые подходят к нему, они не принимаются вашим сервисом - пароль не верный, но другой мне на почту не приходил. Изменить пароль тоже не получилось. Можете подсказать, как выполнить вход через почту? | H46: 11:00-12:00
B47: Гришина Светлана | H47: 12:00-13:00
B48: Червякова Ольга | C48: Restream | D48: Завершен | G48: зарегистрировалась в вашекм сервисе. настроила трансляцию с зум. а при передачи трансляции с вашего сервиса на ютуб и кинескоп, ничего не происходит | H48: 13:00-14:00
B49: Червякова Ольга | H49: 14:00-15:00
B50: Червякова Ольга | H50: 15:00-16:00
B51: Червякова Ольга | H51: 16:00-17:00
B52: Червякова Ольга | H52: 17:00-18:00
B53: Толкачев Егор | H53: 18:00-19:00
B54: Толкачев Егор | H54: 19:00-20:00
B55: Толкачев Егор | H55: 20:00-21:00
B56: Толкачев Егор | H56: 21:00-22:00
B57: Толкачев Егор | H57: 22:00-23:00
A58: 45905 | B58: Щемелинин Владислав | H58: 9:00-10:00
B59: Щемелинин Владислав | H59: 10:00-11:00
B60: Щемелинин Владислав | H60: 11:00-12:00
B61: Щемелинин Владислав | H61: 12:00-13:00
B62: Червякова Ольга | H62: 13:00-14:00
B63: Червякова Ольга | H63: 14:00-15:00
B64: Червякова Ольга | H64: 15:00-16:00
B65: Червякова Ольга | H65: 16:00-17:00
B66: Червякова Ольга | H66: 17:00-18:00
B67: Гришина Светлана | H67: 18:00-19:00
B68: Гришина Светлана | C68: Restream | D68: Завершен | G68: Здравствуйте. Не работает стрим из obs, пропуска кадров нет, но до рестрима поток не доходит Сигнал есть, а кпртинки нету рестрим не работает, трафик с обс уходит, а вывода нет | H68: 19:00-20:00
B69: Гришина Светлана | C69: Restream | D69: Завершен | G69: А есть у кого такая проблема, что ОБС не с первого раза стрим стартует, и приходится несколько раз вписывать ключ потока и url-адрес? Напрямую всегда все нормально, только с Рестрим такая штука. И происходило это на разных версиях ОБСа и Windows. | H69: 20:00-21:00
B70: Гришина Светлана | H70: 21:00-22:00
B71: Гришина Светлана | H71: 22:00-23:00
A72: 45906 | B72: Червякова Ольга | C72: МОНИКИ | D72: Завершен | G72: Доброе утро! в 10-00 у меня лекция. Не могу войти в свой аккаунт | H72: 9:00-10:00
B73: Червякова Ольга | C73: КХЛ | D73: Завершен | G73: Подскажите, у меня подписка на одну команду? | H73: 10:00-11:00
B74: Червякова Ольга | H74: 11:00-12:00
B75: Червякова Ольга | H75: 12:00-13:00
B76: Червякова Ольга | H76: 13:00-14:00
B77: Червякова Ольга | H77: 14:00-15:00
B78: Червякова Ольга | H78: 15:00-16:00
B79: Червякова Ольга | H79: 16:00-17:00
B80: Гришина Светлана | H80: 17:00-18:00
B81: Гришина Светлана | H81: 18:00-19:00
B82: Червякова Ольга | H82: 19:00-20:00
B83: Червякова Ольга | H83: 20:00-21:00
B84: Червякова Ольга | H84: 21:00-22:00
B85: Гришина Светлана | H85: 22:00-23:00
A86: 45907 | B86: Червякова Ольга | H86: 9:00-10:00
B87: Червякова Ольга | H87: 10:00-11:00
B88: Червякова Ольга | H88: 11:00-12:00
B89: Червякова Ольга | H89: 12:00-13:00
B90: Червякова Ольга | H90: 13:00-14:00
B91: Червякова Ольга | H91: 14:00-15:00
B92: Червякова Ольга | H92: 15:00-16:00
B93: Червякова Ольга | H93: 16:00-17:00
B94: Червякова Ольга | C94: Restream | D94: Завершен | G94: Здравствуйте, не подключается к youtube - пишет Ошибка авторизации на платформе: youtube, время: 2025-09-07T17:34MSK | H94: 17:00-18:00
B95: Щемелинин Владислав | H95: 18:00-19:00
B96: Щемелинин Владислав | H96: 19:00-20:00
B97: Щемелинин Владислав | H97: 20:00-21:00
B98: Щемелинин Владислав | H98: 21:00-22:00
B99: Щемелинин Владислав | H99: 22:00-23:00
A100: 45908 | B100: Червякова Ольга | H100: 9:00-10:00
...

Sheet Август 25
B1: Ответственный | C1: Клиент | D1: Статус обращения | E1: Срок решения и комментарий | F1: Решение (ссылка на тикет/ссылка на документацию) | G1: Обращение клиента | H1: Время | I1: Конышев | J1: Макогонюк | K1: Удалов | L1: Шавло | M1: Соловьёв | N1: Червякова | O1: Толкачев | P1: Макаров | Q1: Курасов
A2: 45870 | B2: Алексеева Александра | H2: 9:00-10:00
B3: Алексеева Александра | H3: 10:00-11:00
B4: Алексеева Александра | H4: 11:00-12:00
B5: Алексеева Александра | H5: 12:00-13:00
B6: Червякова Ольга | C6: МатчТВ | D6: Завершен | E6: По данному вопросу необхоимо писать Максиму Крылову | G6: Добрый день. У нас не загружается админка вебкастера | H6: 13:00-14:00
B7: Червякова Ольга | H7: 14:00-15:00
B8: Червякова Ольга | H8: 15:00-16:00
B9: Червякова Ольга | H9: 16:00-17:00
B10: Червякова Ольга | C10: Ifree | D10: Завершен | G10: Коллеги, добрый день. https://ifree.webcaster.pro/client/video_files/533693 - просьба вырезать кадры с 00:00:00 по 00:00:02, т.е. информация о возрастном ограничении показываться не должна | H10: 17:00-18:00
B11: Щемелинин Владислав | H11: 18:00-19:00
B12: Щемелинин Владислав | C12: Ifree | D12: Завершен | G12: Коллеги, добрый день. https://ifree.webcaster.pro/client/video_files/533693 - просьба вырезать кадры с 00:00:00 по 00:00:02, т.е. информация о возрастном ограничении показываться не должна | H12: 19:00-20:00
B13: Щемелинин Владислав | H13: 20:00-21:00
B14: Щемелинин Владислав | H14: 21:00-22:00
B15: Щемелинин Владислав | H15: 22:00-23:00
A16: 45871 | B16: Алексеева Александра | H16: 9:00-10:00
B17: Алексеева Александра | H17: 10:00-11:00
B18: Алексеева Александра | H18: 11:00-12:00
B19: Алексеева Александра | H19: 12:00-13:00
B20: Алексеева Александра | H20: 13:00-14:00
B21: Алексеева Александра | H21: 14:00-15:00
B22: Червякова Ольга | H22: 15:00-16:00
B23: Гришина Светлана | H23: 16:00-17:00
B24: Щемелинин Владислав | H24: 17:00-18:00
B25: Щемелинин Владислав | H25: 18:00-19:00
B26: Червякова Ольга | H26: 19:00-20:00
B27: Червякова Ольга | H27: 20:00-21:00
B28: Червякова Ольга | H28: 21:00-22:00
B29: Червякова Ольга | H29: 22:00-23:00
A30: 45872 | B30: Алексеева Александра | H30: 9:00-10:00
B31: Алексеева Александра | H31: 10:00-11:00
B32: Алексеева Александра | C32: Restream | D32: Завершен | E32: были перебои в тг | G32: Добрый день. Подскажите, уже долгое время наблюдаем проблему, при запуске рестрима на телеграмм, он начинает работать часа через пол. Как можно решить данную проблему? | H32: 11:00-12:00
B33: Алексеева Александра | H33: 12:00-13:00
B34: Червякова Ольга | H34: 13:00-14:00
B35: Червякова Ольга | H35: 14:00-15:00
B36: Гришина Светлана | H36: 15:00-16:00
B37: Червякова Ольга | H37: 16:00-17:00
B38: Червякова Ольга | C38: МатчТВ | D38: Завершен | G38: @Vozimer @radlibek @Vadim_Ilyin Всем привет! а для старых Самсунгов ничего не меняли? Сегодня уже 4-я жалоба по приложению версии 3.8 (старые самсунги) такого плана. Эфиры не работают, а ппв работает нормально | H38: 17:00-18:00
B39: Щемелинин Владислав | H39: 18:00-19:00
B40: Щемелинин Владислав | H40: 19:00-20:00
B41: Щемелинин Владислав | H41: 20:00-21:00
B42: Щемелинин Владислав | H42: 21:00-22:00
B43: Щемелинин Владислав | H43: 22:00-23:00
A44: 45873 | B44: Червякова Ольга | H44: 9:00-10:00
B45: Червякова Ольга | H45: 10:00-11:00
B46: Червякова Ольга | H46: 11:00-12:00
B47: Червякова Ольга | C47: МатчТВ | D47: Завершен | G47: Коллеги, добрый день! У нас стейдж лежит https://admin.video.matchtv.zxz.su/admin посмотрите плиз | H47: 12:00-13:00
B48: Червякова Ольга | C48: ТВСтарт | D48: Завершен | G48: Здравствуйте! Сейчас хотим потестить поток срт от нас к вам. Подскажите, пожалуйста, есть ли инструменты контроля качества потока (по картинке, по звуку), мониторинг артефактов/ошибок? | H48: 13:00-14:00
B49: Червякова Ольга | C49: Ifree | D49: Завершен | G49: Добрый день! Поглядите пожалуйста уже долгое время вот здесь стоит 33% всего конвертации https://ifree.webcaster.pro/client/video_files/1145130 | H49: 14:00-15:00
B50: Червякова Ольга | C50: Restream | D50: Завершен | G50: Регистрацию в реестре РКН имеете? | H50: 15:00-16:00
B51: Червякова Ольга | H51: 16:00-17:00
B52: Червякова Ольга | C52: Мокси | D52: Завершен | G52: Добрый день, скажите, а есть ли возможность трансляции, которая была вчера сделать окончание раньше чем она закончилась? | H52: 17:00-18:00
B53: Червякова Ольга | H53: 18:00-19:00
B54: Щемелинин Владислав | H54: 19:00-20:00
B55: Щемелинин Владислав | H55: 20:00-21:00
B56: Щемелинин Владислав | H56: 21:00-22:00
B57: Щемелинин Владислав | H57: 22:00-23:00
A58: 45874 | B58: Алексеева Александра | H58: 9:00-10:00
B59: Алексеева Александра | H59: 10:00-11:00
B60: Алексеева Александра | H60: 11:00-12:00
B61: Алексеева Александра | H61: 12:00-13:00
B62: Червякова Ольга | H62: 13:00-14:00
B63: Червякова Ольга | C63: МатчТВ | D63: Завершен | E63: Матч сделал другую склейку, информацию по обращению передана Саше в тикет с архивацей контента матч тв | F63: https://rdm.inventos.ru/issues/160447 | G63: Добрый день! Нам нужно скачать обзор. Сколько еще времени займет устранение бага? | H63: 14:00-15:00
B64: Червякова Ольга | H64: 15:00-16:00
B65: Червякова Ольга | H65: 16:00-17:00
B66: Червякова Ольга | H66: 17:00-18:00
B67: Щемелинин Владислав | H67: 18:00-19:00
B68: Щемелинин Владислав | H68: 19:00-20:00
B69: Щемелинин Владислав | H69: 20:00-21:00
B70: Щемелинин Владислав | H70: 21:00-22:00
B71: Щемелинин Владислав | H71: 22:00-23:00
A72: 45875 | B72: Алексеева Александра | H72: 9:00-10:00
B73: Алексеева Александра | H73: 10:00-11:00
B74: Алексеева Александра | H74: 11:00-12:00
B75: Червякова Ольга | H75: 12:00-13:00
B76: Червякова Ольга | H76: 13:00-14:00
B77: Червякова Ольга | H77: 14:00-15:00
B78: Червякова Ольга | H78: 15:00-16:00
B79: Червякова Ольга | H79: 16:00-17:00
B80: Червякова Ольга | H80: 17:00-18:00
H81: 18:00-19:00
B82: Кузнецова Алиса | H82: 19:00-20:00
B83: Кузнецова Алиса | H83: 20:00-21:00
B84: Кузнецова Алиса | H84: 21:00-22:00
B85: Кузнецова Алиса | H85: 22:00-23:00
A86: 45876 | B86: Алексеева Александра | H86: 9:00-10:00
B87: Алексеева Александра | H87: 10:00-11:00
B88: Алексеева Александра | H88: 11:00-12:00
B89: Алексеева Александра | H89: 12:00-13:00
B90: Червякова Ольга | C90: МатчТВ | D90: Завершен | G90: можете запустить трансляцию https://admin.video.matchtv.zxz.su/client/channels/1/watch?autostart=1 | H90: 13:00-14:00
B91: Червякова Ольга | H91: 14:00-15:00
B92: Червякова Ольга | H92: 15:00-16:00
B93: Червякова Ольга | H93: 16:00-17:00
B94: Червякова Ольга | H94: 17:00-18:00
B95: Щемелинин Владислав | H95: 18:00-19:00
B96: Щемелинин Владислав | H96: 19:00-20:00
B97: Щемелинин Владислав | H97: 20:00-21:00
B98: Щемелинин Владислав | H98: 21:00-22:00
B99: Щемелинин Владислав | H99: 22:00-23:00
A100: 45877 | B100: Червякова Ольга | H100: 9:00-10:00
...

Sheet Март 26
A1: Дата | B1: Ответственный | C1: Клиент | D1: Статус обращения | E1: Срок решения и комментарий | F1: Решение (ссылка на тикет/ссылка на документацию) | G1: Обращение клиента | H1: Время | I1: Статус внесения обращения в Obsidian | J1: Ссылка на Merge Request
A2: 46082 | B2: Мишина Анна | H2: 9:00-10:00
B3: Мишина Анна | H3: 10:00-11:00
B4: Мишина Анна | H4: 11:00-12:00
B5: Мишина Анна | H5: 12:00-13:00
B6: Мишина Анна | C6: МатчТВ | D6: Создан тикет | E6: дополнила тикет | G6: Здравствуйте! Со слов пользователя: Качество в настройках выставлено 1080 и судя по плееру с FHD оно не меняется, но по качеству это даже не 720. Смотрю сейчас матч Динамо-Крылья https://matchtv.ru/football/rpl/552400857-dinamo-kryliasovetov-01-03-2026 | H6: 13:00-14:00
B7: Мишина Анна | H7: 14:00-15:00
B8: Мишина Анна | H8: 15:00-16:00
B9: Мишина Анна | H9: 16:00-17:00
B10: Мишина Анна | C10: Restream | D10: В работе | G10: "да. запустил тестовую трансляцию через осмо покет 2. Указал ключ потока в приложении, но эфир не идет." | H10: 17:00-18:00
B11: Мишина Анна | H11: 18:00-19:00
B12: Мишина Анна | H12: 19:00-20:00
B13: Мишина Анна | C13: Restream | D13: В работе | E13: задал много вопросов, хочет тариф, жду ответа | G13: Здравствуйте! | H13: 20:00-21:00
B14: Мишина Анна | H14: 21:00-22:00
B15: Мишина Анна | H15: 22:00-23:00
A16: 46083 | B16: Червякова Ольга | H16: 9:00-10:00
B17: Червякова Ольга | C17: МатчТВ | D17: Создан тикет | E17: во всех таких обращениях всегда создаем тикет на Данилу Аленичева | G17: Добрый день! Пользователь PnUW8XbeT4y3syQ2XO6H4w в приложении на Смарт ТВ при попытке смотреть прямой эфир каналов Матч Премьер и Матч ТВ получает ошибку «не удалось загрузить видео» Другие приложения например ОККО на данном ТВ работают. Перезапуск ТВ по питанию результатов не дал. Смарт ТВ Samsung | H17: 10:00-11:00 | I17: Не требует инструкции
B18: Червякова Ольга | H18: 11:00-12:00
B19: Червякова Ольга | C19: МОНИКИ | D19: Завершен | E19: не вернулся с ос | G19: Здравствуйте, пришлите, пожалуйста, скриншот как у вас отображается | H19: 12:00-13:00 | I19: Не требует инструкции
B20: Червякова Ольга | H20: 13:00-14:00
B21: Червякова Ольга | H21: 14:00-15:00
B22: Червякова Ольга | H22: 15:00-16:00
B23: Червякова Ольга | H23: 16:00-17:00
B24: Червякова Ольга | H24: 17:00-18:00
B25: Червякова Ольга | H25: 18:00-19:00
B26: Червякова Ольга | C26: МХЛ | D26: Завершен | E26: была повышенная нагрузка на платформу | G26: У меня еле-еле прогружаются странницы, а у коллег весит экспорт | H26: 19:00-20:00 | I26: Добавлена | J26: https://gitlab.inventos.ru/knowledge-base/obsidian/-/merge_requests/396/diffs#c006b4b0649e180e6fa92f7a904040e260a2df29
B27: Червякова Ольга | C27: КХЛ | D27: Завершен | E27: была повышенная нагрузка на платформу | G27: Приветствую! Яндекс жалуется на проблемы с экспортом | H27: 20:00-21:00 | I27: Добавлена | J27: https://gitlab.inventos.ru/knowledge-base/obsidian/-/merge_requests/396/diffs#c006b4b0649e180e6fa92f7a904040e260a2df29
B28: Червякова Ольга | H28: 21:00-22:00
B29: Червякова Ольга | H29: 22:00-23:00
A30: 46084 | B30: Червякова Ольга | H30: 9:00-10:00
B31: Червякова Ольга | H31: 10:00-11:00
B32: Червякова Ольга | H32: 11:00-12:00
B33: Червякова Ольга | H33: 12:00-13:00
B34: Червякова Ольга | H34: 13:00-14:00
B35: Червякова Ольга | H35: 14:00-15:00
B36: Червякова Ольга | C36: МатчТВ | D36: Завершен | E36: Должно быть, это ожидаемое поведение в приложениях на телевизорах. В расписании прямого эфира карточки прошедших событий видимо отображаются только для информации. То есть, из расписания канала нельзя посмотреть прошедшие события с этого канала. Можно посмотреть только live. Ни на Матч Премьер, ни на другом канале | G36: Добрый день! У пользователя AUDyPZtKnvEg7wHoyUKiFz на Смарт ТВ Самсунг 19_MUSEL_UHD_BASIC в приложении недоступен просмотр архива канала Матч Премьер. Прямой эфир работает. Проблема только на Смарт ТВ. Со слов пользователя: Открываю расписание вчерашнее и выбираю перенесенный матч (впрочем любая старая трансляция выбирается) но нажимая на ОК или пуск с пульта трансляция не стартует. А текущая трансляция запускается. Приложение пользователь переустановил, не помогло. | H36: 15:00-16:00 | I36: Добавлена | J36: https://gitlab.inventos.ru/knowledge-base/obsidian/-/merge_requests/396/diffs#c006b4b0649e180e6fa92f7a904040e260a2df29
B37: Червякова Ольга | C37: КХЛ | D37: Завершен | E37: инструкция по замене видео уже есть | G37: сможете, пожалуйста. забрать матч сочи - торпедо от 01.03 по ссылке https://disk.khl.ru/s/LAmF6mqYJdq2HYp | H37: 16:00-17:00 | I37: Не требует инструкции
B38: Червякова Ольга | H38: 17:00-18:00
B39: Червякова Ольга | H39: 18:00-19:00
B40: Червякова Ольга | H40: 19:00-20:00
B41: Червякова Ольга | H41: 20:00-21:00
B42: Червякова Ольга | H42: 21:00-22:00
B43: Червякова Ольга | H43: 22:00-23:00
A44: 46085 | B44: Червякова Ольга | H44: 9:00-10:00
B45: Червякова Ольга | H45: 10:00-11:00
B46: Червякова Ольга | H46: 11:00-12:00
B47: Червякова Ольга | H47: 12:00-13:00
B48: Червякова Ольга | H48: 13:00-14:00
B49: Червякова Ольга | H49: 14:00-15:00
B50: Червякова Ольга | H50: 15:00-16:00
B51: Червякова Ольга | H51: 16:00-17:00
B52: Червякова Ольга | H52: 17:00-18:00
B53: Червякова Ольга | H53: 18:00-19:00
B54: Червякова Ольга | H54: 19:00-20:00
B55: Гришина Светлана | H55: 20:00-21:00
B56: Червякова Ольга | H56: 21:00-22:00
B57: Червякова Ольга | H57: 22:00-23:00
A58: 46086 | B58: Гришина Светлана | H58: 9:00-10:00
B59: Гришина Светлана | H59: 10:00-11:00
B60: Гришина Светлана | C60: МОНИКИ | D60: Завершен | G60: Кафедра ОВП (семейной медицины). ПК Профпатология. Проведение экспертизы профессиональных заболеваний. (05.03.2026) - https://wbnr.su:50443/rooms?meet=ca572237-4ecd-4da9-b12e-aa4794604457 - Отсутствуют участники | H60: 11:00-12:00 | I60: Не требует инструкции
B61: Гришина Светлана | H61: 12:00-13:00
B62: Гришина Светлана | H62: 13:00-14:00
B63: Гришина Светлана | H63: 14:00-15:00
B64: Гришина Светлана | H64: 15:00-16:00
B65: Гришина Светлана | C65: МатчТВ | D65: Завершен | E65: перехватил Коснстантин | G65: Добрый день! Пользователю на ПК во всех браузерах недоступен просмотр на Сайте Матч ТВ При попытке просмотре прямого эфира Матч ТВ или любого обзора матча получает ошибку Сайт video.matchtv.ru отправил недействительный ответ. ОСwin 10 pro Chrome Версия: 145.0.7632.117 (официальная сборка) (64 бит) | H65: 16:00-17:00
B66: Гришина Светлана | H66: 17:00-18:00
B67: Гришина Светлана | H67: 18:00-19:00
B68: Гришина Светлана | H68: 19:00-20:00
B69: Гришина Светлана | H69: 20:00-21:00
B70: Гришина Светлана | H70: 21:00-22:00
B71: Гришина Светлана | H71: 22:00-23:00
A72: 46087 | B72: Червякова Ольга | C72: Новый клиент | D72: Завершен | E72: передала Насте | G72: Добрый день, смогу ли использовать вашу площадку для своих целей ? Мне нужна защита от скачиваний 360 градусных видео в качестве 8к 30\60фпс . | H72: 9:00-10:00
B73: Червякова Ольга | H73: 10:00-11:00
B74: Червякова Ольга | H74: 11:00-12:00
B75: Червякова Ольга | H75: 12:00-13:00
B76: Червякова Ольга | H76: 13:00-14:00
B77: Червякова Ольга | H77: 14:00-15:00
B78: Червякова Ольга | H78: 15:00-16:00
B79: Червякова Ольга | C79: МатчТВ | D79: Завершен | E79: ответил Константин | G79: Здравствуйте! Вот это проблема снова повторилась. Какие сейчас актуальные подсети для просмотра Видео? | H79: 16:00-17:00
B80: Червякова Ольга | H80: 17:00-18:00
B81: Червякова Ольга | C81: МатчТВ | D81: Завершен | E81: не вернулся с ос | F81: попросили посмотреть с компьютера и записать хар файл | G81: Добрый день! У пользователя 4mA5BwkieD34fhLAkABppi сегодня приложение и сайт перестали работать через Wi-Fi. Через LTE все работает. Роутер перезагружал, не помогло. Ошибки нет, просто черный экран на сайте и в приложении на Смарт ТВ. Все другие сайты и приложения работают. Устройства: Poco m6 pro, android 15 Google w2 приставка смарт ТВ, андроид 11 Droidlogicx98plus, приставка смарт ТВ, андроид 11. IP: 45.80.46.9 Провайдер UpiterTelecom Ltd | H81: 18:00-19:00 | I81: Не требует инструкции
B82: Червякова Ольга | C82: МатчТВ | D82: Завершен | E82: не вернулся с ос | F82: попросили посмотреть с компьютера и записать хар файл | G82: Еще один пользователь с такой же проблемой olgMHOSlRZKWh_wVpZ0Nqw Приложение Матч ТВ с сегодняшнего дня работает только от мобильной сети на смартфоне. А от роутера вай-фай не работает ни на смартфоне ни в смартТВ. При этом все остальные приложения нормально работают от вайфай на смартТВ и в смартфоне. Проблема появилась после 17.00 6 марта Провайдер ETelecom | H82: 19:00-20:00 | I82: Не требует инструкции
B83: Червякова Ольга | H83: 20:00-21:00
B84: Червякова Ольга | H84: 21:00-22:00
B85: Червякова Ольга | H85: 22:00-23:00
A86: 46088 | B86: Гришина Светлана | H86: 9:00-10:00
B87: Гришина Светлана | H87: 10:00-11:00
B88: Гришина Светлана | H88: 11:00-12:00
B89: Гришина Светлана | H89: 12:00-13:00
B90: Гришина Светлана | H90: 13:00-14:00
B91: Гришина Светлана | H91: 14:00-15:00
B92: Гришина Светлана | H92: 15:00-16:00
B93: Мишина Анна | H93: 16:00-17:00
B94: Мишина Анна | H94: 17:00-18:00
B95: Мишина Анна | H95: 18:00-19:00
B96: Мишина Анна | H96: 19:00-20:00
B97: Мишина Анна | H97: 20:00-21:00
B98: Мишина Анна | H98: 21:00-22:00
B99: Мишина Анна | H99: 22:00-23:00
A100: 46089 | B100: Червякова Ольга | H100: 9:00-10:00
...

Sheet Январь 26
A1: Дата | B1: Ответственный | C1: Клиент | D1: Статус обращения | E1: Срок решения и комментарий | F1: Решение (ссылка на тикет/ссылка на документацию) | G1: Обращение клиента | H1: Время | I1: Статус внесения обращения в Obsidian | J1: Ссылка на Merge Request
A2: 46023 | B2: Мишина Анна | H2: 9:00-10:00
B3: Мишина Анна | H3: 10:00-11:00
B4: Мишина Анна | H4: 11:00-12:00
B5: Мишина Анна | H5: 12:00-13:00
B6: Мишина Анна | H6: 13:00-14:00
B7: Червякова Ольга | H7: 14:00-15:00
B8: Червякова Ольга | H8: 15:00-16:00
B9: Червякова Ольга | H9: 16:00-17:00
B10: Червякова Ольга | H10: 17:00-18:00
B11: Червякова Ольга | H11: 18:00-19:00
B12: Червякова Ольга | H12: 19:00-20:00
B13: Червякова Ольга | H13: 20:00-21:00
B14: Червякова Ольга | H14: 21:00-22:00
B15: Червякова Ольга | C15: Restream | D15: Завершен | G15: разрывается стрим на часит прямо сейчас | H15: 22:00-23:00 | I15: Не требует инструкции
A16: 46024 | B16: Мишина Анна | C16: Restream | D16: Завершен | E16: а мы хз что с ней делать, относится к обращениям от 28.12 и всем последующим подобным | G16: уже 9 кусков, вместо одной полноценной записи стриа | H16: 9:00-10:00 | I16: Добавлена
B17: Мишина Анна | H17: 10:00-11:00
B18: Мишина Анна | H18: 11:00-12:00
B19: Мишина Анна | H19: 12:00-13:00
B20: Мишина Анна | H20: 13:00-14:00
B21: Мишина Анна | H21: 14:00-15:00
B22: Мишина Анна | C22: Restream | D22: Завершен | E22: внесла | G22: здравствуйте. Как мне удалить аккаунт? | H22: 15:00-16:00 | I22: Добавлена
B23: Червякова Ольга | H23: 16:00-17:00
B24: Червякова Ольга | H24: 17:00-18:00
B25: Червякова Ольга | H25: 18:00-19:00
B26: Червякова Ольга | H26: 19:00-20:00
B27: Червякова Ольга | H27: 20:00-21:00
B28: Червякова Ольга | H28: 21:00-22:00
B29: Червякова Ольга | H29: 22:00-23:00
A30: 46025 | B30: Мишина Анна | H30: 9:00-10:00
B31: Мишина Анна | C31: Restream | D31: Завершен | E31: тарифчик кастомный по готовой инструкции | G31: моя учетка ugaidv@gmail.com добавьте пжлст возможность иметь три источника. возможно понадобится сегодня. | H31: 10:00-11:00 | I31: Добавлена
B32: Мишина Анна | H32: 11:00-12:00
B33: Мишина Анна | H33: 12:00-13:00
B34: Мишина Анна | H34: 13:00-14:00
B35: Мишина Анна | H35: 14:00-15:00
B36: Мишина Анна | H36: 15:00-16:00
B37: Мишина Анна | H37: 16:00-17:00
B38: Мишина Анна | H38: 17:00-18:00
B39: Мишина Анна | H39: 18:00-19:00
B40: Мишина Анна | H40: 19:00-20:00
B41: Мишина Анна | H41: 20:00-21:00
B42: Мишина Анна | H42: 21:00-22:00
B43: Мишина Анна | H43: 22:00-23:00
A44: 46026 | B44: Червякова Ольга | H44: 9:00-10:00
B45: Червякова Ольга | H45: 10:00-11:00
B46: Червякова Ольга | H46: 11:00-12:00
B47: Червякова Ольга | C47: Restream | D47: Завершен | G47: Со скольки камер я могу стримить на своем тарифе? | H47: 12:00-13:00 | I47: Не требует инструкции
B48: Червякова Ольга | H48: 13:00-14:00
B49: Червякова Ольга | H49: 14:00-15:00
B50: Червякова Ольга | H50: 15:00-16:00
B51: Червякова Ольга | H51: 16:00-17:00
B52: Червякова Ольга | H52: 17:00-18:00
B53: Червякова Ольга | C53: МатчТВ | D53: Завершен | E53: пользователь не вернулся с ос | G53: Добрый вечер! У пользователя на сайте Матч ТВ при просмотре ошибка. Со слов пользователя пробовал в разных браузерах. | H53: 18:00-19:00 | I53: Не требует инструкции
B54: Червякова Ольга | H54: 19:00-20:00
B55: Червякова Ольга | H55: 20:00-21:00
B56: Червякова Ольга | H56: 21:00-22:00
B57: Червякова Ольга | H57: 22:00-23:00
A58: 46027 | B58: Червякова Ольга | H58: 9:00-10:00
B59: Червякова Ольга | H59: 10:00-11:00
B60: Червякова Ольга | C60: Restream | D60: Завершен | G60: коллеги, зачем здесь два столбика? теряются же названия каналов | H60: 11:00-12:00
B61: Червякова Ольга | H61: 12:00-13:00
B62: Червякова Ольга | H62: 13:00-14:00
B63: Мишина Анна | H63: 14:00-15:00
B64: Мишина Анна | H64: 15:00-16:00
B65: Мишина Анна | H65: 16:00-17:00
B66: Мишина Анна | H66: 17:00-18:00
B67: Мишина Анна | H67: 18:00-19:00
B68: Мишина Анна | H68: 19:00-20:00
B69: Мишина Анна | H69: 20:00-21:00
B70: Мишина Анна | H70: 21:00-22:00
B71: Мишина Анна | C71: Restream | D71: Завершен | E71: дело было в ссылке, подливала такой тип обращений | G71: Добрый вечер, почему то ен стримит на кик, в чем может быть проблема? | H71: 22:00-23:00 | I71: Добавлена
A72: 46028 | B72: Червякова Ольга | H72: 9:00-10:00
B73: Червякова Ольга | H73: 10:00-11:00
B74: Червякова Ольга | H74: 11:00-12:00
B75: Червякова Ольга | C75: Ifree | D75: Завершен | G75: Коллеги, добрый день. https://ifree.webcaster.pro/client/video_files/109691 - можете, пожалуйста, для этого видео увеличить громкость? Сейчас приходится выкручивать на 80% звук, чтобы услышать нормально речь | H75: 12:00-13:00 | I75: Добавлена
B76: Червякова Ольга | H76: 13:00-14:00
B77: Червякова Ольга | H77: 14:00-15:00
B78: Червякова Ольга | H78: 15:00-16:00
B79: Червякова Ольга | H79: 16:00-17:00
B80: Червякова Ольга | H80: 17:00-18:00
B81: Червякова Ольга | H81: 18:00-19:00
B82: Червякова Ольга | H82: 19:00-20:00
B83: Червякова Ольга | H83: 20:00-21:00
B84: Червякова Ольга | H84: 21:00-22:00
B85: Червякова Ольга | H85: 22:00-23:00
A86: 46029 | B86: Мишина Анна | C86: Restream | D86: Завершен | E86: Саше передала, пока ничего неизвестно | G86: Здравствуйте, в OBS выбрал сервер "Custom", ввёл rtmp и ключ потока На сайте сигнала нет, при старте стрима в OBS выдаёт вот это, в чем проблема? | H86: 9:00-10:00 | I86: Не требует инструкции
B87: Мишина Анна | C87: Restream | D87: Завершен | E87: тоже передала, тоже ничего не сказал пока что(( | G87: Не работает рестрим что такое Покупаю платный и уже какой раз хочу запустить и не работает! | H87: 10:00-11:00 | I87: Не требует инструкции
B88: Мишина Анна | H88: 11:00-12:00
B89: Мишина Анна | H89: 12:00-13:00
B90: Мишина Анна | H90: 13:00-14:00
B91: Мишина Анна | H91: 14:00-15:00
B92: Мишина Анна | H92: 15:00-16:00
B93: Мишина Анна | H93: 16:00-17:00
B94: Мишина Анна | H94: 17:00-18:00
B95: Мишина Анна | H95: 18:00-19:00
B96: Мишина Анна | H96: 19:00-20:00
B97: Мишина Анна | H97: 20:00-21:00
B98: Мишина Анна | H98: 21:00-22:00
B99: Мишина Анна | H99: 22:00-23:00
A100: 46030 | B100: Червякова Ольга | H100: 9:00-10:00
...

Sheet Апрель 26
A1: Дата | B1: Ответственный | C1: Клиент | D1: Статус обращения | E1: Срок решения и комментарий | F1: Решение (ссылка на тикет/ссылка на документацию) | G1: Обращение клиента | H1: Время | I1: Статус внесения обращения в Obsidian | J1: Ссылка на Merge Request
A2: 46113 | B2: Гришина Светлана | H2: 9:00-10:00
B3: Гришина Светлана | H3: 10:00-11:00
B4: Гришина Светлана | H4: 11:00-12:00
B5: Червякова Ольга | H5: 12:00-13:00
B6: Червякова Ольга | H6: 13:00-14:00
B7: Червякова Ольга | H7: 14:00-15:00
B8: Червякова Ольга | H8: 15:00-16:00
B9: Мишина Анна | H9: 16:00-17:00
B10: Мишина Анна | H10: 17:00-18:00
B11: Мишина Анна | H11: 18:00-19:00
B12: Мишина Анна | H12: 19:00-20:00
B13: Мишина Анна | H13: 20:00-21:00
B14: Мишина Анна | H14: 21:00-22:00
B15: Мишина Анна | H15: 22:00-23:00
A16: 46114 | B16: Гришина Светлана | H16: 9:00-10:00
B17: Гришина Светлана | H17: 10:00-11:00
B18: Гришина Светлана | H18: 11:00-12:00
B19: Гришина Светлана | H19: 12:00-13:00
B20: Гришина Светлана | H20: 13:00-14:00
B21: Гришина Светлана | H21: 14:00-15:00
B22: Гришина Светлана | H22: 15:00-16:00
B23: Гришина Светлана | H23: 16:00-17:00
B24: Гришина Светлана | H24: 17:00-18:00
B25: Гришина Светлана | H25: 18:00-19:00
B26: Гришина Светлана | H26: 19:00-20:00
B27: Гришина Светлана | H27: 20:00-21:00
B28: Гришина Светлана | H28: 21:00-22:00
B29: Гришина Светлана | H29: 22:00-23:00
A30: 46115 | B30: Мишина Анна | H30: 9:00-10:00
B31: Мишина Анна | H31: 10:00-11:00
B32: Мишина Анна | H32: 11:00-12:00
B33: Мишина Анна | H33: 12:00-13:00
B34: Мишина Анна | H34: 13:00-14:00
B35: Мишина Анна | H35: 14:00-15:00
B36: Мишина Анна | H36: 15:00-16:00
B37: Мишина Анна | H37: 16:00-17:00
B38: Мишина Анна | H38: 17:00-18:00
B39: Мишина Анна | H39: 18:00-19:00
B40: Мишина Анна | H40: 19:00-20:00
B41: Мишина Анна | H41: 20:00-21:00
B42: Мишина Анна | H42: 21:00-22:00
B43: Мишина Анна | H43: 22:00-23:00
A44: 46116 | B44: Мишина Анна | H44: 9:00-10:00
B45: Мишина Анна | H45: 10:00-11:00
B46: Мишина Анна | H46: 11:00-12:00
B47: Мишина Анна | H47: 12:00-13:00
B48: Мишина Анна | H48: 13:00-14:00
B49: Мишина Анна | H49: 14:00-15:00
B50: Мишина Анна | H50: 15:00-16:00
B51: Мишина Анна | H51: 16:00-17:00
B52: Мишина Анна | H52: 17:00-18:00
B53: Мишина Анна | H53: 18:00-19:00
B54: Мишина Анна | H54: 19:00-20:00
B55: Мишина Анна | H55: 20:00-21:00
B56: Мишина Анна | H56: 21:00-22:00
B57: Мишина Анна | H57: 22:00-23:00
A58: 46117 | B58: Мишина Анна | H58: 9:00-10:00
B59: Мишина Анна | H59: 10:00-11:00
B60: Мишина Анна | H60: 11:00-12:00
B61: Мишина Анна | H61: 12:00-13:00
B62: Мишина Анна | H62: 13:00-14:00
B63: Мишина Анна | H63: 14:00-15:00
B64: Мишина Анна | H64: 15:00-16:00
B65: Мишина Анна | H65: 16:00-17:00
B66: Мишина Анна | H66: 17:00-18:00
B67: Мишина Анна | H67: 18:00-19:00
B68: Мишина Анна | H68: 19:00-20:00
B69: Мишина Анна | H69: 20:00-21:00
B70: Мишина Анна | H70: 21:00-22:00
B71: Мишина Анна | H71: 22:00-23:00
A72: 46118 | B72: Червякова Ольга | H72: 9:00-10:00
B73: Червякова Ольга | H73: 10:00-11:00
B74: Червякова Ольга | H74: 11:00-12:00
B75: Червякова Ольга | H75: 12:00-13:00
B76: Червякова Ольга | H76: 13:00-14:00
B77: Червякова Ольга | H77: 14:00-15:00
B78: Червякова Ольга | H78: 15:00-16:00
B79: Червякова Ольга | H79: 16:00-17:00
B80: Червякова Ольга | H80: 17:00-18:00
B81: Червякова Ольга | H81: 18:00-19:00
B82: Червякова Ольга | H82: 19:00-20:00
B83: Червякова Ольга | H83: 20:00-21:00
B84: Червякова Ольга | H84: 21:00-22:00
B85: Червякова Ольга | H85: 22:00-23:00
A86: 46119 | B86: Червякова Ольга | H86: 9:00-10:00
B87: Червякова Ольга | H87: 10:00-11:00
B88: Червякова Ольга | H88: 11:00-12:00
B89: Червякова Ольга | H89: 12:00-13:00
B90: Червякова Ольга | H90: 13:00-14:00
B91: Червякова Ольга | H91: 14:00-15:00
B92: Червякова Ольга | H92: 15:00-16:00
B93: Червякова Ольга | H93: 16:00-17:00
B94: Червякова Ольга | H94: 17:00-18:00
B95: Червякова Ольга | H95: 18:00-19:00
B96: Червякова Ольга | H96: 19:00-20:00
B97: Червякова Ольга | H97: 20:00-21:00
B98: Червякова Ольга | H98: 21:00-22:00
B99: Червякова Ольга | H99: 22:00-23:00
A100: 46120 | B100: Гришина Светлана | H100: 9:00-10:00
...

Sheet Июнь 25
B1: Ответственный | C1: Клиент | D1: Статус обращения | E1: Срок решения и комментарий | F1: Решение (ссылка на тикет/ссылка на документацию) | G1: Обращение клиента | H1: Время | I1: Конышев | J1: Макогонюк | K1: Удалов | L1: Шавло | M1: Соловьёв | N1: Червякова | O1: Толкачев | P1: Макаров | Q1: Курасов
A2: 45809 | B2: Червякова Ольга | C2: Restream | D2: Завершен | G2: на каком тарифе возможен выбор количества битрейта на каждый из каналов? | H2: 9:00-10:00
B3: Червякова Ольга | C3: МатчТВ | D3: Завершен | G3: Доброе утро коллеги. можете посмотреть канал srt17 на него нам подают сигнал, со слов поставщика но я ничего не вижу в админке | H3: 10:00-11:00
B4: Червякова Ольга | H4: 11:00-12:00
B5: Червякова Ольга | H5: 12:00-13:00
B6: Червякова Ольга | H6: 13:00-14:00
B7: Червякова Ольга | H7: 14:00-15:00
B8: Червякова Ольга | H8: 15:00-16:00
B9: Червякова Ольга | H9: 16:00-17:00
B10: Червякова Ольга | H10: 17:00-18:00
B11: Червякова Ольга | C11: Restream | D11: Завершен | F11: Такое поведение бывает, когда программа для стриминга отправляет нам несколько запросов одновременно и перегружает нашу платформу. Мы уже работаем над исправлением этой ситуации. | G11: Появилась такая проблема. Скопировал ключ и сервер в OBS, но трансляция не запускается, пишет - Для текущей службы нет доступного URl-адреса. Два часа назад всё работало. Что может быть? | H11: 18:00-19:00
B12: Червякова Ольга | C12: МатчТВ | D12: Завершен | G12: Максим @konyshevvvv у нас в приложении для тв на трансляции Кубка России, которая сейчас идет, откуда-то вылезло фейковое качество 4К. В потоке этого качества нет | H12: 19:00-20:00
B13: Червякова Ольга | H13: 20:00-21:00
B14: Червякова Ольга | H14: 21:00-22:00
B15: Червякова Ольга | H15: 22:00-23:00
A16: 45810 | B16: Алексеева Александра | C16: МОНИКИ | D16: Завершен | F16: ## Инструкция по решению проблемы Шаг 1: - Описание действий: заходим в админку Webcaster в раздел Главная-Медиа-Видео (https://webcaster.pro/client/all_video ), выбираем клиента Moniki_Ed и вставляем название вебинара. - Результаты: информация о вебинаре Шаг 2: - Описание действий: если вебинар найден, то нажимаем в правом столбике на карандашик и переходим в раздел редактирования. В самом низу нажимаем экспорт в мп4. После экспорта нажимаем "Создать ссылку", копируем ее и отправляем в чат с МОНИКИ - Результаты: ссылка на скачивание вебинара Шаг 3: - Описание действий: если вебинар не найден, то можно обратиться к Шавло Анастасия для уточнения информации. Возможно, запись вебинара не велась или была утеряна. - Результаты: информация о вебинаре | G16: можно ли вытащить эту лекцию? КФиПМД с курсом клинической фармакологии. Комплексный подход к ведению пациентов, получающих антитромботическую терапию. | H16: 9:00-10:00
B17: Алексеева Александра | H17: 10:00-11:00
B18: Алексеева Александра | H18: 11:00-12:00
B19: Алексеева Александра | H19: 12:00-13:00
B20: Алексеева Александра | H20: 13:00-14:00
B21: Червякова Ольга | C21: Restream | D21: Завершен | F21: Направляем пользователя на наш сайт, так как данная информация публикуется там. | G21: мульти чат заработал для кика и ютуба? | H21: 14:00-15:00
B22: Червякова Ольга | H22: 15:00-16:00
B23: Червякова Ольга | H23: 16:00-17:00
B24: Червякова Ольга | H24: 17:00-18:00
B25: Щемелинин Владислав | H25: 18:00-19:00
B26: Щемелинин Владислав | H26: 19:00-20:00
B27: Щемелинин Владислав | H27: 20:00-21:00
B28: Щемелинин Владислав | H28: 21:00-22:00
B29: Щемелинин Владислав | H29: 22:00-23:00
A30: 45811 | B30: Алексеева Александра | H30: 9:00-10:00
B31: Алексеева Александра | H31: 10:00-11:00
B32: Алексеева Александра | H32: 11:00-12:00
B33: Алексеева Александра | H33: 12:00-13:00
B34: Алексеева Александра | H34: 13:00-14:00
B35: Червякова Ольга | H35: 14:00-15:00
B36: Червякова Ольга | H36: 15:00-16:00
B37: Червякова Ольга | H37: 16:00-17:00
B38: Червякова Ольга | H38: 17:00-18:00
B39: Толкачев Егор | H39: 18:00-19:00
B40: Толкачев Егор | C40: Restream | D40: В работе | G40: Здравствуйте, продолжает скакать картинка | H40: 19:00-20:00
B41: Толкачев Егор | H41: 20:00-21:00
B42: Червякова Ольга | H42: 21:00-22:00
B43: Червякова Ольга | H43: 22:00-23:00
A44: 45812 | B44: Алексеева Александра | H44: 9:00-10:00
B45: Алексеева Александра | H45: 10:00-11:00
B46: Кузнецова Алиса | H46: 11:00-12:00
B47: Кузнецова Алиса | H47: 12:00-13:00
B48: Кузнецова Алиса | H48: 13:00-14:00
B49: Червякова Ольга | H49: 14:00-15:00
B50: Червякова Ольга | C50: Restream | D50: Завершен | F50: Уточняем информацию у менеджера проекта Получаем ответ, что данная проблема уже изучается. | G50: У меня обс к сервису не коннектится - подключение спрасывается и обс уходит в бесконечный цикл переподключений. | H50: 15:00-16:00
B51: Червякова Ольга | H51: 16:00-17:00
B52: Червякова Ольга | H52: 17:00-18:00
B53: Щемелинин Владислав | H53: 18:00-19:00
B54: Щемелинин Владислав | H54: 19:00-20:00
B55: Щемелинин Владислав | H55: 20:00-21:00
B56: Щемелинин Владислав | H56: 21:00-22:00
B57: Щемелинин Владислав | H57: 22:00-23:00
A58: 45813 | B58: Алексеева Александра | H58: 9:00-10:00
B59: Алексеева Александра | H59: 10:00-11:00
B60: Алексеева Александра | H60: 11:00-12:00
B61: Алексеева Александра | H61: 12:00-13:00
B62: Алексеева Александра | C62: ОТР | D62: Завершен | E62: Данная роль https://webcaster.pro/admin/roles/545/permissions редактировалась последний раз (кроме сегодня) в 2020 году )) А в тикете https://rdm.inventos.ru/issues/142599 подход к блэкауту был изменен и появились новые галочки в ролях, которые для ОТР никто после релиза видимо в эту роль не поставил. А сами ОТР пользовались последний раз заглушками вручную 06.03.2024, а 25.03.2024 выкатился релиз с их исправлениями. | G62: Ребята, вебкастер, посмотрите пожалуйста поведение на видео от редактора ОТР. складывается впечатлением что ручное управление заглушки не отрабатывает - либо что-то делаем не так | H62: 13:00-14:00
B63: Червякова Ольга | H63: 14:00-15:00
B64: Червякова Ольга | C64: Restream | D64: Завершен | F64: Благодарим за предоставленную информацию | G64: Добрый день. Закрывайте кейс - проблемы всё таки на моей стороне. Она весьма странная и специфичная, но ваш сервис тут точно не при чём. | H64: 15:00-16:00
B65: Червякова Ольга | H65: 16:00-17:00
B66: Червякова Ольга | H66: 17:00-18:00
B67: Червякова Ольга | H67: 18:00-19:00
B68: Червякова Ольга | C68: Restream | D68: Завершен | G68: Здравствуйте! Не транслируется на страницу VK | H68: 19:00-20:00
B69: Червякова Ольга | H69: 20:00-21:00
B70: Червякова Ольга | H70: 21:00-22:00
B71: Червякова Ольга | H71: 22:00-23:00
A72: 45814 | B72: Алексеева Александра | H72: 9:00-10:00
B73: Алексеева Александра | H73: 10:00-11:00
B74: Кузнецова Алиса | H74: 11:00-12:00
B75: Кузнецова Алиса | H75: 12:00-13:00
B76: Кузнецова Алиса | H76: 13:00-14:00
B77: Червякова Ольга | H77: 14:00-15:00
B78: Червякова Ольга | H78: 15:00-16:00
B79: Червякова Ольга | H79: 16:00-17:00
B80: Червякова Ольга | H80: 17:00-18:00
B81: Щемелинин Владислав | H81: 18:00-19:00
B82: Щемелинин Владислав | H82: 19:00-20:00
B83: Щемелинин Владислав | H83: 20:00-21:00
B84: Щемелинин Владислав | H84: 21:00-22:00
B85: Щемелинин Владислав | H85: 22:00-23:00
A86: 45815 | B86: Червякова Ольга | H86: 9:00-10:00
B87: Червякова Ольга | H87: 10:00-11:00
B88: Червякова Ольга | H88: 11:00-12:00
B89: Червякова Ольга | C89: Restream | D89: Завершен | F89: В настоящее время у нас реализована следующая функциональность для работы с вертикальными видео из OBS: При использовании OBS вертикальный стрим передаётся как отдельный поток. В связи с этим мы можем предложить индивидуальный тарифный план, предусматривающий два входящих потока — стандартный и вертикальный. Далее оба потока могут быть транслированы на необходимые вам платформы. | G89: Скажите, а эта фишка тоже будет работать через рестрим? На днях увидел, что твич собирается ввести подобную фичу с обс. Правда не совсем понял, как оно работает... Я слышал, что ютуб сам обрезает твой стрим для того, чтобы он высвечивался в шортс, но не уверен насчёт твича. Может кто-нибудь что-нибудь знает о подробностях? | H89: 12:00-13:00
B90: Червякова Ольга | H90: 13:00-14:00
B91: Червякова Ольга | H91: 14:00-15:00
B92: Червякова Ольга | H92: 15:00-16:00
B93: Червякова Ольга | H93: 16:00-17:00
B94: Червякова Ольга | C94: Restream | D94: Завершен | G94: Добрый день, уже три раза пробую рестрим в Рутуб не получается | H94: 17:00-18:00
B95: Толкачев Егор | H95: 18:00-19:00
B96: Толкачев Егор | H96: 19:00-20:00
B97: Толкачев Егор | H97: 20:00-21:00
B98: Толкачев Егор | H98: 21:00-22:00
B99: Толкачев Егор | H99: 22:00-23:00
A100: 45816 | B100: Червякова Ольга | H100: 9:00-10:00
...

Sheet Июль 25
B1: Ответственный | C1: Клиент | D1: Статус обращения | E1: Срок решения и комментарий | F1: Решение (ссылка на тикет/ссылка на документацию) | G1: Обращение клиента | H1: Время | I1: Конышев | J1: Макогонюк | K1: Удалов | L1: Шавло | M1: Соловьёв | N1: Червякова | O1: Толкачев | P1: Макаров | Q1: Курасов
A2: 45839 | B2: Алексеева Александра | H2: 9:00-10:00
B3: Алексеева Александра | H3: 10:00-11:00
B4: Алексеева Александра | H4: 11:00-12:00
B5: Червякова Ольга | H5: 12:00-13:00
B6: Червякова Ольга | H6: 13:00-14:00
B7: Червякова Ольга | H7: 14:00-15:00
B8: Толкачев Егор | H8: 15:00-16:00
B9: Толкачев Егор | H9: 16:00-17:00
B10: Толкачев Егор | H10: 17:00-18:00
B11: Толкачев Егор | H11: 18:00-19:00
B12: Толкачев Егор | H12: 19:00-20:00
B13: Червякова Ольга | H13: 20:00-21:00
B14: Червякова Ольга | H14: 21:00-22:00
B15: Червякова Ольга | H15: 22:00-23:00
A16: 45840 | B16: Алексеева Александра | H16: 9:00-10:00
B17: Алексеева Александра | H17: 10:00-11:00
B18: Алексеева Александра | H18: 11:00-12:00
B19: Червякова Ольга | C19: Новый клиент | D19: Завершен | G19: подскажите сколько сейчас у меня есть места в общем на хостинге? | H19: 12:00-13:00
B20: Червякова Ольга | C20: КХЛ | D20: Создан тикет | G20: Коллеги, заметил один момент на вебкастере. Через поиск хочу найти все голы Виноградова за сезон 24/25 | H20: 13:00-14:00
B21: Червякова Ольга | H21: 14:00-15:00
B22: Червякова Ольга | H22: 15:00-16:00
B23: Червякова Ольга | H23: 16:00-17:00
B24: Червякова Ольга | H24: 17:00-18:00
B25: Щемелинин Владислав | C25: Мокси | D25: Завершен | F25: Мы ранее уже настраивали второй канал, адрес и ключ все еще актуальны. Информацию передавали в личные сообщения | G25: Добрый вечер. Можно на субботу и воскресение организовать 2 канала эфира? Будет две трансляции параллельно | H25: 18:00-19:00
B26: Щемелинин Владислав | C26: Restream | D26: Завершен | F26: При запуске следующей трансляции советуем поставить стандартную или малую задержку. | G26: Что у вас опять с соединением? Ютуб пишет что видеопоток поступает слишком медленно! | H26: 19:00-20:00
B27: Щемелинин Владислав | H27: 20:00-21:00
B28: Щемелинин Владислав | H28: 21:00-22:00
B29: Щемелинин Владислав | H29: 22:00-23:00
A30: 45841 | B30: Алексеева Александра | H30: 9:00-10:00
B31: Алексеева Александра | H31: 10:00-11:00
B32: Алексеева Александра | H32: 11:00-12:00
B33: Червякова Ольга | H33: 12:00-13:00
B34: Червякова Ольга | H34: 13:00-14:00
B35: Червякова Ольга | H35: 14:00-15:00
B36: Червякова Ольга | H36: 15:00-16:00
B37: Червякова Ольга | H37: 16:00-17:00
B38: Червякова Ольга | H38: 17:00-18:00
B39: Червякова Ольга | H39: 18:00-19:00
B40: Червякова Ольга | H40: 19:00-20:00
B41: Толкачев Егор | H41: 20:00-21:00
B42: Толкачев Егор | H42: 21:00-22:00
B43: Толкачев Егор | C43: Restream | D43: Завершен | G43: А чат с ВК Видео Лайв не работает у вас? | H43: 22:00-23:00
A44: 45842 | B44: Алексеева Александра | H44: 9:00-10:00
B45: Алексеева Александра | H45: 10:00-11:00
B46: Алексеева Александра | H46: 11:00-12:00
B47: Алексеева Александра | H47: 12:00-13:00
B48: Алексеева Александра | H48: 13:00-14:00
B49: Толкачев Егор | H49: 14:00-15:00
B50: Толкачев Егор | H50: 15:00-16:00
B51: Толкачев Егор | H51: 16:00-17:00
B52: Толкачев Егор | H52: 17:00-18:00
B53: Щемелинин Владислав | H53: 18:00-19:00
B54: Щемелинин Владислав | H54: 19:00-20:00
B55: Щемелинин Владислав | H55: 20:00-21:00
B56: Щемелинин Владислав | H56: 21:00-22:00
B57: Щемелинин Владислав | H57: 22:00-23:00
A58: 45843 | B58: Червякова Ольга | H58: 9:00-10:00
B59: Червякова Ольга | H59: 10:00-11:00
B60: Червякова Ольга | H60: 11:00-12:00
B61: Червякова Ольга | H61: 12:00-13:00
B62: Червякова Ольга | H62: 13:00-14:00
B63: Червякова Ольга | H63: 14:00-15:00
B64: Червякова Ольга | H64: 15:00-16:00
B65: Червякова Ольга | H65: 16:00-17:00
B66: Червякова Ольга | H66: 17:00-18:00
B67: Червякова Ольга | H67: 18:00-19:00
B68: Червякова Ольга | H68: 19:00-20:00
B69: Гришина Светлана | C69: Restream | D69: Завершен | F69: Объяснила про тарифы по ссылке, Проконсультировала по значению битрейта | G69: Добрый день. Как купить тариф | H69: 20:00-21:00
B70: Гришина Светлана | C70: Restream | D70: Завершен | F70: Предоставила инструкцию по настройке каналов. | G70: Здравствуйте, Не понимаю как привязать каналы | H70: 21:00-22:00
B71: Гришина Светлана | H71: 22:00-23:00
A72: 45844 | B72: Алексеева Александра | H72: 9:00-10:00
B73: Алексеева Александра | H73: 10:00-11:00
B74: Алексеева Александра | H74: 11:00-12:00
B75: Червякова Ольга | H75: 12:00-13:00
B76: Червякова Ольга | H76: 13:00-14:00
B77: Червякова Ольга | H77: 14:00-15:00
B78: Червякова Ольга | H78: 15:00-16:00
B79: Червякова Ольга | H79: 16:00-17:00
B80: Червякова Ольга | H80: 17:00-18:00
B81: Щемелинин Владислав | H81: 18:00-19:00
B82: Щемелинин Владислав | C82: Restream | D82: Завершен | F82: Не правильно введен URL и ключ трансляции | G82: Здравствуйте! В первый раз пытаюсь запустить трансляцию через ваш сервис. На Twitch + ВК Плей Видео Лайв. Сервис показывает что сигнал есть Так-же показывает что сигнал на площадки идёт но трансляции нет. | H82: 19:00-20:00
B83: Щемелинин Владислав | H83: 20:00-21:00
B84: Щемелинин Владислав | H84: 21:00-22:00
B85: Щемелинин Владислав | H85: 22:00-23:00
A86: 45845 | B86: Алексеева Александра | H86: 9:00-10:00
B87: Алексеева Александра | H87: 10:00-11:00
B88: Алексеева Александра | H88: 11:00-12:00
B89: Алексеева Александра | H89: 12:00-13:00
B90: Червякова Ольга | C90: МатчТВ | D90: Завершен | G90: Всем привет! @small9rose @konyshevvvv Помогите, пожалуйста, разобраться с случаем: 1) Пользователь оформляет подписку в приложении по акции и с удовольствием её использует; 2) За два дня до очередного продления подписки он отвязывает старую карту и привязывает новую в приложении; 3) За один день до продления подписки он удаляет аккаунт ГИД; 4) Деньги за продление не списываются, всё ок. 5) Он увидел, что подписки нет 06.07.2025, и покупает в плеере новую подписку. (Я предполагаю, что аккаунт в ГИД он не восстановил, но был авторизован удаленным внутри плеера?) Эта покупка подписки не отображается поиском (https://api.video.matchtv.ru/admin/transactions?utf8=%E2%9C%93&transaction%5Bfilter%5D%5Bid%5D=&transaction%5Bfilter%5D%5Bcode%5D=&transaction%5Bfilter%5D%5Bpromocode%5D=&transaction%5Bfilter%5D%5Bevent_key%5D=&transaction%5Bfilter%5D%5Bcomment%5D=&transaction%5Bfilter%5D%5Bhd%5D=&transaction%5Bfilter%5D%5Btransaction_types%5D%5B%5D=&transaction%5Bfilter%5D%5Bouter_id%5D=2ffcddb9-000f-5000-b000-1bae3fe269b9&transaction%5Bfilter%5D%5Bcustomer_key%5D=&transaction%5Bfilter%5D%5Buid%5D=&transaction%5Bfilter%5D%5Bemail%5D=&transaction%5Bfilter%5D%5Bphone%5D=&transaction%5Bfilter%5D%5Bip%5D=&transaction%5Bfilter%5D%5Bdate_from%5D=2025-06-23&transaction%5Bfilter%5D%5Bdate_to%5D=2025-07-07&transaction%5Bfilter%5D%5Bactive%5D=0&transaction%5Bfilter%5D%5Bamount_gteq%5D=&transaction%5Bfilter%5D%5Bamount_lteq%5D=&transaction%5Bfilter%5D%5Baccess_start_time_from%5D=&transaction%5Bfilter%5D%5Baccess_start_time_to%5D=&transaction%5Bfilter%5D%5Baccess_end_time_from%5D=&transaction%5Bfilter%5D%5Baccess_end_time_to%5D=&transaction%5Bfilter%5D%5Bpartner_ids%5D%5B%5D=&transaction%5Bfilter%5D%5Bpayment_services%5D%5B%5D=&transaction%5Bfilter%5D%5Bstatus%5D=&transaction%5Bfilter%5D%5Btype%5D=&transaction%5Bfilter%5D%5Bpromo_code%5D=&transaction%5Bfilter%5D%5Bapplications%5D%5B%5D=&transaction%5Bfilter%5D%5Btrial%5D=&transaction%5Bfilter%5D%5Brecurring%5D=&transaction%5Bfilter%5D%5Boutput_from_sequence%5D=). И в старом аккаунте (https://api.video.matchtv.ru/client/users/9195962) её нет. Вопрос, что делать и как быть? | H90: 13:00-14:00
B91: Червякова Ольга | H91: 14:00-15:00
B92: Червякова Ольга | H92: 15:00-16:00
B93: Червякова Ольга | H93: 16:00-17:00
B94: Червякова Ольга | H94: 17:00-18:00
B95: Червякова Ольга | H95: 18:00-19:00
B96: Червякова Ольга | C96: ТВСтарт | D96: Завершен | G96: Здравствуйте. Посмотрите, пожалуйста стрим в вк на этой трансляции, нет ли там проблем? | H96: 19:00-20:00
B97: Червякова Ольга | H97: 20:00-21:00
B98: Червякова Ольга | H98: 21:00-22:00
B99: Червякова Ольга | H99: 22:00-23:00
A100: 45846 | B100: Алексеева Александра | H100: 9:00-10:00
...

Sheet Отчет Январь
A1: Отчет по сотрудникам за месяц | H1: Отчет по клиентам за месяц
A2: Сотрудник | B2: Количество часов | C2: Количество нерабочих часов (для штатных сотрудников) | D2: Количество успешно завершенных заявок | E2: Количество заявок, переведенных в тикеты | F2: Количество незавершенных заявок | H2: Клиент | I2: Количество поступивших обращений | J2: Количество успешно закрытых обращений | K2: Количество обращений, переведенных в тикеты | L2: Количество обращений в работе
A3: Червякова Ольга | B3: =COUNTIF('Январь 26'!$B$2:B1005, A3) -> 196 | C3: =SUM(B49:AE49) -> 0 | D3: =COUNTIFS('Январь 26'!$B$2:B1005, A3, 'Январь 26'!$D$2:D1005, 'Служебный лист 2'!$C$2) -> 20 | E3: =COUNTIFS('Январь 26'!$B$2:B1005, A3, 'Январь 26'!$D$2:D1005, 'Служебный лист 2'!$C$3) -> 1 | F3: =COUNTIFS('Январь 26'!$B$2:B1005, A3, 'Январь 26'!$D$2:D1005, 'Служебный лист 2'!$C$4) -> 0 | H3: МХЛ | I3: =COUNTIF('Январь 26'!$C$2:C1005, H3) -> 4 | J3: =COUNTIFS('Январь 26'!$C$2:C1005, H3, 'Январь 26'!$D$2:D1005, 'Служебный лист 2'!$C$2) -> 3 | K3: =COUNTIFS('Январь 26'!$C$2:C1005, H3, 'Январь 26'!$D$2:D1005, 'Служебный лист 2'!$C$3) -> 0 | L3: =COUNTIFS('Январь 26'!$C$2:C1005, H3, 'Январь 26'!$D$2:D1005, 'Служебный лист 2'!$C$4) -> 1
A4: Толкачев Егор | B4: =COUNTIF('Январь 26'!$B$2:B1005, A4) -> 0 | C4: =SUM(B50:AE50) -> 0 | D4: =COUNTIFS('Январь 26'!$B$2:B1005, A4, 'Январь 26'!$D$2:D1005, 'Служебный лист 2'!$C$2) -> 0 | E4: =COUNTIFS('Январь 26'!$B$2:B1005, A4, 'Январь 26'!$D$2:D1005, 'Служебный лист 2'!$C$3) -> 0 | F4: =COUNTIFS('Январь 26'!$B$2:B1005, A4, 'Январь 26'!$D$2:D1005, 'Служебный лист 2'!$C$4) -> 0 | H4: КХЛ | I4: =COUNTIF('Январь 26'!$C$2:C1005, H4) -> 8 | J4: =COUNTIFS('Январь 26'!$C$2:C1005, H4, 'Январь 26'!$D$2:D1005, 'Служебный лист 2'!$C$2) -> 7 | K4: =COUNTIFS('Январь 26'!$C$2:C1005, H4, 'Январь 26'!$D$2:D1005, 'Служебный лист 2'!$C$3) -> 0 | L4: =COUNTIFS('Январь 26'!$C$2:C1005, H4, 'Январь 26'!$D$2:D1005, 'Служебный лист 2'!$C$4) -> 1
A5: Андреева Варвара | B5: =COUNTIF('Январь 26'!$B$2:B1005, A5) -> 0 | C5: =SUM(B51:AE51) -> 0 | D5: =COUNTIFS('Январь 26'!$B$2:B1005, A5, 'Январь 26'!$D$2:D1005, 'Служебный лист 2'!$C$2) -> 0 | E5: =COUNTIFS('Январь 26'!$B$2:B1005, A5, 'Январь 26'!$D$2:D1005, 'Служебный лист 2'!$C$3) -> 0 | F5: =COUNTIFS('Январь 26'!$B$2:B1005, A5, 'Январь 26'!$D$2:D1005, 'Служебный лист 2'!$C$4) -> 0 | H5: ОТР | I5: =COUNTIF('Январь 26'!$C$2:C1005, H5) -> 0 | J5: =COUNTIFS('Январь 26'!$C$2:C1005, H5, 'Январь 26'!$D$2:D1005, 'Служебный лист 2'!$C$2) -> 0 | K5: =COUNTIFS('Январь 26'!$C$2:C1005, H5, 'Январь 26'!$D$2:D1005, 'Служебный лист 2'!$C$3) -> 0 | L5: =COUNTIFS('Январь 26'!$C$2:C1005, H5, 'Январь 26'!$D$2:D1005, 'Служебный лист 2'!$C$4) -> 0
A6: Белов Дмитрий | B6: =COUNTIF('Январь 26'!$B$2:B1005, A6) -> 0 | C6: =SUM(B52:AE52) -> 0 | D6: =COUNTIFS('Январь 26'!$B$2:B1005, A6, 'Январь 26'!$D$2:D1005, 'Служебный лист 2'!$C$2) -> 0 | E6: =COUNTIFS('Январь 26'!$B$2:B1005, A6, 'Январь 26'!$D$2:D1005, 'Служебный лист 2'!$C$3) -> 0 | F6: =COUNTIFS('Январь 26'!$B$2:B1005, A6, 'Январь 26'!$D$2:D1005, 'Служебный лист 2'!$C$4) -> 0 | H6: ТВСтарт | I6: =COUNTIF('Январь 26'!$C$2:C1005, H6) -> 1 | J6: =COUNTIFS('Январь 26'!$C$2:C1005, H6, 'Январь 26'!$D$2:D1005, 'Служебный лист 2'!$C$2) -> 1 | K6: =COUNTIFS('Январь 26'!$C$2:C1005, H6, 'Январь 26'!$D$2:D1005, 'Служебный лист 2'!$C$3) -> 0 | L6: =COUNTIFS('Январь 26'!$C$2:C1005, H6, 'Январь 26'!$D$2:D1005, 'Служебный лист 2'!$C$4) -> 0
A7: Кузнецова Алиса | B7: =COUNTIF('Январь 26'!$B$2:B1005, A7) -> 0 | C7: =SUM(B53:AE53) -> 0 | D7: =COUNTIFS('Январь 26'!$B$2:B1005, A7, 'Январь 26'!$D$2:D1005, 'Служебный лист 2'!$C$2) -> 0 | E7: =COUNTIFS('Январь 26'!$B$2:B1005, A7, 'Январь 26'!$D$2:D1005, 'Служебный лист 2'!$C$3) -> 0 | F7: =COUNTIFS('Январь 26'!$B$2:B1005, A7, 'Январь 26'!$D$2:D1005, 'Служебный лист 2'!$C$4) -> 0 | H7: ЛигаВТБ | I7: =COUNTIF('Январь 26'!$C$2:C1005, H7) -> 0 | J7: =COUNTIFS('Январь 26'!$C$2:C1005, H7, 'Январь 26'!$D$2:D1005, 'Служебный лист 2'!$C$2) -> 0 | K7: =COUNTIFS('Январь 26'!$C$2:C1005, H7, 'Январь 26'!$D$2:D1005, 'Служебный лист 2'!$C$3) -> 0 | L7: =COUNTIFS('Январь 26'!$C$2:C1005, H7, 'Январь 26'!$D$2:D1005, 'Служебный лист 2'!$C$4) -> 0
A8: Щемелинин Владислав | B8: =COUNTIF('Январь 26'!$B$2:B1005, A8) -> 0 | C8: =SUM(B54:AE54) -> 0 | D8: =COUNTIFS('Январь 26'!$B$2:B1005, A8, 'Январь 26'!$D$2:D1005, 'Служебный лист 2'!$C$2) -> 0 | E8: =COUNTIFS('Январь 26'!$B$2:B1005, A8, 'Январь 26'!$D$2:D1005, 'Служебный лист 2'!$C$3) -> 0 | F8: =COUNTIFS('Январь 26'!$B$2:B1005, A8, 'Январь 26'!$D$2:D1005, 'Служебный лист 2'!$C$4) -> 0 | H8: РедВеб | I8: =COUNTIF('Январь 26'!$C$2:C1005, H8) -> 0 | J8: =COUNTIFS('Январь 26'!$C$2:C1005, H8, 'Январь 26'!$D$2:D1005, 'Служебный лист 2'!$C$2) -> 0 | K8: =COUNTIFS('Январь 26'!$C$2:C1005, H8, 'Январь 26'!$D$2:D1005, 'Служебный лист 2'!$C$3) -> 0 | L8: =COUNTIFS('Январь 26'!$C$2:C1005, H8, 'Январь 26'!$D$2:D1005, 'Служебный лист 2'!$C$4) -> 0
A9: Гришина Светлана | B9: =COUNTIF('Январь 26'!$B$2:B1005, A9) -> 31 | C9: =SUM(B55:AE55) -> 0 | D9: =COUNTIFS('Январь 26'!$B$2:B1005, A9, 'Январь 26'!$D$2:D1005, 'Служебный лист 2'!$C$2) -> 7 | E9: =COUNTIFS('Январь 26'!$B$2:B1005, A9, 'Январь 26'!$D$2:D1005, 'Служебный лист 2'!$C$3) -> 1 | F9: =COUNTIFS('Январь 26'!$B$2:B1005, A9, 'Январь 26'!$D$2:D1005, 'Служебный лист 2'!$C$4) -> 0 | H9: Прямая речь | I9: =COUNTIF('Январь 26'!$C$2:C1005, H9) -> 0 | J9: =COUNTIFS('Январь 26'!$C$2:C1005, H9, 'Январь 26'!$D$2:D1005, 'Служебный лист 2'!$C$2) -> 0 | K9: =COUNTIFS('Январь 26'!$C$2:C1005, H9, 'Январь 26'!$D$2:D1005, 'Служебный лист 2'!$C$3) -> 0 | L9: =COUNTIFS('Январь 26'!$C$2:C1005, H9, 'Январь 26'!$D$2:D1005, 'Служебный лист 2'!$C$4) -> 0
A10: Мишина Анна | B10: =COUNTIF('Январь 26'!$B$2:B1005, A10) -> 207 | C10: =SUM(B56:AE56) -> 0 | D10: =COUNTIFS('Январь 26'!$B$2:B1005, A10, 'Январь 26'!$D$2:D1005, 'Служебный лист 2'!$C$2) -> 63 | E10: =COUNTIFS('Январь 26'!$B$2:B1005, A10, 'Январь 26'!$D$2:D1005, 'Служебный лист 2'!$C$3) -> 2 | F10: =COUNTIFS('Январь 26'!$B$2:B1005, A10, 'Январь 26'!$D$2:D1005, 'Служебный лист 2'!$C$4) -> 2 | H10: МатчТВ | I10: =COUNTIF('Январь 26'!$C$2:C1005, H10) -> 12 | J10: =COUNTIFS('Январь 26'!$C$2:C1005, H10, 'Январь 26'!$D$2:D1005, 'Служебный лист 2'!$C$2) -> 10 | K10: =COUNTIFS('Январь 26'!$C$2:C1005, H10, 'Январь 26'!$D$2:D1005, 'Служебный лист 2'!$C$3) -> 2 | L10: =COUNTIFS('Январь 26'!$C$2:C1005, H10, 'Январь 26'!$D$2:D1005, 'Служебный лист 2'!$C$4) -> 0
A11: Алексеева Александра | B11: =COUNTIF('Январь 26'!$B$2:B1005, A11) -> 0 | C11: =SUM(B57:AE57) -> 0 | D11: =COUNTIFS('Январь 26'!$B$2:B1005, A11, 'Январь 26'!$D$2:D1005, 'Служебный лист 2'!$C$2) -> 0 | E11: =COUNTIFS('Январь 26'!$B$2:B1005, A11, 'Январь 26'!$D$2:D1005, 'Служебный лист 2'!$C$3) -> 0 | F11: =COUNTIFS('Январь 26'!$B$2:B1005, A11, 'Январь 26'!$D$2:D1005, 'Служебный лист 2'!$C$4) -> 0 | H11: RDS | I11: =COUNTIF('Январь 26'!$C$2:C1005, H11) -> 0 | J11: =COUNTIFS('Январь 26'!$C$2:C1005, H11, 'Январь 26'!$D$2:D1005, 'Служебный лист 2'!$C$2) -> 0 | K11: =COUNTIFS('Январь 26'!$C$2:C1005, H11, 'Январь 26'!$D$2:D1005, 'Служебный лист 2'!$C$3) -> 0 | L11: =COUNTIFS('Январь 26'!$C$2:C1005, H11, 'Январь 26'!$D$2:D1005, 'Служебный лист 2'!$C$4) -> 0
A12: ВСЕГО | B12: =SUM(B3:B11) -> 434 | C12: =SUM(C3:C11) -> 0 | D12: =SUM(D3:D11) -> 90 | E12: =SUM(E3:E11) -> 4 | F12: =SUM(F3:F11) -> 2 | H12: Ifree | I12: =COUNTIF('Январь 26'!$C$2:C1005, H12) -> 3 | J12: =COUNTIFS('Январь 26'!$C$2:C1005, H12, 'Январь 26'!$D$2:D1005, 'Служебный лист 2'!$C$2) -> 2 | K12: =COUNTIFS('Январь 26'!$C$2:C1005, H12, 'Январь 26'!$D$2:D1005, 'Служебный лист 2'!$C$3) -> 1 | L12: =COUNTIFS('Январь 26'!$C$2:C1005, H12, 'Январь 26'!$D$2:D1005, 'Служебный лист 2'!$C$4) -> 0
H13: ЖХЛ | I13: =COUNTIF('Январь 26'!$C$2:C1005, H13) -> 0 | J13: =COUNTIFS('Январь 26'!$C$2:C1005, H13, 'Январь 26'!$D$2:D1005, 'Служебный лист 2'!$C$2) -> 0 | K13: =COUNTIFS('Январь 26'!$C$2:C1005, H13, 'Январь 26'!$D$2:D1005, 'Служебный лист 2'!$C$3) -> 0 | L13: =COUNTIFS('Январь 26'!$C$2:C1005, H13, 'Январь 26'!$D$2:D1005, 'Служебный лист 2'!$C$4) -> 0
H14: М1 | I14: =COUNTIF('Январь 26'!$C$2:C1005, H14) -> 1 | J14: =COUNTIFS('Январь 26'!$C$2:C1005, H14, 'Январь 26'!$D$2:D1005, 'Служебный лист 2'!$C$2) -> 1 | K14: =COUNTIFS('Январь 26'!$C$2:C1005, H14, 'Январь 26'!$D$2:D1005, 'Служебный лист 2'!$C$3) -> 0 | L14: =COUNTIFS('Январь 26'!$C$2:C1005, H14, 'Январь 26'!$D$2:D1005, 'Служебный лист 2'!$C$4) -> 0
H15: Кари | I15: =COUNTIF('Январь 26'!$C$2:C1005, H15) -> 0 | J15: =COUNTIFS('Январь 26'!$C$2:C1005, H15, 'Январь 26'!$D$2:D1005, 'Служебный лист 2'!$C$2) -> 0 | K15: =COUNTIFS('Январь 26'!$C$2:C1005, H15, 'Январь 26'!$D$2:D1005, 'Служебный лист 2'!$C$3) -> 0 | L15: =COUNTIFS('Январь 26'!$C$2:C1005, H15, 'Январь 26'!$D$2:D1005, 'Служебный лист 2'!$C$4) -> 0
H16: sberzvok | I16: =COUNTIF('Январь 26'!$C$2:C1005, H16) -> 0 | J16: =COUNTIFS('Январь 26'!$C$2:C1005, H16, 'Январь 26'!$D$2:D1005, 'Служебный лист 2'!$C$2) -> 0 | K16: =COUNTIFS('Январь 26'!$C$2:C1005, H16, 'Январь 26'!$D$2:D1005, 'Служебный лист 2'!$C$3) -> 0 | L16: =COUNTIFS('Январь 26'!$C$2:C1005, H16, 'Январь 26'!$D$2:D1005, 'Служебный лист 2'!$C$4) -> 0
H17: Sports | I17: =COUNTIF('Январь 26'!$C$2:C1005, H17) -> 0 | J17: =COUNTIFS('Январь 26'!$C$2:C1005, H17, 'Январь 26'!$D$2:D1005, 'Служебный лист 2'!$C$2) -> 0 | K17: =COUNTIFS('Январь 26'!$C$2:C1005, H17, 'Январь 26'!$D$2:D1005, 'Служебный лист 2'!$C$3) -> 0 | L17: =COUNTIFS('Январь 26'!$C$2:C1005, H17, 'Январь 26'!$D$2:D1005, 'Служебный лист 2'!$C$4) -> 0
A18: ='Служебный лист'!A13:A1005 -> 0 | H18: Максима | I18: =COUNTIF('Январь 26'!$C$2:C1005, H18) -> 0 | J18: =COUNTIFS('Январь 26'!$C$2:C1005, H18, 'Январь 26'!$D$2:D1005, 'Служебный лист 2'!$C$2) -> 0 | K18: =COUNTIFS('Январь 26'!$C$2:C1005, H18, 'Январь 26'!$D$2:D1005, 'Служебный лист 2'!$C$3) -> 0 | L18: =COUNTIFS('Январь 26'!$C$2:C1005, H18, 'Январь 26'!$D$2:D1005, 'Служебный лист 2'!$C$4) -> 0
A19: ='Служебный лист'!A14:A1005 -> 0 | H19: Restream | I19: =COUNTIF('Январь 26'!$C$2:C1005, H19) -> 49 | J19: =COUNTIFS('Январь 26'!$C$2:C1005, H19, 'Январь 26'!$D$2:D1005, 'Служебный лист 2'!$C$2) -> 49 | K19: =COUNTIFS('Январь 26'!$C$2:C1005, H19, 'Январь 26'!$D$2:D1005, 'Служебный лист 2'!$C$3) -> 0 | L19: =COUNTIFS('Январь 26'!$C$2:C1005, H19, 'Январь 26'!$D$2:D1005, 'Служебный лист 2'!$C$4) -> 0
C20: Количество успешно завершенных заявок | D20: =D12 -> 90 | H20: МОНИКИ | I20: =COUNTIF('Январь 26'!$C$2:C1005, H20) -> 9 | J20: =COUNTIFS('Январь 26'!$C$2:C1005, H20, 'Январь 26'!$D$2:D1005, 'Служебный лист 2'!$C$2) -> 9 | K20: =COUNTIFS('Январь 26'!$C$2:C1005, H20, 'Январь 26'!$D$2:D1005, 'Служебный лист 2'!$C$3) -> 0 | L20: =COUNTIFS('Январь 26'!$C$2:C1005, H20, 'Январь 26'!$D$2:D1005, 'Служебный лист 2'!$C$4) -> 0
A21: ='Служебный лист'!A15:A1005 -> 0 | C21: Количество заявок, переведенных в тикеты | D21: =E12 -> 4 | H21: Федерация гандбола России | I21: =COUNTIF('Январь 26'!$C$2:C1005, H21) -> 1 | J21: =COUNTIFS('Январь 26'!$C$2:C1005, H21, 'Январь 26'!$D$2:D1005, 'Служебный лист 2'!$C$2) -> 1 | K21: =COUNTIFS('Январь 26'!$C$2:C1005, H21, 'Январь 26'!$D$2:D1005, 'Служебный лист 2'!$C$3) -> 0 | L21: =COUNTIFS('Январь 26'!$C$2:C1005, H21, 'Январь 26'!$D$2:D1005, 'Служебный лист 2'!$C$4) -> 0
C22: Количество незавершенных заявок | D22: =F12 -> 2 | H22: Новый клиент | I22: =COUNTIF('Январь 26'!$C$2:C1005, H22) -> 8 | J22: =COUNTIFS('Январь 26'!$C$2:C1005, H22, 'Январь 26'!$D$2:D1005, 'Служебный лист 2'!$C$2) -> 7 | K22: =COUNTIFS('Январь 26'!$C$2:C1005, H22, 'Январь 26'!$D$2:D1005, 'Служебный лист 2'!$C$3) -> 1 | L22: =COUNTIFS('Январь 26'!$C$2:C1005, H22, 'Январь 26'!$D$2:D1005, 'Служебный лист 2'!$C$4) -> 0
H23: ВСЕГО | I23: =SUM(I3:I22) -> 96 | J23: =SUM(J3:J22) -> 90 | K23: =SUM(K3:K22) -> 4 | L23: =SUM(L2:L22) -> 2
H27: ='Служебный лист'!B19:B1005 -> 0
H28: ='Служебный лист'!B20:B1005 -> 0
H29: ='Служебный лист'!B21:B1005 -> 0
H30: ='Служебный лист'!B22:B1005 -> 0
H31: ='Служебный лист'!B23:B1005 -> 0
H32: ='Служебный лист'!B24:B1005 -> 0
H33: ='Служебный лист'!B25:B1005 -> 0
H34: ='Служебный лист'!B26:B1005 -> 0
H35: ='Служебный лист'!B27:B1005 -> 0
H36: ='Служебный лист'!B28:B1005 -> 0
H37: ='Служебный лист'!B29:B1005 -> 0
A46: Нерабочие часы штатных сотрудников

Sheet Отчет Декабрь
A1: Отчет по сотрудникам за месяц | H1: Отчет по клиентам за месяц
A2: Сотрудник | B2: Количество часов | C2: Количество нерабочих часов (для штатных сотрудников) | D2: Количество успешно завершенных заявок | E2: Количество заявок, переведенных в тикеты | F2: Количество незавершенных заявок | H2: Клиент | I2: Количество поступивших обращений | J2: Количество успешно закрытых обращений | K2: Количество обращений, переведенных в тикеты | L2: Количество обращений в работе
A3: Червякова Ольга | B3: =COUNTIF('Декабрь 25'!$B$2:B1005, A3) -> 212 | C3: =SUM(B49:AE49) -> 0 | D3: =COUNTIFS('Декабрь 25'!$B$2:B1005, A3, 'Декабрь 25'!$D$2:D1005, 'Служебный лист 2'!$C$2) -> 29 | E3: =COUNTIFS('Декабрь 25'!$B$2:B1005, A3, 'Декабрь 25'!$D$2:D1005, 'Служебный лист 2'!$C$3) -> 0 | F3: =COUNTIFS('Декабрь 25'!$B$2:B1005, A3, 'Декабрь 25'!$D$2:D1005, 'Служебный лист 2'!$C$4) -> 0 | H3: МХЛ | I3: =COUNTIF('Декабрь 25'!$C$2:C1005, H3) -> 5 | J3: =COUNTIFS('Декабрь 25'!$C$2:C1005, H3, 'Декабрь 25'!$D$2:D1005, 'Служебный лист 2'!$C$2) -> 5 | K3: =COUNTIFS('Декабрь 25'!$C$2:C1005, H3, 'Декабрь 25'!$D$2:D1005, 'Служебный лист 2'!$C$3) -> 0 | L3: =COUNTIFS('Декабрь 25'!$C$2:C1005, H3, 'Декабрь 25'!$D$2:D1005, 'Служебный лист 2'!$C$4) -> 0
A4: Толкачев Егор | B4: =COUNTIF('Декабрь 25'!$B$2:B1005, A4) -> 0 | C4: =SUM(B50:AE50) -> 0 | D4: =COUNTIFS('Декабрь 25'!$B$2:B1005, A4, 'Декабрь 25'!$D$2:D1005, 'Служебный лист 2'!$C$2) -> 0 | E4: =COUNTIFS('Декабрь 25'!$B$2:B1005, A4, 'Декабрь 25'!$D$2:D1005, 'Служебный лист 2'!$C$3) -> 0 | F4: =COUNTIFS('Декабрь 25'!$B$2:B1005, A4, 'Декабрь 25'!$D$2:D1005, 'Служебный лист 2'!$C$4) -> 0 | H4: КХЛ | I4: =COUNTIF('Декабрь 25'!$C$2:C1005, H4) -> 9 | J4: =COUNTIFS('Декабрь 25'!$C$2:C1005, H4, 'Декабрь 25'!$D$2:D1005, 'Служебный лист 2'!$C$2) -> 9 | K4: =COUNTIFS('Декабрь 25'!$C$2:C1005, H4, 'Декабрь 25'!$D$2:D1005, 'Служебный лист 2'!$C$3) -> 0 | L4: =COUNTIFS('Декабрь 25'!$C$2:C1005, H4, 'Декабрь 25'!$D$2:D1005, 'Служебный лист 2'!$C$4) -> 0
A5: Андреева Варвара | B5: =COUNTIF('Декабрь 25'!$B$2:B1005, A5) -> 8 | C5: =SUM(B51:AE51) -> 0 | D5: =COUNTIFS('Декабрь 25'!$B$2:B1005, A5, 'Декабрь 25'!$D$2:D1005, 'Служебный лист 2'!$C$2) -> 3 | E5: =COUNTIFS('Декабрь 25'!$B$2:B1005, A5, 'Декабрь 25'!$D$2:D1005, 'Служебный лист 2'!$C$3) -> 0 | F5: =COUNTIFS('Декабрь 25'!$B$2:B1005, A5, 'Декабрь 25'!$D$2:D1005, 'Служебный лист 2'!$C$4) -> 0 | H5: ОТР | I5: =COUNTIF('Декабрь 25'!$C$2:C1005, H5) -> 0 | J5: =COUNTIFS('Декабрь 25'!$C$2:C1005, H5, 'Декабрь 25'!$D$2:D1005, 'Служебный лист 2'!$C$2) -> 0 | K5: =COUNTIFS('Декабрь 25'!$C$2:C1005, H5, 'Декабрь 25'!$D$2:D1005, 'Служебный лист 2'!$C$3) -> 0 | L5: =COUNTIFS('Декабрь 25'!$C$2:C1005, H5, 'Декабрь 25'!$D$2:D1005, 'Служебный лист 2'!$C$4) -> 0
A6: Белов Дмитрий | B6: =COUNTIF('Декабрь 25'!$B$2:B1005, A6) -> 0 | C6: =SUM(B52:AE52) -> 0 | D6: =COUNTIFS('Декабрь 25'!$B$2:B1005, A6, 'Декабрь 25'!$D$2:D1005, 'Служебный лист 2'!$C$2) -> 0 | E6: =COUNTIFS('Декабрь 25'!$B$2:B1005, A6, 'Декабрь 25'!$D$2:D1005, 'Служебный лист 2'!$C$3) -> 0 | F6: =COUNTIFS('Декабрь 25'!$B$2:B1005, A6, 'Декабрь 25'!$D$2:D1005, 'Служебный лист 2'!$C$4) -> 0 | H6: ТВСтарт | I6: =COUNTIF('Декабрь 25'!$C$2:C1005, H6) -> 7 | J6: =COUNTIFS('Декабрь 25'!$C$2:C1005, H6, 'Декабрь 25'!$D$2:D1005, 'Служебный лист 2'!$C$2) -> 7 | K6: =COUNTIFS('Декабрь 25'!$C$2:C1005, H6, 'Декабрь 25'!$D$2:D1005, 'Служебный лист 2'!$C$3) -> 0 | L6: =COUNTIFS('Декабрь 25'!$C$2:C1005, H6, 'Декабрь 25'!$D$2:D1005, 'Служебный лист 2'!$C$4) -> 0
A7: Кузнецова Алиса | B7: =COUNTIF('Декабрь 25'!$B$2:B1005, A7) -> 0 | C7: =SUM(B53:AE53) -> 0 | D7: =COUNTIFS('Декабрь 25'!$B$2:B1005, A7, 'Декабрь 25'!$D$2:D1005, 'Служебный лист 2'!$C$2) -> 0 | E7: =COUNTIFS('Декабрь 25'!$B$2:B1005, A7, 'Декабрь 25'!$D$2:D1005, 'Служебный лист 2'!$C$3) -> 0 | F7: =COUNTIFS('Декабрь 25'!$B$2:B1005, A7, 'Декабрь 25'!$D$2:D1005, 'Служебный лист 2'!$C$4) -> 0 | H7: ЛигаВТБ | I7: =COUNTIF('Декабрь 25'!$C$2:C1005, H7) -> 0 | J7: =COUNTIFS('Декабрь 25'!$C$2:C1005, H7, 'Декабрь 25'!$D$2:D1005, 'Служебный лист 2'!$C$2) -> 0 | K7: =COUNTIFS('Декабрь 25'!$C$2:C1005, H7, 'Декабрь 25'!$D$2:D1005, 'Служебный лист 2'!$C$3) -> 0 | L7: =COUNTIFS('Декабрь 25'!$C$2:C1005, H7, 'Декабрь 25'!$D$2:D1005, 'Служебный лист 2'!$C$4) -> 0
A8: Щемелинин Владислав | B8: =COUNTIF('Декабрь 25'!$B$2:B1005, A8) -> 0 | C8: =SUM(B54:AE54) -> 0 | D8: =COUNTIFS('Декабрь 25'!$B$2:B1005, A8, 'Декабрь 25'!$D$2:D1005, 'Служебный лист 2'!$C$2) -> 0 | E8: =COUNTIFS('Декабрь 25'!$B$2:B1005, A8, 'Декабрь 25'!$D$2:D1005, 'Служебный лист 2'!$C$3) -> 0 | F8: =COUNTIFS('Декабрь 25'!$B$2:B1005, A8, 'Декабрь 25'!$D$2:D1005, 'Служебный лист 2'!$C$4) -> 0 | H8: РедВеб | I8: =COUNTIF('Декабрь 25'!$C$2:C1005, H8) -> 0 | J8: =COUNTIFS('Декабрь 25'!$C$2:C1005, H8, 'Декабрь 25'!$D$2:D1005, 'Служебный лист 2'!$C$2) -> 0 | K8: =COUNTIFS('Декабрь 25'!$C$2:C1005, H8, 'Декабрь 25'!$D$2:D1005, 'Служебный лист 2'!$C$3) -> 0 | L8: =COUNTIFS('Декабрь 25'!$C$2:C1005, H8, 'Декабрь 25'!$D$2:D1005, 'Служебный лист 2'!$C$4) -> 0
A9: Гришина Светлана | B9: =COUNTIF('Декабрь 25'!$B$2:B1005, A9) -> 66 | C9: =SUM(B55:AE55) -> 0 | D9: =COUNTIFS('Декабрь 25'!$B$2:B1005, A9, 'Декабрь 25'!$D$2:D1005, 'Служебный лист 2'!$C$2) -> 28 | E9: =COUNTIFS('Декабрь 25'!$B$2:B1005, A9, 'Декабрь 25'!$D$2:D1005, 'Служебный лист 2'!$C$3) -> 0 | F9: =COUNTIFS('Декабрь 25'!$B$2:B1005, A9, 'Декабрь 25'!$D$2:D1005, 'Служебный лист 2'!$C$4) -> 0 | H9: Прямая речь | I9: =COUNTIF('Декабрь 25'!$C$2:C1005, H9) -> 1 | J9: =COUNTIFS('Декабрь 25'!$C$2:C1005, H9, 'Декабрь 25'!$D$2:D1005, 'Служебный лист 2'!$C$2) -> 1 | K9: =COUNTIFS('Декабрь 25'!$C$2:C1005, H9, 'Декабрь 25'!$D$2:D1005, 'Служебный лист 2'!$C$3) -> 0 | L9: =COUNTIFS('Декабрь 25'!$C$2:C1005, H9, 'Декабрь 25'!$D$2:D1005, 'Служебный лист 2'!$C$4) -> 0
A10: Мишина Анна | B10: =COUNTIF('Декабрь 25'!$B$2:B1005, A10) -> 148 | C10: =SUM(B56:AE56) -> 0 | D10: =COUNTIFS('Декабрь 25'!$B$2:B1005, A10, 'Декабрь 25'!$D$2:D1005, 'Служебный лист 2'!$C$2) -> 43 | E10: =COUNTIFS('Декабрь 25'!$B$2:B1005, A10, 'Декабрь 25'!$D$2:D1005, 'Служебный лист 2'!$C$3) -> 0 | F10: =COUNTIFS('Декабрь 25'!$B$2:B1005, A10, 'Декабрь 25'!$D$2:D1005, 'Служебный лист 2'!$C$4) -> 0 | H10: МатчТВ | I10: =COUNTIF('Декабрь 25'!$C$2:C1005, H10) -> 7 | J10: =COUNTIFS('Декабрь 25'!$C$2:C1005, H10, 'Декабрь 25'!$D$2:D1005, 'Служебный лист 2'!$C$2) -> 7 | K10: =COUNTIFS('Декабрь 25'!$C$2:C1005, H10, 'Декабрь 25'!$D$2:D1005, 'Служебный лист 2'!$C$3) -> 0 | L10: =COUNTIFS('Декабрь 25'!$C$2:C1005, H10, 'Декабрь 25'!$D$2:D1005, 'Служебный лист 2'!$C$4) -> 0
A11: Алексеева Александра | B11: =COUNTIF('Декабрь 25'!$B$2:B1005, A11) -> 0 | C11: =SUM(B57:AE57) -> 0 | D11: =COUNTIFS('Декабрь 25'!$B$2:B1005, A11, 'Декабрь 25'!$D$2:D1005, 'Служебный лист 2'!$C$2) -> 0 | E11: =COUNTIFS('Декабрь 25'!$B$2:B1005, A11, 'Декабрь 25'!$D$2:D1005, 'Служебный лист 2'!$C$3) -> 0 | F11: =COUNTIFS('Декабрь 25'!$B$2:B1005, A11, 'Декабрь 25'!$D$2:D1005, 'Служебный лист 2'!$C$4) -> 0 | H11: RDS | I11: =COUNTIF('Декабрь 25'!$C$2:C1005, H11) -> 1 | J11: =COUNTIFS('Декабрь 25'!$C$2:C1005, H11, 'Декабрь 25'!$D$2:D1005, 'Служебный лист 2'!$C$2) -> 1 | K11: =COUNTIFS('Декабрь 25'!$C$2:C1005, H11, 'Декабрь 25'!$D$2:D1005, 'Служебный лист 2'!$C$3) -> 0 | L11: =COUNTIFS('Декабрь 25'!$C$2:C1005, H11, 'Декабрь 25'!$D$2:D1005, 'Служебный лист 2'!$C$4) -> 0
A12: ВСЕГО | B12: =SUM(B3:B11) -> 434 | C12: =SUM(C3:C11) -> 0 | D12: =SUM(D3:D11) -> 103 | E12: =SUM(E3:E11) -> 0 | F12: =SUM(F3:F11) -> 0 | H12: Ifree | I12: =COUNTIF('Декабрь 25'!$C$2:C1005, H12) -> 5 | J12: =COUNTIFS('Декабрь 25'!$C$2:C1005, H12, 'Декабрь 25'!$D$2:D1005, 'Служебный лист 2'!$C$2) -> 5 | K12: =COUNTIFS('Декабрь 25'!$C$2:C1005, H12, 'Декабрь 25'!$D$2:D1005, 'Служебный лист 2'!$C$3) -> 0 | L12: =COUNTIFS('Декабрь 25'!$C$2:C1005, H12, 'Декабрь 25'!$D$2:D1005, 'Служебный лист 2'!$C$4) -> 0
H13: ЖХЛ | I13: =COUNTIF('Декабрь 25'!$C$2:C1005, H13) -> 0 | J13: =COUNTIFS('Декабрь 25'!$C$2:C1005, H13, 'Декабрь 25'!$D$2:D1005, 'Служебный лист 2'!$C$2) -> 0 | K13: =COUNTIFS('Декабрь 25'!$C$2:C1005, H13, 'Декабрь 25'!$D$2:D1005, 'Служебный лист 2'!$C$3) -> 0 | L13: =COUNTIFS('Декабрь 25'!$C$2:C1005, H13, 'Декабрь 25'!$D$2:D1005, 'Служебный лист 2'!$C$4) -> 0
H14: М1 | I14: =COUNTIF('Декабрь 25'!$C$2:C1005, H14) -> 1 | J14: =COUNTIFS('Декабрь 25'!$C$2:C1005, H14, 'Декабрь 25'!$D$2:D1005, 'Служебный лист 2'!$C$2) -> 1 | K14: =COUNTIFS('Декабрь 25'!$C$2:C1005, H14, 'Декабрь 25'!$D$2:D1005, 'Служебный лист 2'!$C$3) -> 0 | L14: =COUNTIFS('Декабрь 25'!$C$2:C1005, H14, 'Декабрь 25'!$D$2:D1005, 'Служебный лист 2'!$C$4) -> 0
H15: Кари | I15: =COUNTIF('Декабрь 25'!$C$2:C1005, H15) -> 0 | J15: =COUNTIFS('Декабрь 25'!$C$2:C1005, H15, 'Декабрь 25'!$D$2:D1005, 'Служебный лист 2'!$C$2) -> 0 | K15: =COUNTIFS('Декабрь 25'!$C$2:C1005, H15, 'Декабрь 25'!$D$2:D1005, 'Служебный лист 2'!$C$3) -> 0 | L15: =COUNTIFS('Декабрь 25'!$C$2:C1005, H15, 'Декабрь 25'!$D$2:D1005, 'Служебный лист 2'!$C$4) -> 0
H16: sberzvok | I16: =COUNTIF('Декабрь 25'!$C$2:C1005, H16) -> 0 | J16: =COUNTIFS('Декабрь 25'!$C$2:C1005, H16, 'Декабрь 25'!$D$2:D1005, 'Служебный лист 2'!$C$2) -> 0 | K16: =COUNTIFS('Декабрь 25'!$C$2:C1005, H16, 'Декабрь 25'!$D$2:D1005, 'Служебный лист 2'!$C$3) -> 0 | L16: =COUNTIFS('Декабрь 25'!$C$2:C1005, H16, 'Декабрь 25'!$D$2:D1005, 'Служебный лист 2'!$C$4) -> 0
H17: Sports | I17: =COUNTIF('Декабрь 25'!$C$2:C1005, H17) -> 0 | J17: =COUNTIFS('Декабрь 25'!$C$2:C1005, H17, 'Декабрь 25'!$D$2:D1005, 'Служебный лист 2'!$C$2) -> 0 | K17: =COUNTIFS('Декабрь 25'!$C$2:C1005, H17, 'Декабрь 25'!$D$2:D1005, 'Служебный лист 2'!$C$3) -> 0 | L17: =COUNTIFS('Декабрь 25'!$C$2:C1005, H17, 'Декабрь 25'!$D$2:D1005, 'Служебный лист 2'!$C$4) -> 0
A18: ='Служебный лист'!A13:A1005 -> 0 | H18: Максима | I18: =COUNTIF('Декабрь 25'!$C$2:C1005, H18) -> 0 | J18: =COUNTIFS('Декабрь 25'!$C$2:C1005, H18, 'Декабрь 25'!$D$2:D1005, 'Служебный лист 2'!$C$2) -> 0 | K18: =COUNTIFS('Декабрь 25'!$C$2:C1005, H18, 'Декабрь 25'!$D$2:D1005, 'Служебный лист 2'!$C$3) -> 0 | L18: =COUNTIFS('Декабрь 25'!$C$2:C1005, H18, 'Декабрь 25'!$D$2:D1005, 'Служебный лист 2'!$C$4) -> 0
A19: ='Служебный лист'!A14:A1005 -> 0 | H19: Restream | I19: =COUNTIF('Декабрь 25'!$C$2:C1005, H19) -> 39 | J19: =COUNTIFS('Декабрь 25'!$C$2:C1005, H19, 'Декабрь 25'!$D$2:D1005, 'Служебный лист 2'!$C$2) -> 39 | K19: =COUNTIFS('Декабрь 25'!$C$2:C1005, H19, 'Декабрь 25'!$D$2:D1005, 'Служебный лист 2'!$C$3) -> 0 | L19: =COUNTIFS('Декабрь 25'!$C$2:C1005, H19, 'Декабрь 25'!$D$2:D1005, 'Служебный лист 2'!$C$4) -> 0
C20: Количество успешно завершенных заявок | D20: =D12 -> 103 | H20: МОНИКИ | I20: =COUNTIF('Декабрь 25'!$C$2:C1005, H20) -> 16 | J20: =COUNTIFS('Декабрь 25'!$C$2:C1005, H20, 'Декабрь 25'!$D$2:D1005, 'Служебный лист 2'!$C$2) -> 16 | K20: =COUNTIFS('Декабрь 25'!$C$2:C1005, H20, 'Декабрь 25'!$D$2:D1005, 'Служебный лист 2'!$C$3) -> 0 | L20: =COUNTIFS('Декабрь 25'!$C$2:C1005, H20, 'Декабрь 25'!$D$2:D1005, 'Служебный лист 2'!$C$4) -> 0
A21: ='Служебный лист'!A15:A1005 -> 0 | C21: Количество заявок, переведенных в тикеты | D21: =E12 -> 0 | H21: Федерация гандбола России | I21: =COUNTIF('Декабрь 25'!$C$2:C1005, H21) -> 0 | J21: =COUNTIFS('Декабрь 25'!$C$2:C1005, H21, 'Декабрь 25'!$D$2:D1005, 'Служебный лист 2'!$C$2) -> 0 | K21: =COUNTIFS('Декабрь 25'!$C$2:C1005, H21, 'Декабрь 25'!$D$2:D1005, 'Служебный лист 2'!$C$3) -> 0 | L21: =COUNTIFS('Декабрь 25'!$C$2:C1005, H21, 'Декабрь 25'!$D$2:D1005, 'Служебный лист 2'!$C$4) -> 0
C22: Количество незавершенных заявок | D22: =F12 -> 0 | H22: Новый клиент | I22: =COUNTIF('Декабрь 25'!$C$2:C1005, H22) -> 12 | J22: =COUNTIFS('Декабрь 25'!$C$2:C1005, H22, 'Декабрь 25'!$D$2:D1005, 'Служебный лист 2'!$C$2) -> 12 | K22: =COUNTIFS('Декабрь 25'!$C$2:C1005, H22, 'Декабрь 25'!$D$2:D1005, 'Служебный лист 2'!$C$3) -> 0 | L22: =COUNTIFS('Декабрь 25'!$C$2:C1005, H22, 'Декабрь 25'!$D$2:D1005, 'Служебный лист 2'!$C$4) -> 0
H23: ВСЕГО | I23: =SUM(I3:I22) -> 103 | J23: =SUM(J3:J22) -> 103 | K23: =SUM(K3:K22) -> 0 | L23: =SUM(L2:L22) -> 0
H27: ='Служебный лист'!B19:B1005 -> 0
H28: ='Служебный лист'!B20:B1005 -> 0
H29: ='Служебный лист'!B21:B1005 -> 0
H30: ='Служебный лист'!B22:B1005 -> 0
H31: ='Служебный лист'!B23:B1005 -> 0
H32: ='Служебный лист'!B24:B1005 -> 0
H33: ='Служебный лист'!B25:B1005 -> 0
H34: ='Служебный лист'!B26:B1005 -> 0
H35: ='Служебный лист'!B27:B1005 -> 0
H36: ='Служебный лист'!B28:B1005 -> 0
H37: ='Служебный лист'!B29:B1005 -> 0
A46: Нерабочие часы штатных сотрудников

Sheet Отчет Ноябрь
A1: Отчет по сотрудникам за месяц | H1: Отчет по клиентам за месяц
A2: Сотрудник | B2: Количество часов | C2: Количество нерабочих часов (для штатных сотрудников) | D2: Количество успешно завершенных заявок | E2: Количество заявок, переведенных в тикеты | F2: Количество незавершенных заявок | H2: Клиент | I2: Количество поступивших обращений | J2: Количество успешно закрытых обращений | K2: Количество обращений, переведенных в тикеты | L2: Количество обращений в работе
A3: Червякова Ольга | B3: =COUNTIF('Ноябрь 25 '!$B$2:B1005, A3) -> 213 | C3: =SUM(B49:AE49) -> 0 | D3: =COUNTIFS('Ноябрь 25 '!$B$2:B1005, A3, 'Ноябрь 25 '!$D$2:D1005, 'Служебный лист 2'!$C$2) -> 44 | E3: =COUNTIFS('Ноябрь 25 '!$B$2:B1005, A3, 'Ноябрь 25 '!$D$2:D1005, 'Служебный лист 2'!$C$3) -> 2 | F3: =COUNTIFS('Ноябрь 25 '!$B$2:B1005, A3, 'Ноябрь 25 '!$D$2:D1005, 'Служебный лист 2'!$C$4) -> 1 | H3: МХЛ | I3: =COUNTIF('Ноябрь 25 '!$C$2:C1005, H3) -> 5 | J3: =COUNTIFS('Ноябрь 25 '!$C$2:C1005, H3, 'Ноябрь 25 '!$D$2:D1005, 'Служебный лист 2'!$C$2) -> 5 | K3: =COUNTIFS('Ноябрь 25 '!$C$2:C1005, H3, 'Ноябрь 25 '!$D$2:D1005, 'Служебный лист 2'!$C$3) -> 0 | L3: =COUNTIFS('Ноябрь 25 '!$C$2:C1005, H3, 'Ноябрь 25 '!$D$2:D1005, 'Служебный лист 2'!$C$4) -> 0
A4: Толкачев Егор | B4: =COUNTIF('Ноябрь 25 '!$B$2:B1005, A4) -> 10 | C4: =SUM(B50:AE50) -> 0 | D4: =COUNTIFS('Ноябрь 25 '!$B$2:B1005, A4, 'Ноябрь 25 '!$D$2:D1005, 'Служебный лист 2'!$C$2) -> 0 | E4: =COUNTIFS('Ноябрь 25 '!$B$2:B1005, A4, 'Ноябрь 25 '!$D$2:D1005, 'Служебный лист 2'!$C$3) -> 0 | F4: =COUNTIFS('Ноябрь 25 '!$B$2:B1005, A4, 'Ноябрь 25 '!$D$2:D1005, 'Служебный лист 2'!$C$4) -> 0 | H4: КХЛ | I4: =COUNTIF('Ноябрь 25 '!$C$2:C1005, H4) -> 5 | J4: =COUNTIFS('Ноябрь 25 '!$C$2:C1005, H4, 'Ноябрь 25 '!$D$2:D1005, 'Служебный лист 2'!$C$2) -> 5 | K4: =COUNTIFS('Ноябрь 25 '!$C$2:C1005, H4, 'Ноябрь 25 '!$D$2:D1005, 'Служебный лист 2'!$C$3) -> 0 | L4: =COUNTIFS('Ноябрь 25 '!$C$2:C1005, H4, 'Ноябрь 25 '!$D$2:D1005, 'Служебный лист 2'!$C$4) -> 0
A5: Андреева Варвара | B5: =COUNTIF('Ноябрь 25 '!$B$2:B1005, A5) -> 0 | C5: =SUM(B51:AE51) -> 0 | D5: =COUNTIFS('Ноябрь 25 '!$B$2:B1005, A5, 'Ноябрь 25 '!$D$2:D1005, 'Служебный лист 2'!$C$2) -> 0 | E5: =COUNTIFS('Ноябрь 25 '!$B$2:B1005, A5, 'Ноябрь 25 '!$D$2:D1005, 'Служебный лист 2'!$C$3) -> 0 | F5: =COUNTIFS('Ноябрь 25 '!$B$2:B1005, A5, 'Ноябрь 25 '!$D$2:D1005, 'Служебный лист 2'!$C$4) -> 0 | H5: ОТР | I5: =COUNTIF('Ноябрь 25 '!$C$2:C1005, H5) -> 1 | J5: =COUNTIFS('Ноябрь 25 '!$C$2:C1005, H5, 'Ноябрь 25 '!$D$2:D1005, 'Служебный лист 2'!$C$2) -> 1 | K5: =COUNTIFS('Ноябрь 25 '!$C$2:C1005, H5, 'Ноябрь 25 '!$D$2:D1005, 'Служебный лист 2'!$C$3) -> 0 | L5: =COUNTIFS('Ноябрь 25 '!$C$2:C1005, H5, 'Ноябрь 25 '!$D$2:D1005, 'Служебный лист 2'!$C$4) -> 0
A6: Белов Дмитрий | B6: =COUNTIF('Ноябрь 25 '!$B$2:B1005, A6) + 12 -> 20 | C6: =SUM(B52:AE52) -> 0 | D6: =COUNTIFS('Ноябрь 25 '!$B$2:B1005, A6, 'Ноябрь 25 '!$D$2:D1005, 'Служебный лист 2'!$C$2) -> 4 | E6: =COUNTIFS('Ноябрь 25 '!$B$2:B1005, A6, 'Ноябрь 25 '!$D$2:D1005, 'Служебный лист 2'!$C$3) -> 0 | F6: =COUNTIFS('Ноябрь 25 '!$B$2:B1005, A6, 'Ноябрь 25 '!$D$2:D1005, 'Служебный лист 2'!$C$4) -> 0 | H6: ТВСтарт | I6: =COUNTIF('Ноябрь 25 '!$C$2:C1005, H6) -> 2 | J6: =COUNTIFS('Ноябрь 25 '!$C$2:C1005, H6, 'Ноябрь 25 '!$D$2:D1005, 'Служебный лист 2'!$C$2) -> 2 | K6: =COUNTIFS('Ноябрь 25 '!$C$2:C1005, H6, 'Ноябрь 25 '!$D$2:D1005, 'Служебный лист 2'!$C$3) -> 0 | L6: =COUNTIFS('Ноябрь 25 '!$C$2:C1005, H6, 'Ноябрь 25 '!$D$2:D1005, 'Служебный лист 2'!$C$4) -> 0
A7: Кузнецова Алиса | B7: =COUNTIF('Ноябрь 25 '!$B$2:B1005, A7) -> 0 | C7: =SUM(B53:AE53) -> 0 | D7: =COUNTIFS('Ноябрь 25 '!$B$2:B1005, A7, 'Ноябрь 25 '!$D$2:D1005, 'Служебный лист 2'!$C$2) -> 0 | E7: =COUNTIFS('Ноябрь 25 '!$B$2:B1005, A7, 'Ноябрь 25 '!$D$2:D1005, 'Служебный лист 2'!$C$3) -> 0 | F7: =COUNTIFS('Ноябрь 25 '!$B$2:B1005, A7, 'Ноябрь 25 '!$D$2:D1005, 'Служебный лист 2'!$C$4) -> 0 | H7: ЛигаВТБ | I7: =COUNTIF('Ноябрь 25 '!$C$2:C1005, H7) -> 0 | J7: =COUNTIFS('Ноябрь 25 '!$C$2:C1005, H7, 'Ноябрь 25 '!$D$2:D1005, 'Служебный лист 2'!$C$2) -> 0 | K7: =COUNTIFS('Ноябрь 25 '!$C$2:C1005, H7, 'Ноябрь 25 '!$D$2:D1005, 'Служебный лист 2'!$C$3) -> 0 | L7: =COUNTIFS('Ноябрь 25 '!$C$2:C1005, H7, 'Ноябрь 25 '!$D$2:D1005, 'Служебный лист 2'!$C$4) -> 0
A8: Щемелинин Владислав | B8: =COUNTIF('Ноябрь 25 '!$B$2:B1005, A8) -> 0 | C8: =SUM(B54:AE54) -> 0 | D8: =COUNTIFS('Ноябрь 25 '!$B$2:B1005, A8, 'Ноябрь 25 '!$D$2:D1005, 'Служебный лист 2'!$C$2) -> 0 | E8: =COUNTIFS('Ноябрь 25 '!$B$2:B1005, A8, 'Ноябрь 25 '!$D$2:D1005, 'Служебный лист 2'!$C$3) -> 0 | F8: =COUNTIFS('Ноябрь 25 '!$B$2:B1005, A8, 'Ноябрь 25 '!$D$2:D1005, 'Служебный лист 2'!$C$4) -> 0 | H8: РедВеб | I8: =COUNTIF('Ноябрь 25 '!$C$2:C1005, H8) -> 0 | J8: =COUNTIFS('Ноябрь 25 '!$C$2:C1005, H8, 'Ноябрь 25 '!$D$2:D1005, 'Служебный лист 2'!$C$2) -> 0 | K8: =COUNTIFS('Ноябрь 25 '!$C$2:C1005, H8, 'Ноябрь 25 '!$D$2:D1005, 'Служебный лист 2'!$C$3) -> 0 | L8: =COUNTIFS('Ноябрь 25 '!$C$2:C1005, H8, 'Ноябрь 25 '!$D$2:D1005, 'Служебный лист 2'!$C$4) -> 0
A9: Гришина Светлана | B9: =COUNTIF('Ноябрь 25 '!$B$2:B1005, A9) -1 -> 74 | C9: =SUM(B55:AE55) -> 0 | D9: =COUNTIFS('Ноябрь 25 '!$B$2:B1005, A9, 'Ноябрь 25 '!$D$2:D1005, 'Служебный лист 2'!$C$2) -> 8 | E9: =COUNTIFS('Ноябрь 25 '!$B$2:B1005, A9, 'Ноябрь 25 '!$D$2:D1005, 'Служебный лист 2'!$C$3) -> 0 | F9: =COUNTIFS('Ноябрь 25 '!$B$2:B1005, A9, 'Ноябрь 25 '!$D$2:D1005, 'Служебный лист 2'!$C$4) -> 0 | H9: Прямая речь | I9: =COUNTIF('Ноябрь 25 '!$C$2:C1005, H9) -> 0 | J9: =COUNTIFS('Ноябрь 25 '!$C$2:C1005, H9, 'Ноябрь 25 '!$D$2:D1005, 'Служебный лист 2'!$C$2) -> 0 | K9: =COUNTIFS('Ноябрь 25 '!$C$2:C1005, H9, 'Ноябрь 25 '!$D$2:D1005, 'Служебный лист 2'!$C$3) -> 0 | L9: =COUNTIFS('Ноябрь 25 '!$C$2:C1005, H9, 'Ноябрь 25 '!$D$2:D1005, 'Служебный лист 2'!$C$4) -> 0
A10: Мишина Анна | B10: =COUNTIF('Ноябрь 25 '!$B$2:B1005, A10) -> 114 | C10: =SUM(B56:AE56) -> 0 | D10: =COUNTIFS('Ноябрь 25 '!$B$2:B1005, A10, 'Ноябрь 25 '!$D$2:D1005, 'Служебный лист 2'!$C$2) -> 33 | E10: =COUNTIFS('Ноябрь 25 '!$B$2:B1005, A10, 'Ноябрь 25 '!$D$2:D1005, 'Служебный лист 2'!$C$3) -> 0 | F10: =COUNTIFS('Ноябрь 25 '!$B$2:B1005, A10, 'Ноябрь 25 '!$D$2:D1005, 'Служебный лист 2'!$C$4) -> 0 | H10: МатчТВ | I10: =COUNTIF('Ноябрь 25 '!$C$2:C1005, H10) -> 17 | J10: =COUNTIFS('Ноябрь 25 '!$C$2:C1005, H10, 'Ноябрь 25 '!$D$2:D1005, 'Служебный лист 2'!$C$2) -> 14 | K10: =COUNTIFS('Ноябрь 25 '!$C$2:C1005, H10, 'Ноябрь 25 '!$D$2:D1005, 'Служебный лист 2'!$C$3) -> 2 | L10: =COUNTIFS('Ноябрь 25 '!$C$2:C1005, H10, 'Ноябрь 25 '!$D$2:D1005, 'Служебный лист 2'!$C$4) -> 1
A11: Алексеева Александра | B11: =COUNTIF('Ноябрь 25 '!$B$2:B1005, A11) -> 0 | C11: =SUM(B57:AE57) -> 0 | D11: =COUNTIFS('Ноябрь 25 '!$B$2:B1005, A11, 'Ноябрь 25 '!$D$2:D1005, 'Служебный лист 2'!$C$2) -> 0 | E11: =COUNTIFS('Ноябрь 25 '!$B$2:B1005, A11, 'Ноябрь 25 '!$D$2:D1005, 'Служебный лист 2'!$C$3) -> 0 | F11: =COUNTIFS('Ноябрь 25 '!$B$2:B1005, A11, 'Ноябрь 25 '!$D$2:D1005, 'Служебный лист 2'!$C$4) -> 0 | H11: RDS | I11: =COUNTIF('Ноябрь 25 '!$C$2:C1005, H11) -> 0 | J11: =COUNTIFS('Ноябрь 25 '!$C$2:C1005, H11, 'Ноябрь 25 '!$D$2:D1005, 'Служебный лист 2'!$C$2) -> 0 | K11: =COUNTIFS('Ноябрь 25 '!$C$2:C1005, H11, 'Ноябрь 25 '!$D$2:D1005, 'Служебный лист 2'!$C$3) -> 0 | L11: =COUNTIFS('Ноябрь 25 '!$C$2:C1005, H11, 'Ноябрь 25 '!$D$2:D1005, 'Служебный лист 2'!$C$4) -> 0
A12: ВСЕГО | B12: =SUM(B3:B9) -> 317 | C12: =SUM(C3:C9) -> 0 | D12: =SUM(D3:D9) -> 56 | E12: =SUM(E3:E9) -> 2 | F12: =SUM(F3:F10) -> 1 | H12: Ifree | I12: =COUNTIF('Ноябрь 25 '!$C$2:C1005, H12) -> 4 | J12: =COUNTIFS('Ноябрь 25 '!$C$2:C1005, H12, 'Ноябрь 25 '!$D$2:D1005, 'Служебный лист 2'!$C$2) -> 4 | K12: =COUNTIFS('Ноябрь 25 '!$C$2:C1005, H12, 'Ноябрь 25 '!$D$2:D1005, 'Служебный лист 2'!$C$3) -> 0 | L12: =COUNTIFS('Ноябрь 25 '!$C$2:C1005, H12, 'Ноябрь 25 '!$D$2:D1005, 'Служебный лист 2'!$C$4) -> 0
H13: ЖХЛ | I13: =COUNTIF('Ноябрь 25 '!$C$2:C1005, H13) -> 0 | J13: =COUNTIFS('Ноябрь 25 '!$C$2:C1005, H13, 'Ноябрь 25 '!$D$2:D1005, 'Служебный лист 2'!$C$2) -> 0 | K13: =COUNTIFS('Ноябрь 25 '!$C$2:C1005, H13, 'Ноябрь 25 '!$D$2:D1005, 'Служебный лист 2'!$C$3) -> 0 | L13: =COUNTIFS('Ноябрь 25 '!$C$2:C1005, H13, 'Ноябрь 25 '!$D$2:D1005, 'Служебный лист 2'!$C$4) -> 0
H14: М1 | I14: =COUNTIF('Ноябрь 25 '!$C$2:C1005, H14) -> 0 | J14: =COUNTIFS('Ноябрь 25 '!$C$2:C1005, H14, 'Ноябрь 25 '!$D$2:D1005, 'Служебный лист 2'!$C$2) -> 0 | K14: =COUNTIFS('Ноябрь 25 '!$C$2:C1005, H14, 'Ноябрь 25 '!$D$2:D1005, 'Служебный лист 2'!$C$3) -> 0 | L14: =COUNTIFS('Ноябрь 25 '!$C$2:C1005, H14, 'Ноябрь 25 '!$D$2:D1005, 'Служебный лист 2'!$C$4) -> 0
H15: Кари | I15: =COUNTIF('Ноябрь 25 '!$C$2:C1005, H15) -> 0 | J15: =COUNTIFS('Ноябрь 25 '!$C$2:C1005, H15, 'Ноябрь 25 '!$D$2:D1005, 'Служебный лист 2'!$C$2) -> 0 | K15: =COUNTIFS('Ноябрь 25 '!$C$2:C1005, H15, 'Ноябрь 25 '!$D$2:D1005, 'Служебный лист 2'!$C$3) -> 0 | L15: =COUNTIFS('Ноябрь 25 '!$C$2:C1005, H15, 'Ноябрь 25 '!$D$2:D1005, 'Служебный лист 2'!$C$4) -> 0
H16: sberzvok | I16: =COUNTIF('Ноябрь 25 '!$C$2:C1005, H16) -> 0 | J16: =COUNTIFS('Ноябрь 25 '!$C$2:C1005, H16, 'Ноябрь 25 '!$D$2:D1005, 'Служебный лист 2'!$C$2) -> 0 | K16: =COUNTIFS('Ноябрь 25 '!$C$2:C1005, H16, 'Ноябрь 25 '!$D$2:D1005, 'Служебный лист 2'!$C$3) -> 0 | L16: =COUNTIFS('Ноябрь 25 '!$C$2:C1005, H16, 'Ноябрь 25 '!$D$2:D1005, 'Служебный лист 2'!$C$4) -> 0
H17: Sports | I17: =COUNTIF('Ноябрь 25 '!$C$2:C1005, H17) -> 0 | J17: =COUNTIFS('Ноябрь 25 '!$C$2:C1005, H17, 'Ноябрь 25 '!$D$2:D1005, 'Служебный лист 2'!$C$2) -> 0 | K17: =COUNTIFS('Ноябрь 25 '!$C$2:C1005, H17, 'Ноябрь 25 '!$D$2:D1005, 'Служебный лист 2'!$C$3) -> 0 | L17: =COUNTIFS('Ноябрь 25 '!$C$2:C1005, H17, 'Ноябрь 25 '!$D$2:D1005, 'Служебный лист 2'!$C$4) -> 0
A18: ='Служебный лист'!A13:A1005 -> 0 | H18: Максима | I18: =COUNTIF('Ноябрь 25 '!$C$2:C1005, H18) -> 0 | J18: =COUNTIFS('Ноябрь 25 '!$C$2:C1005, H18, 'Ноябрь 25 '!$D$2:D1005, 'Служебный лист 2'!$C$2) -> 0 | K18: =COUNTIFS('Ноябрь 25 '!$C$2:C1005, H18, 'Ноябрь 25 '!$D$2:D1005, 'Служебный лист 2'!$C$3) -> 0 | L18: =COUNTIFS('Ноябрь 25 '!$C$2:C1005, H18, 'Ноябрь 25 '!$D$2:D1005, 'Служебный лист 2'!$C$4) -> 0
A19: ='Служебный лист'!A14:A1005 -> 0 | H19: Restream | I19: =COUNTIF('Ноябрь 25 '!$C$2:C1005, H19) -> 45 | J19: =COUNTIFS('Ноябрь 25 '!$C$2:C1005, H19, 'Ноябрь 25 '!$D$2:D1005, 'Служебный лист 2'!$C$2) -> 45 | K19: =COUNTIFS('Ноябрь 25 '!$C$2:C1005, H19, 'Ноябрь 25 '!$D$2:D1005, 'Служебный лист 2'!$C$3) -> 0 | L19: =COUNTIFS('Ноябрь 25 '!$C$2:C1005, H19, 'Ноябрь 25 '!$D$2:D1005, 'Служебный лист 2'!$C$4) -> 0
C20: Количество успешно завершенных заявок | D20: =D12 -> 56 | H20: МОНИКИ | I20: =COUNTIF('Ноябрь 25 '!$C$2:C1005, H20) -> 11 | J20: =COUNTIFS('Ноябрь 25 '!$C$2:C1005, H20, 'Ноябрь 25 '!$D$2:D1005, 'Служебный лист 2'!$C$2) -> 9 | K20: =COUNTIFS('Ноябрь 25 '!$C$2:C1005, H20, 'Ноябрь 25 '!$D$2:D1005, 'Служебный лист 2'!$C$3) -> 0 | L20: =COUNTIFS('Ноябрь 25 '!$C$2:C1005, H20, 'Ноябрь 25 '!$D$2:D1005, 'Служебный лист 2'!$C$4) -> 0
A21: ='Служебный лист'!A15:A1005 -> 0 | C21: Количество заявок, переведенных в тикеты | D21: =E12 -> 2 | H21: Федерация гандбола России | I21: =COUNTIF('Ноябрь 25 '!$C$2:C1005, H21) -> 1 | J21: =COUNTIFS('Ноябрь 25 '!$C$2:C1005, H21, 'Ноябрь 25 '!$D$2:D1005, 'Служебный лист 2'!$C$2) -> 1 | K21: =COUNTIFS('Ноябрь 25 '!$C$2:C1005, H21, 'Ноябрь 25 '!$D$2:D1005, 'Служебный лист 2'!$C$3) -> 0 | L21: =COUNTIFS('Ноябрь 25 '!$C$2:C1005, H21, 'Ноябрь 25 '!$D$2:D1005, 'Служебный лист 2'!$C$4) -> 0
C22: Количество незавершенных заявок | D22: =F12 -> 1 | H22: Новый клиент | I22: =COUNTIF('Ноябрь 25 '!$C$2:C1005, H22) -> 4 | J22: =COUNTIFS('Ноябрь 25 '!$C$2:C1005, H22, 'Ноябрь 25 '!$D$2:D1005, 'Служебный лист 2'!$C$2) -> 3 | K22: =COUNTIFS('Ноябрь 25 '!$C$2:C1005, H22, 'Ноябрь 25 '!$D$2:D1005, 'Служебный лист 2'!$C$3) -> 0 | L22: =COUNTIFS('Ноябрь 25 '!$C$2:C1005, H22, 'Ноябрь 25 '!$D$2:D1005, 'Служебный лист 2'!$C$4) -> 0
H23: ВСЕГО | I23: =SUM(I3:I22) -> 95 | J23: =SUM(J3:J22) -> 89 | K23: =SUM(K3:K22) -> 2 | L23: =SUM(L2:L22) -> 1
H27: ='Служебный лист'!B19:B1005 -> 0
H28: ='Служебный лист'!B20:B1005 -> 0
H29: ='Служебный лист'!B21:B1005 -> 0
H30: ='Служебный лист'!B22:B1005 -> 0
H31: ='Служебный лист'!B23:B1005 -> 0
H32: ='Служебный лист'!B24:B1005 -> 0
H33: ='Служебный лист'!B25:B1005 -> 0
H34: ='Служебный лист'!B26:B1005 -> 0
H35: ='Служебный лист'!B27:B1005 -> 0
H36: ='Служебный лист'!B28:B1005 -> 0
H37: ='Служебный лист'!B29:B1005 -> 0
A46: Нерабочие часы штатных сотрудников

Sheet Май 25
B1: Ответственный | C1: Клиент | D1: Статус обращения | E1: Срок решения и комментарий | F1: Решение (ссылка на тикет/ссылка на документацию) | G1: Обращение клиента | H1: Время | I1: Конышев | J1: Макогонюк | K1: Удалов | L1: Шавло | M1: Соловьёв | N1: Червякова | O1: Толкачев | P1: Макаров | Q1: Курасов
A2: 45778 | B2: Алексеева Александра | H2: 9:00-10:00
B3: Алексеева Александра | H3: 10:00-11:00
B4: Алексеева Александра | H4: 11:00-12:00
B5: Червякова Ольга | H5: 12:00-13:00
B6: Червякова Ольга | H6: 13:00-14:00
B7: Тимохина Дарья | H7: 14:00-15:00
B8: Тимохина Дарья | H8: 15:00-16:00
B9: Тимохина Дарья | H9: 16:00-17:00
B10: Тимохина Дарья | H10: 17:00-18:00
B11: Толкачев Егор | H11: 18:00-19:00
B12: Толкачев Егор | H12: 19:00-20:00
B13: Толкачев Егор | H13: 20:00-21:00
B14: Червякова Ольга | H14: 21:00-22:00
B15: Червякова Ольга | H15: 22:00-23:00
A16: 45779 | B16: Алексеева Александра | H16: 9:00-10:00
B17: Алексеева Александра | H17: 10:00-11:00
B18: Алексеева Александра | H18: 11:00-12:00
B19: Алексеева Александра | H19: 12:00-13:00
B20: Алексеева Александра | H20: 13:00-14:00
B21: Червякова Ольга | H21: 14:00-15:00
B22: Червякова Ольга | H22: 15:00-16:00
B23: Червякова Ольга | H23: 16:00-17:00
B24: Толкачев Егор | H24: 17:00-18:00
B25: Толкачев Егор | H25: 18:00-19:00
B26: Толкачев Егор | H26: 19:00-20:00
B27: Червякова Ольга | H27: 20:00-21:00
B28: Червякова Ольга | H28: 21:00-22:00
B29: Червякова Ольга | H29: 22:00-23:00
A30: 45780 | B30: Алексеева Александра | H30: 9:00-10:00
B31: Алексеева Александра | H31: 10:00-11:00
B32: Алексеева Александра | H32: 11:00-12:00
B33: Червякова Ольга | H33: 12:00-13:00
B34: Червякова Ольга | H34: 13:00-14:00
B35: Червякова Ольга | H35: 14:00-15:00
B36: Червякова Ольга | H36: 15:00-16:00
B37: Червякова Ольга | H37: 16:00-17:00
B38: Червякова Ольга | H38: 17:00-18:00
B39: Толкачев Егор | H39: 18:00-19:00
B40: Толкачев Егор | H40: 19:00-20:00
B41: Толкачев Егор | H41: 20:00-21:00
B42: Червякова Ольга | H42: 21:00-22:00
B43: Червякова Ольга | H43: 22:00-23:00
A44: 45781 | B44: Алексеева Александра | H44: 9:00-10:00
B45: Алексеева Александра | H45: 10:00-11:00
B46: Алексеева Александра | H46: 11:00-12:00
B47: Червякова Ольга | H47: 12:00-13:00
B48: Червякова Ольга | H48: 13:00-14:00
B49: Червякова Ольга | H49: 14:00-15:00
B50: Червякова Ольга | H50: 15:00-16:00
B51: Тимохина Дарья | H51: 16:00-17:00
B52: Тимохина Дарья | H52: 17:00-18:00
B53: Червякова Ольга | H53: 18:00-19:00
B54: Червякова Ольга | H54: 19:00-20:00
B55: Червякова Ольга | H55: 20:00-21:00
B56: Червякова Ольга | H56: 21:00-22:00
B57: Червякова Ольга | H57: 22:00-23:00
A58: 45782 | B58: Алексеева Александра | H58: 9:00-10:00
B59: Алексеева Александра | H59: 10:00-11:00
B60: Алексеева Александра | H60: 11:00-12:00
B61: Алексеева Александра | H61: 12:00-13:00
B62: Алексеева Александра | H62: 13:00-14:00
B63: Червякова Ольга | H63: 14:00-15:00
B64: Червякова Ольга | H64: 15:00-16:00
B65: Червякова Ольга | H65: 16:00-17:00
B66: Червякова Ольга | H66: 17:00-18:00
B67: Толкачев Егор | H67: 18:00-19:00
B68: Толкачев Егор | H68: 19:00-20:00
B69: Червякова Ольга | H69: 20:00-21:00
B70: Червякова Ольга | H70: 21:00-22:00
B71: Червякова Ольга | H71: 22:00-23:00
A72: 45783 | B72: Алексеева Александра | H72: 9:00-10:00
B73: Алексеева Александра | H73: 10:00-11:00
B74: Алексеева Александра | H74: 11:00-12:00
B75: Алексеева Александра | H75: 12:00-13:00
B76: Алексеева Александра | H76: 13:00-14:00
B77: Тимохина Дарья | H77: 14:00-15:00
B78: Тимохина Дарья | H78: 15:00-16:00
B79: Тимохина Дарья | C79: Restream | D79: Завершен | E79: Эта функция пока в разработке | G79: А что по поводу опции отключения автоизменений в названии и категории при интегрированном подключении каналов (не через "другое")? | H79: 16:00-17:00
B80: Червякова Ольга | H80: 17:00-18:00
B81: Толкачев Егор | H81: 18:00-19:00
B82: Толкачев Егор | H82: 19:00-20:00
B83: Червякова Ольга | H83: 20:00-21:00
B84: Червякова Ольга | H84: 21:00-22:00
B85: Червякова Ольга | H85: 22:00-23:00
A86: 45784 | B86: Алексеева Александра | H86: 9:00-10:00
B87: Алексеева Александра | H87: 10:00-11:00
B88: Алексеева Александра | H88: 11:00-12:00
B89: Алексеева Александра | H89: 12:00-13:00
B90: Алексеева Александра | C90: Новый клиент | D90: Завершен | E90: передала Анастасии Шавло | G90: Подскажите пожалуйста, на сервисе присутствует возможность хранить ВИДИО и транслировать его, на платформу KICK и ТВИЧ без энкодеров, на примую\ | H90: 13:00-14:00
B91: Червякова Ольга | H91: 14:00-15:00
B92: Червякова Ольга | H92: 15:00-16:00
B93: Червякова Ольга | H93: 16:00-17:00
B94: Червякова Ольга | H94: 17:00-18:00
B95: Тимохина Дарья | H95: 18:00-19:00
B96: Тимохина Дарья | H96: 19:00-20:00
B97: Тимохина Дарья | H97: 20:00-21:00
B98: Червякова Ольга | H98: 21:00-22:00
B99: Червякова Ольга | H99: 22:00-23:00
A100: 45785 | B100: Червякова Ольга | H100: 9:00-10:00
...

Sheet Апрель 25
B1: Ответственный | C1: Клиент | D1: Статус обращения | E1: Срок решения и комментарий | F1: Решение (ссылка на тикет/ссылка на документацию) | G1: Обращение клиента | H1: Время | I1: Конышев | J1: Макогонюк | K1: Удалов | L1: Шавло | M1: Соловьёв | N1: Червякова | O1: Толкачев | P1: Макаров | Q1: Курасов
A2: 45748 | B2: Алексеева Александра | H2: 9:00-10:00
B3: Алексеева Александра | H3: 10:00-11:00
B4: Алексеева Александра | C4: МатчТВ | D4: Завершен | E4: Проблема решалась 2 дня | F4: https://mm.inventos.ru/inventos/pl/ts9i4wdei3gqjjwfyh4t5gnbsh | G4: Добрый день! Происходит бесконечная загрузка страницы а после отваливается по таймауту https://video.matchtv.zxz.su/client/events/1254025/edit Пытаюсь стучаться и с домашнего интернета и мобильно, с впн и без - результат один. Причем со слов коллег-удаленщиков у ни работает все нормально. Помогите решить проблему, пожалуйста | H4: 11:00-12:00
B5: Алексеева Александра | H5: 12:00-13:00
B6: Червякова Ольга | H6: 13:00-14:00
B7: Червякова Ольга | H7: 14:00-15:00
B8: Червякова Ольга | C8: Restream | D8: Завершен | G8: У меня вопрос, проблему с битрейтом решили? Можно ставить цифру побольше? Просто у меня видео транслируется в ненадлежащем качестве | H8: 15:00-16:00
B9: Червякова Ольга | H9: 16:00-17:00
B10: Червякова Ольга | C10: Restream | D10: Завершен | G10: Добрый день,не пришло подтверждение почты, исправьте пожалуйста этот момент | H10: 17:00-18:00
B11: Тимохина Дарья | H11: 18:00-19:00
B12: Тимохина Дарья | H12: 19:00-20:00
B13: Червякова Ольга | H13: 20:00-21:00
B14: Червякова Ольга | H14: 21:00-22:00
B15: Червякова Ольга | H15: 22:00-23:00
A16: 45749 | B16: Алексеева Александра | H16: 9:00-10:00
B17: Алексеева Александра | H17: 10:00-11:00
B18: Алексеева Александра | H18: 11:00-12:00
B19: Алексеева Александра | H19: 12:00-13:00
B20: Червякова Ольга | C20: МатчТВ | D20: Завершен | G20: Добрый день! Пользователю из ЛНР недоступен просмотр Матч ТВ на сайте. Ошибка - недоступно в вашем регионе. Date: Wed, 02 Apr 25 12:12:03 +0300 GeoIP country: RU GeoIP country nginx: RU GeoIP region nginx: MOW HTTP_USER_AGENT: Mozilla/5.0 (X11; Linux x86_64) AppleWebKit/537.36 (KHTML, like Gecko) Chrome/126.0.0.0 YaBrowser/24.7.0.0 Safari/537.36 REMOTE_ADDR: 5.188.121.158 HTTP_X_FORWARDED_FOR: 109.254.131.2 IP-Z: 109.254.131.2 Proxied IP: 5.188.121.158 Network Family: common Current UID/SU: / HAS FLASH: false MSE: true Впн нет Провайдер Матрикс | H20: 13:00-14:00
B21: Червякова Ольга | H21: 14:00-15:00
B22: Червякова Ольга | H22: 15:00-16:00
B23: Червякова Ольга | H23: 16:00-17:00
B24: Червякова Ольга | H24: 17:00-18:00
B25: Толкачев Егор | H25: 18:00-19:00
B26: Толкачев Егор | H26: 19:00-20:00
B27: Тимохина Дарья | H27: 20:00-21:00
B28: Червякова Ольга | H28: 21:00-22:00
B29: Червякова Ольга | H29: 22:00-23:00
A30: 45750 | B30: Алексеева Александра | C30: Restream | D30: Создан тикет | F30: https://rdm.inventos.ru/issues/156599 | G30: ребята, привет. я все понимаю, но уже полмесяца чат толком не работает на стримах. можно все-таки узнать, когда будет обновление, которое эту проблему уже решит? трансляции проводить в таких условиях не комфортно ни нам, ни зрителям. | H30: 9:00-10:00
B31: Алексеева Александра | C31: МатчТВ | D31: Завершен | E31: Леша Симаков: Яндекс не ответил вовремя на наш запрос за файлом | G31: Добрый вечер! Не получается запустить конвертацию ролика по ссылкам... | H31: 10:00-11:00
B32: Алексеева Александра | C32: МОНИКИ | D32: Завершен | E32: Инструкцию отписала клиенту | G32: Помогите подключиться к лекции | H32: 11:00-12:00
B33: Алексеева Александра | H33: 12:00-13:00
B34: Червякова Ольга | C34: МатчТВ | D34: Завершен | G34: Добрый день! У пользователя из РФ на Смарт ТВ в приложении при попытке просмотреть обзоры прошедших матчей пишет, что не поддерживается в вашем регионе. Прямой эфир показывает нормально. GeoIP country: AG GeoIP country nginx: RU GeoIP region nginx: MOW HTTP_USER_AGENT: Mozilla/5.0 (Windows NT 10.0; Win64; x64) AppleWebKit/537.36 (KHTML, like Gecko) Chrome/134.0.0.0 Safari/537.36 REMOTE_ADDR: 5.188.121.199 HTTP_X_FORWARDED_FOR: 91.108.33.227 IP-Z: 91.108.33.227 Proxied IP: 5.188.121.199 Network Family: common Current UID/SU: / HAS FLASH: false MSE: true ВПН не установлен. Провайдер: Е-Телеком, https://www.etelecom.ru/ | H34: 13:00-14:00
B35: Червякова Ольга | H35: 14:00-15:00
B36: Червякова Ольга | H36: 15:00-16:00
B37: Червякова Ольга | H37: 16:00-17:00
B38: Червякова Ольга | H38: 17:00-18:00
B39: Толкачев Егор | C39: Новый клиент | D39: Завершен | G39: добрый день, трансляция матча Локо мхк Динамо М нет звука | H39: 18:00-19:00
B40: Толкачев Егор | H40: 19:00-20:00
B41: Толкачев Егор | H41: 20:00-21:00
B42: Червякова Ольга | H42: 21:00-22:00
B43: Червякова Ольга | H43: 22:00-23:00
A44: 45751 | B44: Алексеева Александра | C44: Restream | D44: Завершен | E44: пользователь не ответил на вопросы (вк) | G44: Доброго дня. Нет ли возможности при рестриме на ютуб запускать текущую подготовленную трансляцию, а не создавать запланированную? я использую для чтения чата программу mini чат и он банально не видит этой трансляции, плюс надо постоянно после запуска теги заполнять и категорию | H44: 9:00-10:00
B45: Алексеева Александра | H45: 10:00-11:00
B46: Алексеева Александра | H46: 11:00-12:00
B47: Алексеева Александра | C47: Restream | D47: Завершен | G47: Добрый день. Можно проверить наличие проблемы ? | H47: 12:00-13:00
B48: Червякова Ольга | H48: 13:00-14:00
B49: Червякова Ольга | H49: 14:00-15:00
B50: Червякова Ольга | H50: 15:00-16:00
B51: Червякова Ольга | H51: 16:00-17:00
B52: Толкачев Егор | H52: 17:00-18:00
B53: Толкачев Егор | H53: 18:00-19:00
B54: Толкачев Егор | H54: 19:00-20:00
B55: Тимохина Дарья | H55: 20:00-21:00
B56: Червякова Ольга | H56: 21:00-22:00
B57: Червякова Ольга | H57: 22:00-23:00
A58: 45752 | B58: Червякова Ольга | H58: 9:00-10:00
B59: Червякова Ольга | H59: 10:00-11:00
B60: Червякова Ольга | H60: 11:00-12:00
B61: Червякова Ольга | H61: 12:00-13:00
B62: Червякова Ольга | H62: 13:00-14:00
B63: Червякова Ольга | H63: 14:00-15:00
B64: Червякова Ольга | H64: 15:00-16:00
B65: Червякова Ольга | H65: 16:00-17:00
B66: Червякова Ольга | H66: 17:00-18:00
B67: Толкачев Егор | H67: 18:00-19:00
B68: Толкачев Егор | H68: 19:00-20:00
B69: Червякова Ольга | H69: 20:00-21:00
B70: Червякова Ольга | H70: 21:00-22:00
B71: Червякова Ольга | H71: 22:00-23:00
A72: 45753 | B72: Червякова Ольга | H72: 9:00-10:00
B73: Червякова Ольга | H73: 10:00-11:00
B74: Червякова Ольга | H74: 11:00-12:00
B75: Червякова Ольга | H75: 12:00-13:00
B76: Червякова Ольга | H76: 13:00-14:00
B77: Тимохина Дарья | H77: 14:00-15:00
B78: Тимохина Дарья | H78: 15:00-16:00
B79: Тимохина Дарья | H79: 16:00-17:00
B80: Тимохина Дарья | C80: Restream | D80: Завершен | G80: Дратвуйте. Позвольте в ЛС? | H80: 17:00-18:00
B81: Червякова Ольга | H81: 18:00-19:00
B82: Червякова Ольга | H82: 19:00-20:00
B83: Червякова Ольга | H83: 20:00-21:00
B84: Червякова Ольга | H84: 21:00-22:00
B85: Червякова Ольга | H85: 22:00-23:00
A86: 45754 | B86: Алексеева Александра | C86: МОНИКИ | D86: Завершен | E86: Мы не отвечаем за тесты | G86: Добрый день! Пришлите, пожалуйста, ссылку на тесты На Вовлекай у меня не открывается | H86: 9:00-10:00
B87: Алексеева Александра | C87: Restream | D87: Завершен | E87: Пользователь переустановил обс | G87: Доброе утро! Вторую неделю имеются проблемы с трансляцией в телеграм - сигнал туда не доходит, хотя всё необходимое настроено | H87: 10:00-11:00
B88: Алексеева Александра | C88: Restream | D88: Завершен | E88: Передала Анастасии Шавло | G88: Здравствуйте , нам для мониторинга сотрудников нужен сервис рестриминга 12 человек в 2 смены по 6 обычный контроль за работой | H88: 11:00-12:00
B89: Алексеева Александра | C89: МатчТВ | D89: Завершен | E89: Восстановить не получилось, видео попало под очистку хранилищ | F89: https://mm.inventos.ru/inventos/pl/i4wbfueqtbg75qe47dwexzqaxo | G89: Коллеги, добрый день! Есть ли возможность как-то восстановить это видео? https://video.matchtv.ru/client/events/1158938 Написано, что оно было удалено почему-то. Мы его не удаляли | H89: 12:00-13:00
B90: Червякова Ольга | H90: 13:00-14:00
B91: Червякова Ольга | H91: 14:00-15:00
B92: Червякова Ольга | H92: 15:00-16:00
B93: Червякова Ольга | H93: 16:00-17:00
B94: Червякова Ольга | H94: 17:00-18:00
B95: Толкачев Егор | H95: 18:00-19:00
B96: Толкачев Егор | H96: 19:00-20:00
B97: Толкачев Егор | H97: 20:00-21:00
B98: Червякова Ольга | H98: 21:00-22:00
B99: Червякова Ольга | H99: 22:00-23:00
A100: 45755 | B100: Алексеева Александра | C100: Restream | D100: Завершен | E100: игнорит | G100: Привет! Не бросайте тапки, но такое дело : рестримил в твич и ВК просадки были беспощадные. Когда стримлю без рестрима и и только на, скажем, твич - то все идеально, значит не а инете дело. А еще чат не сработал, как надо… Эти беды из-за бесплатности моего тарифа или есть другие причины и просто так звезды сегодня сошлись? | H100: 9:00-10:00
...

Sheet Март 25
B1: Ответственный | C1: Клиент | D1: Статус обращения | E1: Срок решения и комментарий | F1: Решение (ссылка на тикет/ссылка на документацию) | G1: Обращение клиента | H1: Время | I1: Конышев | J1: Макогонюк | K1: Удалов | L1: Шавло | M1: Соловьёв | N1: Червякова | O1: Толкачев | P1: Макаров | Q1: Курасов
A2: 45717 | B2: Алексеева Александра | C2: КХЛ | D2: Завершен | G2: Коллеги, доброе утро. Вчера были проблемы с сигналом матча Стальные Лисы - Лада. Я загрузил на вебкастер файл этого матча. https://api-video.khl.ru/client/events/2715255/edit Загрузите его в архив | H2: 9:00-10:00
B3: Алексеева Александра | C3: ТВСтарт | D3: Завершен | F3: https://rdm.inventos.ru/issues/158063 | G3: Коллеги, доброе утро. В плеере, после завершения трансляции, в верхней части растра появлялся общий хронометрах медиа, а сейчас он пропал. Возможно ли нам его вернуть. | H3: 10:00-11:00
B4: Алексеева Александра | C4: МатчТВ | D4: Завершен | G4: Доброе утро! В приложении при открытии матча Енисей - Алания получаю ошибку на iOS и Android | H4: 11:00-12:00
B5: Червякова Ольга | H5: 12:00-13:00
B6: Червякова Ольга | C6: МатчТВ | D6: Завершен | G6: Добрый день! У пользователя ошибка при просмотре подписки Максимум Date: Sat, 01 Mar 25 13:32:17 +0300 GeoIP country: RU GeoIP country nginx: RU GeoIP region nginx: MOW HTTP_USER_AGENT: Mozilla/5.0 (Windows NT 10.0; Win64; x64) AppleWebKit/537.36 (KHTML, like Gecko) Chrome/132.0.0.0 YaBrowser/25.2.0.0 Safari/537.36 REMOTE_ADDR: 5.188.121.199 HTTP_X_FORWARDED_FOR: 147.45.126.137 IP-Z: 147.45.126.137 Proxied IP: 5.188.121.199 Network Family: common Current UID/SU: / HAS FLASH: false MSE: true ВПН - нет Провайдер Ростелеком UID W5EYAnZqE2Pit5QNt84cM9 | H6: 13:00-14:00
B7: Червякова Ольга | C7: Restream | D7: Завершен | G7: Добрый день, у меня вопрос по поводу мультичата, у меня 4 площадки вк, трово, ютуб и рутуб, вк и рутуб сообщения в чат не приходят | H7: 14:00-15:00
B8: Червякова Ольга | C8: МатчТВ | D8: Завершен | G8: У пользователя ошибка Date: Sat, 01 Mar 25 14:14:37 +0300 GeoIP country: RU GeoIP country nginx: RU GeoIP region nginx: MOW HTTP_USER_AGENT: Mozilla/5.0 (Linux; Android 10; K) AppleWebKit/537.36 (KHTML, like Gecko) Chrome/126.0.0.0 Mobile Safari/537.36 REMOTE_ADDR: 5.188.121.201 HTTP_X_FORWARDED_FOR: 31.173.84.21 IP-Z: 31.173.84.21 Proxied IP: 5.188.121.201 Network Family: common Current UID/SU: / HAS FLASH: false MSE: true ВПН - нет Провайдер МГТС UID JM1jJn6sRKk1beP2yX3u5p | H8: 15:00-16:00
B9: Соловьёв Владислав | H9: 16:00-17:00
B10: Соловьёв Владислав | H10: 17:00-18:00
B11: Соловьёв Владислав | H11: 18:00-19:00
B12: Толкачев Егор | H12: 19:00-20:00
B13: Толкачев Егор | H13: 20:00-21:00
B14: Толкачев Егор | H14: 21:00-22:00
B15: Толкачев Егор | H15: 22:00-23:00
A16: 45718 | B16: Алексеева Александра | H16: 9:00-10:00
B17: Алексеева Александра | H17: 10:00-11:00
B18: Алексеева Александра | H18: 11:00-12:00
B19: Толкачев Егор | H19: 12:00-13:00
B20: Толкачев Егор | H20: 13:00-14:00
B21: Тимохина Дарья | H21: 14:00-15:00
B22: Тимохина Дарья | H22: 15:00-16:00
B23: Тимохина Дарья | H23: 16:00-17:00
B24: Тимохина Дарья | H24: 17:00-18:00
B25: Червякова Ольга | H25: 18:00-19:00
B26: Червякова Ольга | H26: 19:00-20:00
B27: Червякова Ольга | H27: 20:00-21:00
B28: Червякова Ольга | H28: 21:00-22:00
B29: Червякова Ольга | H29: 22:00-23:00
A30: 45719 | B30: Алексеева Александра | H30: 9:00-10:00
B31: Алексеева Александра | H31: 10:00-11:00
B32: Алексеева Александра | H32: 11:00-12:00
B33: Алексеева Александра | H33: 12:00-13:00
B34: Червякова Ольга | C34: М1 | D34: Завершен | G34: Друзья, всем добрый день 🙌 Обратился клиент, утверждает, что ему не пришёл код доступа к трансляции (покупка за 89 рублей) на почту. Могли бы проверить, пожалуйста? Мейл: sashakarpov2123@gmail.com | H34: 13:00-14:00
B35: Червякова Ольга | C35: Restream | D35: Завершен | G35: здравствуйте, не идет видео и аудио на сайт, при том, что сигнал есть. Проводим тестовые эфиры, из 4х штук получается только один раз вывести изображение. В чем может быть причина?Тариф подключен платный, а провести эфир мы не можем | H35: 14:00-15:00
B36: Червякова Ольга | H36: 15:00-16:00
B37: Тимохина Дарья | H37: 16:00-17:00
B38: Тимохина Дарья | H38: 17:00-18:00
B39: Толкачев Егор | C39: МатчТВ | D39: Завершен | F39: Добавил подсеть в исключения | G39: В ДНР нет просмотра Date: Mon, 03 Mar 25 18:11:15 +0300 | H39: 18:00-19:00
B40: Толкачев Егор | C40: Новый клиент | D40: Завершен | F40: Уточнил какую именно трансляцию нужно было отправить на экспорт, так как в админке их было 2, клиент сам разобрался с проблемой | G40: Здравствуйте, надо скачать игру ЕМЛ ВТБ Уралмаш-2-Минск-М | H40: 19:00-20:00
B41: Червякова Ольга | H41: 20:00-21:00
B42: Червякова Ольга | H42: 21:00-22:00
B43: Червякова Ольга | C43: МатчТВ | D43: Завершен | G43: Добрый вечер! С вашей стороны ничего не менялось с покупками трансляций? https://api.video.matchtv.ru/admin/transactions/87712041 пытаюсь купить трансляцию, но получаю ошибку https://api.video.matchtv.ru/admin/transactions/87712041 | H43: 22:00-23:00
A44: 45720 | B44: Алексеева Александра | H44: 9:00-10:00
B45: Алексеева Александра | H45: 10:00-11:00
B46: Алексеева Александра | H46: 11:00-12:00
B47: Алексеева Александра | H47: 12:00-13:00
B48: Тимохина Дарья | H48: 13:00-14:00
B49: Тимохина Дарья | H49: 14:00-15:00
B50: Тимохина Дарья | C50: Restream | D50: Завершен | F50: Ответ: Здравствуйте! Да, есть | G50: Добрый день На вашем сервисе есть поддержка мултичатов при рестриминге? | H50: 15:00-16:00
B51: Тимохина Дарья | H51: 16:00-17:00
B52: Тимохина Дарья | H52: 17:00-18:00
B53: Червякова Ольга | H53: 18:00-19:00
B54: Червякова Ольга | H54: 19:00-20:00
B55: Червякова Ольга | H55: 20:00-21:00
B56: Червякова Ольга | H56: 21:00-22:00
B57: Червякова Ольга | H57: 22:00-23:00
A58: 45721 | B58: Алексеева Александра | H58: 9:00-10:00
B59: Алексеева Александра | H59: 10:00-11:00
B60: Алексеева Александра | H60: 11:00-12:00
B61: Алексеева Александра | H61: 12:00-13:00
B62: Алексеева Александра | C62: МОНИКИ | D62: Завершен | G62: Здравствуйте, я не смогла подключиться в 10.00 на вебинар, будет ли повторение в 15.00? Видео не могу просмотреть | H62: 13:00-14:00
B63: Алексеева Александра | H63: 14:00-15:00
B64: Алексеева Александра | H64: 15:00-16:00
B65: Алексеева Александра | H65: 16:00-17:00
B66: Алексеева Александра | H66: 17:00-18:00
B67: Червякова Ольга | C67: ТВСтарт | D67: Завершен | F67: Решением занимался l2 | G67: Добрый день. Посмотрите, пожалуйста, нет ли проблем с трансляцией партнёры говорят поток прерывается https://vtb-league.webcaster.pro/client/events/2714187 | H67: 18:00-19:00
B68: Червякова Ольга | C68: МатчТВ | D68: Завершен | F68: Двигаем трансляцию на секунду вперед или назад | G68: Здравствуйте. Коллеги, не проигрывается архив: https://video.matchtv.ru/client/events/1246973/edit | H68: 19:00-20:00
B69: Червякова Ольга | H69: 20:00-21:00
B70: Червякова Ольга | H70: 21:00-22:00
B71: Червякова Ольга | C71: Restream | D71: Завершен | G71: Почему только на restream трансляция идёт | H71: 22:00-23:00
A72: 45722 | B72: Алексеева Александра | H72: 9:00-10:00
B73: Алексеева Александра | H73: 10:00-11:00
B74: Алексеева Александра | H74: 11:00-12:00
B75: Алексеева Александра | H75: 12:00-13:00
B76: Червякова Ольга | H76: 13:00-14:00
B77: Червякова Ольга | C77: МатчТВ | D77: Завершен | E77: Данная надпись отображается при попытке поставить время завершения раньше, чем время начала трансляции Вы можете подвинуть время начала трансляции, а не останавливать её | F77: Двигаем трансляцию на секунду вперед или назад | G77: Добры день. Не получается остановить трансляцию. У не1 изменилось время, и теперь нам надо её остановить и потом снова запустить вовремя. Но при попытке остановить получаем ошибку | H77: 14:00-15:00
B78: Толкачев Егор | H78: 15:00-16:00
B79: Толкачев Егор | H79: 16:00-17:00
B80: Толкачев Егор | H80: 17:00-18:00
B81: Червякова Ольга | H81: 18:00-19:00
B82: Червякова Ольга | C82: ТВСтарт | D82: Завершен | F82: Решением занимался l2 | G82: Добрый вечер, завтра будем дартс показывать, принимаем картинку сейчас с места срт8 с ней всё плохо можете помочь разобраться в чём проблема? | H82: 19:00-20:00
B83: Червякова Ольга | H83: 20:00-21:00
B84: Червякова Ольга | H84: 21:00-22:00
B85: Червякова Ольга | H85: 22:00-23:00
A86: 45723 | B86: Алексеева Александра | H86: 9:00-10:00
B87: Алексеева Александра | H87: 10:00-11:00
B88: Алексеева Александра | H88: 11:00-12:00
B89: Алексеева Александра | H89: 12:00-13:00
B90: Червякова Ольга | H90: 13:00-14:00
B91: Червякова Ольга | C91: МатчТВ | D91: Завершен | F91: Решением занимался l2 | G91: Добрый день. подаю сигнал на ostankino62 сигнала не вижу в админке, с того же места подаю на ostankino63 сигнал и вижу в админке, канал ostankino62 рестартовал не помогает. | H91: 14:00-15:00
B92: Червякова Ольга | H92: 15:00-16:00
B93: Тимохина Дарья | H93: 16:00-17:00
B94: Тимохина Дарья | H94: 17:00-18:00
B95: Червякова Ольга | H95: 18:00-19:00
B96: Червякова Ольга | H96: 19:00-20:00
